Workbook
Name Lista_Categorias: '0_Listas_y_Apoyo'!$A$4:$A$13
Name Lista_MetodosPago: '0_Listas_y_Apoyo'!$B$4:$B$8
Name Lista_Proveedores: '0_Listas_y_Apoyo'!$C$4:$C$9
Name Lista_SKU: '2_Control_de_Stock'!$A$11:$A$210

Sheet 0_Listas_y_Apoyo
A1: PARÁMETROS Y LISTAS MAESTRAS DAMABIS | H1: TABLA DE APOYO · RANKING DE PRODUCTOS (no editar)
A3: Categorías | B3: Métodos de Pago | C3: Proveedores | D3: Estados de Stock | H3: Código/SKU | I3: Descripción | J3: Unidades Mes | K3: Ingresos Mes | L3: Ganancia Mes | M3: Índice Ranking
A4: Libros | B4: Efectivo | C4: Distribuidora Lima Papel SAC | D4: 🟢 OK | H4: =IF('2_Control_de_Stock'!$A$11="","",'2_Control_de_Stock'!$A$11) | I4: =IF('2_Control_de_Stock'!$A$11="","",'2_Control_de_Stock'!$B$11) | J4: =IF($H4="","",SUMIFS('3_Ventas_Diarias'!$E$11:$E$610,'3_Ventas_Diarias'!$C$11:$C$610,$H4,'3_Ventas_Diarias'!$A$11:$A$610,">="&'4_Dashboard_DAMABIS'!$P$5,'3_Ventas_Diarias'!$A$11:$A$610,"<="&'4_Dashboard_DAMABIS'!$P$6)) | K4: =IF($H4="","",SUMIFS('3_Ventas_Diarias'!$G$11:$G$610,'3_Ventas_Diarias'!$C$11:$C$610,$H4,'3_Ventas_Diarias'!$A$11:$A$610,">="&'4_Dashboard_DAMABIS'!$P$5,'3_Ventas_Diarias'!$A$11:$A$610,"<="&'4_Dashboard_DAMABIS'!$P$6)) | L4: =IF($H4="","",SUMIFS('3_Ventas_Diarias'!$J$11:$J$610,'3_Ventas_Diarias'!$C$11:$C$610,$H4,'3_Ventas_Diarias'!$A$11:$A$610,">="&'4_Dashboard_DAMABIS'!$P$5,'3_Ventas_Diarias'!$A$11:$A$610,"<="&'4_Dashboard_DAMABIS'!$P$6)) | M4: =IF($H4="","",N($K4)+ROW()/1000000)
A5: Papelería | B5: Tarjeta | C5: Importadora Kawaii Perú EIRL | D5: 🟡 VIGILAR | H5: =IF('2_Control_de_Stock'!$A$12="","",'2_Control_de_Stock'!$A$12) | I5: =IF('2_Control_de_Stock'!$A$12="","",'2_Control_de_Stock'!$B$12) | J5: =IF($H5="","",SUMIFS('3_Ventas_Diarias'!$E$11:$E$610,'3_Ventas_Diarias'!$C$11:$C$610,$H5,'3_Ventas_Diarias'!$A$11:$A$610,">="&'4_Dashboard_DAMABIS'!$P$5,'3_Ventas_Diarias'!$A$11:$A$610,"<="&'4_Dashboard_DAMABIS'!$P$6)) | K5: =IF($H5="","",SUMIFS('3_Ventas_Diarias'!$G$11:$G$610,'3_Ventas_Diarias'!$C$11:$C$610,$H5,'3_Ventas_Diarias'!$A$11:$A$610,">="&'4_Dashboard_DAMABIS'!$P$5,'3_Ventas_Diarias'!$A$11:$A$610,"<="&'4_Dashboard_DAMABIS'!$P$6)) | L5: =IF($H5="","",SUMIFS('3_Ventas_Diarias'!$J$11:$J$610,'3_Ventas_Diarias'!$C$11:$C$610,$H5,'3_Ventas_Diarias'!$A$11:$A$610,">="&'4_Dashboard_DAMABIS'!$P$5,'3_Ventas_Diarias'!$A$11:$A$610,"<="&'4_Dashboard_DAMABIS'!$P$6)) | M5: =IF($H5="","",N($K5)+ROW()/1000000)
A6: Arte | B6: Transferencia | C6: Editorial Andina SAC | D6: 🟠 REPONER | H6: =IF('2_Control_de_Stock'!$A$13="","",'2_Control_de_Stock'!$A$13) | I6: =IF('2_Control_de_Stock'!$A$13="","",'2_Control_de_Stock'!$B$13) | J6: =IF($H6="","",SUMIFS('3_Ventas_Diarias'!$E$11:$E$610,'3_Ventas_Diarias'!$C$11:$C$610,$H6,'3_Ventas_Diarias'!$A$11:$A$610,">="&'4_Dashboard_DAMABIS'!$P$5,'3_Ventas_Diarias'!$A$11:$A$610,"<="&'4_Dashboard_DAMABIS'!$P$6)) | K6: =IF($H6="","",SUMIFS('3_Ventas_Diarias'!$G$11:$G$610,'3_Ventas_Diarias'!$C$11:$C$610,$H6,'3_Ventas_Diarias'!$A$11:$A$610,">="&'4_Dashboard_DAMABIS'!$P$5,'3_Ventas_Diarias'!$A$11:$A$610,"<="&'4_Dashboard_DAMABIS'!$P$6)) | L6: =IF($H6="","",SUMIFS('3_Ventas_Diarias'!$J$11:$J$610,'3_Ventas_Diarias'!$C$11:$C$610,$H6,'3_Ventas_Diarias'!$A$11:$A$610,">="&'4_Dashboard_DAMABIS'!$P$5,'3_Ventas_Diarias'!$A$11:$A$610,"<="&'4_Dashboard_DAMABIS'!$P$6)) | M6: =IF($H6="","",N($K6)+ROW()/1000000)
A7: Kawaii/Escolar | B7: Yape/Plin | C7: Arte & Color Distribuciones | D7: 🔴 SIN STOCK | H7: =IF('2_Control_de_Stock'!$A$14="","",'2_Control_de_Stock'!$A$14) | I7: =IF('2_Control_de_Stock'!$A$14="","",'2_Control_de_Stock'!$B$14) | J7: =IF($H7="","",SUMIFS('3_Ventas_Diarias'!$E$11:$E$610,'3_Ventas_Diarias'!$C$11:$C$610,$H7,'3_Ventas_Diarias'!$A$11:$A$610,">="&'4_Dashboard_DAMABIS'!$P$5,'3_Ventas_Diarias'!$A$11:$A$610,"<="&'4_Dashboard_DAMABIS'!$P$6)) | K7: =IF($H7="","",SUMIFS('3_Ventas_Diarias'!$G$11:$G$610,'3_Ventas_Diarias'!$C$11:$C$610,$H7,'3_Ventas_Diarias'!$A$11:$A$610,">="&'4_Dashboard_DAMABIS'!$P$5,'3_Ventas_Diarias'!$A$11:$A$610,"<="&'4_Dashboard_DAMABIS'!$P$6)) | L7: =IF($H7="","",SUMIFS('3_Ventas_Diarias'!$J$11:$J$610,'3_Ventas_Diarias'!$C$11:$C$610,$H7,'3_Ventas_Diarias'!$A$11:$A$610,">="&'4_Dashboard_DAMABIS'!$P$5,'3_Ventas_Diarias'!$A$11:$A$610,"<="&'4_Dashboard_DAMABIS'!$P$6)) | M7: =IF($H7="","",N($K7)+ROW()/1000000)
A8: Escritura | B8: Crédito | C8: Faber Perú SA | H8: =IF('2_Control_de_Stock'!$A$15="","",'2_Control_de_Stock'!$A$15) | I8: =IF('2_Control_de_Stock'!$A$15="","",'2_Control_de_Stock'!$B$15) | J8: =IF($H8="","",SUMIFS('3_Ventas_Diarias'!$E$11:$E$610,'3_Ventas_Diarias'!$C$11:$C$610,$H8,'3_Ventas_Diarias'!$A$11:$A$610,">="&'4_Dashboard_DAMABIS'!$P$5,'3_Ventas_Diarias'!$A$11:$A$610,"<="&'4_Dashboard_DAMABIS'!$P$6)) | K8: =IF($H8="","",SUMIFS('3_Ventas_Diarias'!$G$11:$G$610,'3_Ventas_Diarias'!$C$11:$C$610,$H8,'3_Ventas_Diarias'!$A$11:$A$610,">="&'4_Dashboard_DAMABIS'!$P$5,'3_Ventas_Diarias'!$A$11:$A$610,"<="&'4_Dashboard_DAMABIS'!$P$6)) | L8: =IF($H8="","",SUMIFS('3_Ventas_Diarias'!$J$11:$J$610,'3_Ventas_Diarias'!$C$11:$C$610,$H8,'3_Ventas_Diarias'!$A$11:$A$610,">="&'4_Dashboard_DAMABIS'!$P$5,'3_Ventas_Diarias'!$A$11:$A$610,"<="&'4_Dashboard_DAMABIS'!$P$6)) | M8: =IF($H8="","",N($K8)+ROW()/1000000)
A9: Cuadernos | C9: Mayorista Mesa Redonda | H9: =IF('2_Control_de_Stock'!$A$16="","",'2_Control_de_Stock'!$A$16) | I9: =IF('2_Control_de_Stock'!$A$16="","",'2_Control_de_Stock'!$B$16) | J9: =IF($H9="","",SUMIFS('3_Ventas_Diarias'!$E$11:$E$610,'3_Ventas_Diarias'!$C$11:$C$610,$H9,'3_Ventas_Diarias'!$A$11:$A$610,">="&'4_Dashboard_DAMABIS'!$P$5,'3_Ventas_Diarias'!$A$11:$A$610,"<="&'4_Dashboard_DAMABIS'!$P$6)) | K9: =IF($H9="","",SUMIFS('3_Ventas_Diarias'!$G$11:$G$610,'3_Ventas_Diarias'!$C$11:$C$610,$H9,'3_Ventas_Diarias'!$A$11:$A$610,">="&'4_Dashboard_DAMABIS'!$P$5,'3_Ventas_Diarias'!$A$11:$A$610,"<="&'4_Dashboard_DAMABIS'!$P$6)) | L9: =IF($H9="","",SUMIFS('3_Ventas_Diarias'!$J$11:$J$610,'3_Ventas_Diarias'!$C$11:$C$610,$H9,'3_Ventas_Diarias'!$A$11:$A$610,">="&'4_Dashboard_DAMABIS'!$P$5,'3_Ventas_Diarias'!$A$11:$A$610,"<="&'4_Dashboard_DAMABIS'!$P$6)) | M9: =IF($H9="","",N($K9)+ROW()/1000000)
A10: Mochilas y Loncheras | H10: =IF('2_Control_de_Stock'!$A$17="","",'2_Control_de_Stock'!$A$17) | I10: =IF('2_Control_de_Stock'!$A$17="","",'2_Control_de_Stock'!$B$17) | J10: =IF($H10="","",SUMIFS('3_Ventas_Diarias'!$E$11:$E$610,'3_Ventas_Diarias'!$C$11:$C$610,$H10,'3_Ventas_Diarias'!$A$11:$A$610,">="&'4_Dashboard_DAMABIS'!$P$5,'3_Ventas_Diarias'!$A$11:$A$610,"<="&'4_Dashboard_DAMABIS'!$P$6)) | K10: =IF($H10="","",SUMIFS('3_Ventas_Diarias'!$G$11:$G$610,'3_Ventas_Diarias'!$C$11:$C$610,$H10,'3_Ventas_Diarias'!$A$11:$A$610,">="&'4_Dashboard_DAMABIS'!$P$5,'3_Ventas_Diarias'!$A$11:$A$610,"<="&'4_Dashboard_DAMABIS'!$P$6)) | L10: =IF($H10="","",SUMIFS('3_Ventas_Diarias'!$J$11:$J$610,'3_Ventas_Diarias'!$C$11:$C$610,$H10,'3_Ventas_Diarias'!$A$11:$A$610,">="&'4_Dashboard_DAMABIS'!$P$5,'3_Ventas_Diarias'!$A$11:$A$610,"<="&'4_Dashboard_DAMABIS'!$P$6)) | M10: =IF($H10="","",N($K10)+ROW()/1000000)
A11: Tecnología | H11: =IF('2_Control_de_Stock'!$A$18="","",'2_Control_de_Stock'!$A$18) | I11: =IF('2_Control_de_Stock'!$A$18="","",'2_Control_de_Stock'!$B$18) | J11: =IF($H11="","",SUMIFS('3_Ventas_Diarias'!$E$11:$E$610,'3_Ventas_Diarias'!$C$11:$C$610,$H11,'3_Ventas_Diarias'!$A$11:$A$610,">="&'4_Dashboard_DAMABIS'!$P$5,'3_Ventas_Diarias'!$A$11:$A$610,"<="&'4_Dashboard_DAMABIS'!$P$6)) | K11: =IF($H11="","",SUMIFS('3_Ventas_Diarias'!$G$11:$G$610,'3_Ventas_Diarias'!$C$11:$C$610,$H11,'3_Ventas_Diarias'!$A$11:$A$610,">="&'4_Dashboard_DAMABIS'!$P$5,'3_Ventas_Diarias'!$A$11:$A$610,"<="&'4_Dashboard_DAMABIS'!$P$6)) | L11: =IF($H11="","",SUMIFS('3_Ventas_Diarias'!$J$11:$J$610,'3_Ventas_Diarias'!$C$11:$C$610,$H11,'3_Ventas_Diarias'!$A$11:$A$610,">="&'4_Dashboard_DAMABIS'!$P$5,'3_Ventas_Diarias'!$A$11:$A$610,"<="&'4_Dashboard_DAMABIS'!$P$6)) | M11: =IF($H11="","",N($K11)+ROW()/1000000)
A12: Manualidades | H12: =IF('2_Control_de_Stock'!$A$19="","",'2_Control_de_Stock'!$A$19) | I12: =IF('2_Control_de_Stock'!$A$19="","",'2_Control_de_Stock'!$B$19) | J12: =IF($H12="","",SUMIFS('3_Ventas_Diarias'!$E$11:$E$610,'3_Ventas_Diarias'!$C$11:$C$610,$H12,'3_Ventas_Diarias'!$A$11:$A$610,">="&'4_Dashboard_DAMABIS'!$P$5,'3_Ventas_Diarias'!$A$11:$A$610,"<="&'4_Dashboard_DAMABIS'!$P$6)) | K12: =IF($H12="","",SUMIFS('3_Ventas_Diarias'!$G$11:$G$610,'3_Ventas_Diarias'!$C$11:$C$610,$H12,'3_Ventas_Diarias'!$A$11:$A$610,">="&'4_Dashboard_DAMABIS'!$P$5,'3_Ventas_Diarias'!$A$11:$A$610,"<="&'4_Dashboard_DAMABIS'!$P$6)) | L12: =IF($H12="","",SUMIFS('3_Ventas_Diarias'!$J$11:$J$610,'3_Ventas_Diarias'!$C$11:$C$610,$H12,'3_Ventas_Diarias'!$A$11:$A$610,">="&'4_Dashboard_DAMABIS'!$P$5,'3_Ventas_Diarias'!$A$11:$A$610,"<="&'4_Dashboard_DAMABIS'!$P$6)) | M12: =IF($H12="","",N($K12)+ROW()/1000000)
A13: Oficina | H13: =IF('2_Control_de_Stock'!$A$20="","",'2_Control_de_Stock'!$A$20) | I13: =IF('2_Control_de_Stock'!$A$20="","",'2_Control_de_Stock'!$B$20) | J13: =IF($H13="","",SUMIFS('3_Ventas_Diarias'!$E$11:$E$610,'3_Ventas_Diarias'!$C$11:$C$610,$H13,'3_Ventas_Diarias'!$A$11:$A$610,">="&'4_Dashboard_DAMABIS'!$P$5,'3_Ventas_Diarias'!$A$11:$A$610,"<="&'4_Dashboard_DAMABIS'!$P$6)) | K13: =IF($H13="","",SUMIFS('3_Ventas_Diarias'!$G$11:$G$610,'3_Ventas_Diarias'!$C$11:$C$610,$H13,'3_Ventas_Diarias'!$A$11:$A$610,">="&'4_Dashboard_DAMABIS'!$P$5,'3_Ventas_Diarias'!$A$11:$A$610,"<="&'4_Dashboard_DAMABIS'!$P$6)) | L13: =IF($H13="","",SUMIFS('3_Ventas_Diarias'!$J$11:$J$610,'3_Ventas_Diarias'!$C$11:$C$610,$H13,'3_Ventas_Diarias'!$A$11:$A$610,">="&'4_Dashboard_DAMABIS'!$P$5,'3_Ventas_Diarias'!$A$11:$A$610,"<="&'4_Dashboard_DAMABIS'!$P$6)) | M13: =IF($H13="","",N($K13)+ROW()/1000000)
H14: =IF('2_Control_de_Stock'!$A$21="","",'2_Control_de_Stock'!$A$21) | I14: =IF('2_Control_de_Stock'!$A$21="","",'2_Control_de_Stock'!$B$21) | J14: =IF($H14="","",SUMIFS('3_Ventas_Diarias'!$E$11:$E$610,'3_Ventas_Diarias'!$C$11:$C$610,$H14,'3_Ventas_Diarias'!$A$11:$A$610,">="&'4_Dashboard_DAMABIS'!$P$5,'3_Ventas_Diarias'!$A$11:$A$610,"<="&'4_Dashboard_DAMABIS'!$P$6)) | K14: =IF($H14="","",SUMIFS('3_Ventas_Diarias'!$G$11:$G$610,'3_Ventas_Diarias'!$C$11:$C$610,$H14,'3_Ventas_Diarias'!$A$11:$A$610,">="&'4_Dashboard_DAMABIS'!$P$5,'3_Ventas_Diarias'!$A$11:$A$610,"<="&'4_Dashboard_DAMABIS'!$P$6)) | L14: =IF($H14="","",SUMIFS('3_Ventas_Diarias'!$J$11:$J$610,'3_Ventas_Diarias'!$C$11:$C$610,$H14,'3_Ventas_Diarias'!$A$11:$A$610,">="&'4_Dashboard_DAMABIS'!$P$5,'3_Ventas_Diarias'!$A$11:$A$610,"<="&'4_Dashboard_DAMABIS'!$P$6)) | M14: =IF($H14="","",N($K14)+ROW()/1000000)
H15: =IF('2_Control_de_Stock'!$A$22="","",'2_Control_de_Stock'!$A$22) | I15: =IF('2_Control_de_Stock'!$A$22="","",'2_Control_de_Stock'!$B$22) | J15: =IF($H15="","",SUMIFS('3_Ventas_Diarias'!$E$11:$E$610,'3_Ventas_Diarias'!$C$11:$C$610,$H15,'3_Ventas_Diarias'!$A$11:$A$610,">="&'4_Dashboard_DAMABIS'!$P$5,'3_Ventas_Diarias'!$A$11:$A$610,"<="&'4_Dashboard_DAMABIS'!$P$6)) | K15: =IF($H15="","",SUMIFS('3_Ventas_Diarias'!$G$11:$G$610,'3_Ventas_Diarias'!$C$11:$C$610,$H15,'3_Ventas_Diarias'!$A$11:$A$610,">="&'4_Dashboard_DAMABIS'!$P$5,'3_Ventas_Diarias'!$A$11:$A$610,"<="&'4_Dashboard_DAMABIS'!$P$6)) | L15: =IF($H15="","",SUMIFS('3_Ventas_Diarias'!$J$11:$J$610,'3_Ventas_Diarias'!$C$11:$C$610,$H15,'3_Ventas_Diarias'!$A$11:$A$610,">="&'4_Dashboard_DAMABIS'!$P$5,'3_Ventas_Diarias'!$A$11:$A$610,"<="&'4_Dashboard_DAMABIS'!$P$6)) | M15: =IF($H15="","",N($K15)+ROW()/1000000)
H16: =IF('2_Control_de_Stock'!$A$23="","",'2_Control_de_Stock'!$A$23) | I16: =IF('2_Control_de_Stock'!$A$23="","",'2_Control_de_Stock'!$B$23) | J16: =IF($H16="","",SUMIFS('3_Ventas_Diarias'!$E$11:$E$610,'3_Ventas_Diarias'!$C$11:$C$610,$H16,'3_Ventas_Diarias'!$A$11:$A$610,">="&'4_Dashboard_DAMABIS'!$P$5,'3_Ventas_Diarias'!$A$11:$A$610,"<="&'4_Dashboard_DAMABIS'!$P$6)) | K16: =IF($H16="","",SUMIFS('3_Ventas_Diarias'!$G$11:$G$610,'3_Ventas_Diarias'!$C$11:$C$610,$H16,'3_Ventas_Diarias'!$A$11:$A$610,">="&'4_Dashboard_DAMABIS'!$P$5,'3_Ventas_Diarias'!$A$11:$A$610,"<="&'4_Dashboard_DAMABIS'!$P$6)) | L16: =IF($H16="","",SUMIFS('3_Ventas_Diarias'!$J$11:$J$610,'3_Ventas_Diarias'!$C$11:$C$610,$H16,'3_Ventas_Diarias'!$A$11:$A$610,">="&'4_Dashboard_DAMABIS'!$P$5,'3_Ventas_Diarias'!$A$11:$A$610,"<="&'4_Dashboard_DAMABIS'!$P$6)) | M16: =IF($H16="","",N($K16)+ROW()/1000000)
H17: =IF('2_Control_de_Stock'!$A$24="","",'2_Control_de_Stock'!$A$24) | I17: =IF('2_Control_de_Stock'!$A$24="","",'2_Control_de_Stock'!$B$24) | J17: =IF($H17="","",SUMIFS('3_Ventas_Diarias'!$E$11:$E$610,'3_Ventas_Diarias'!$C$11:$C$610,$H17,'3_Ventas_Diarias'!$A$11:$A$610,">="&'4_Dashboard_DAMABIS'!$P$5,'3_Ventas_Diarias'!$A$11:$A$610,"<="&'4_Dashboard_DAMABIS'!$P$6)) | K17: =IF($H17="","",SUMIFS('3_Ventas_Diarias'!$G$11:$G$610,'3_Ventas_Diarias'!$C$11:$C$610,$H17,'3_Ventas_Diarias'!$A$11:$A$610,">="&'4_Dashboard_DAMABIS'!$P$5,'3_Ventas_Diarias'!$A$11:$A$610,"<="&'4_Dashboard_DAMABIS'!$P$6)) | L17: =IF($H17="","",SUMIFS('3_Ventas_Diarias'!$J$11:$J$610,'3_Ventas_Diarias'!$C$11:$C$610,$H17,'3_Ventas_Diarias'!$A$11:$A$610,">="&'4_Dashboard_DAMABIS'!$P$5,'3_Ventas_Diarias'!$A$11:$A$610,"<="&'4_Dashboard_DAMABIS'!$P$6)) | M17: =IF($H17="","",N($K17)+ROW()/1000000)
H18: =IF('2_Control_de_Stock'!$A$25="","",'2_Control_de_Stock'!$A$25) | I18: =IF('2_Control_de_Stock'!$A$25="","",'2_Control_de_Stock'!$B$25) | J18: =IF($H18="","",SUMIFS('3_Ventas_Diarias'!$E$11:$E$610,'3_Ventas_Diarias'!$C$11:$C$610,$H18,'3_Ventas_Diarias'!$A$11:$A$610,">="&'4_Dashboard_DAMABIS'!$P$5,'3_Ventas_Diarias'!$A$11:$A$610,"<="&'4_Dashboard_DAMABIS'!$P$6)) | K18: =IF($H18="","",SUMIFS('3_Ventas_Diarias'!$G$11:$G$610,'3_Ventas_Diarias'!$C$11:$C$610,$H18,'3_Ventas_Diarias'!$A$11:$A$610,">="&'4_Dashboard_DAMABIS'!$P$5,'3_Ventas_Diarias'!$A$11:$A$610,"<="&'4_Dashboard_DAMABIS'!$P$6)) | L18: =IF($H18="","",SUMIFS('3_Ventas_Diarias'!$J$11:$J$610,'3_Ventas_Diarias'!$C$11:$C$610,$H18,'3_Ventas_Diarias'!$A$11:$A$610,">="&'4_Dashboard_DAMABIS'!$P$5,'3_Ventas_Diarias'!$A$11:$A$610,"<="&'4_Dashboard_DAMABIS'!$P$6)) | M18: =IF($H18="","",N($K18)+ROW()/1000000)
H19: =IF('2_Control_de_Stock'!$A$26="","",'2_Control_de_Stock'!$A$26) | I19: =IF('2_Control_de_Stock'!$A$26="","",'2_Control_de_Stock'!$B$26) | J19: =IF($H19="","",SUMIFS('3_Ventas_Diarias'!$E$11:$E$610,'3_Ventas_Diarias'!$C$11:$C$610,$H19,'3_Ventas_Diarias'!$A$11:$A$610,">="&'4_Dashboard_DAMABIS'!$P$5,'3_Ventas_Diarias'!$A$11:$A$610,"<="&'4_Dashboard_DAMABIS'!$P$6)) | K19: =IF($H19="","",SUMIFS('3_Ventas_Diarias'!$G$11:$G$610,'3_Ventas_Diarias'!$C$11:$C$610,$H19,'3_Ventas_Diarias'!$A$11:$A$610,">="&'4_Dashboard_DAMABIS'!$P$5,'3_Ventas_Diarias'!$A$11:$A$610,"<="&'4_Dashboard_DAMABIS'!$P$6)) | L19: =IF($H19="","",SUMIFS('3_Ventas_Diarias'!$J$11:$J$610,'3_Ventas_Diarias'!$C$11:$C$610,$H19,'3_Ventas_Diarias'!$A$11:$A$610,">="&'4_Dashboard_DAMABIS'!$P$5,'3_Ventas_Diarias'!$A$11:$A$610,"<="&'4_Dashboard_DAMABIS'!$P$6)) | M19: =IF($H19="","",N($K19)+ROW()/1000000)
H20: =IF('2_Control_de_Stock'!$A$27="","",'2_Control_de_Stock'!$A$27) | I20: =IF('2_Control_de_Stock'!$A$27="","",'2_Control_de_Stock'!$B$27) | J20: =IF($H20="","",SUMIFS('3_Ventas_Diarias'!$E$11:$E$610,'3_Ventas_Diarias'!$C$11:$C$610,$H20,'3_Ventas_Diarias'!$A$11:$A$610,">="&'4_Dashboard_DAMABIS'!$P$5,'3_Ventas_Diarias'!$A$11:$A$610,"<="&'4_Dashboard_DAMABIS'!$P$6)) | K20: =IF($H20="","",SUMIFS('3_Ventas_Diarias'!$G$11:$G$610,'3_Ventas_Diarias'!$C$11:$C$610,$H20,'3_Ventas_Diarias'!$A$11:$A$610,">="&'4_Dashboard_DAMABIS'!$P$5,'3_Ventas_Diarias'!$A$11:$A$610,"<="&'4_Dashboard_DAMABIS'!$P$6)) | L20: =IF($H20="","",SUMIFS('3_Ventas_Diarias'!$J$11:$J$610,'3_Ventas_Diarias'!$C$11:$C$610,$H20,'3_Ventas_Diarias'!$A$11:$A$610,">="&'4_Dashboard_DAMABIS'!$P$5,'3_Ventas_Diarias'!$A$11:$A$610,"<="&'4_Dashboard_DAMABIS'!$P$6)) | M20: =IF($H20="","",N($K20)+ROW()/1000000)
H21: =IF('2_Control_de_Stock'!$A$28="","",'2_Control_de_Stock'!$A$28) | I21: =IF('2_Control_de_Stock'!$A$28="","",'2_Control_de_Stock'!$B$28) | J21: =IF($H21="","",SUMIFS('3_Ventas_Diarias'!$E$11:$E$610,'3_Ventas_Diarias'!$C$11:$C$610,$H21,'3_Ventas_Diarias'!$A$11:$A$610,">="&'4_Dashboard_DAMABIS'!$P$5,'3_Ventas_Diarias'!$A$11:$A$610,"<="&'4_Dashboard_DAMABIS'!$P$6)) | K21: =IF($H21="","",SUMIFS('3_Ventas_Diarias'!$G$11:$G$610,'3_Ventas_Diarias'!$C$11:$C$610,$H21,'3_Ventas_Diarias'!$A$11:$A$610,">="&'4_Dashboard_DAMABIS'!$P$5,'3_Ventas_Diarias'!$A$11:$A$610,"<="&'4_Dashboard_DAMABIS'!$P$6)) | L21: =IF($H21="","",SUMIFS('3_Ventas_Diarias'!$J$11:$J$610,'3_Ventas_Diarias'!$C$11:$C$610,$H21,'3_Ventas_Diarias'!$A$11:$A$610,">="&'4_Dashboard_DAMABIS'!$P$5,'3_Ventas_Diarias'!$A$11:$A$610,"<="&'4_Dashboard_DAMABIS'!$P$6)) | M21: =IF($H21="","",N($K21)+ROW()/1000000)
H22: =IF('2_Control_de_Stock'!$A$29="","",'2_Control_de_Stock'!$A$29) | I22: =IF('2_Control_de_Stock'!$A$29="","",'2_Control_de_Stock'!$B$29) | J22: =IF($H22="","",SUMIFS('3_Ventas_Diarias'!$E$11:$E$610,'3_Ventas_Diarias'!$C$11:$C$610,$H22,'3_Ventas_Diarias'!$A$11:$A$610,">="&'4_Dashboard_DAMABIS'!$P$5,'3_Ventas_Diarias'!$A$11:$A$610,"<="&'4_Dashboard_DAMABIS'!$P$6)) | K22: =IF($H22="","",SUMIFS('3_Ventas_Diarias'!$G$11:$G$610,'3_Ventas_Diarias'!$C$11:$C$610,$H22,'3_Ventas_Diarias'!$A$11:$A$610,">="&'4_Dashboard_DAMABIS'!$P$5,'3_Ventas_Diarias'!$A$11:$A$610,"<="&'4_Dashboard_DAMABIS'!$P$6)) | L22: =IF($H22="","",SUMIFS('3_Ventas_Diarias'!$J$11:$J$610,'3_Ventas_Diarias'!$C$11:$C$610,$H22,'3_Ventas_Diarias'!$A$11:$A$610,">="&'4_Dashboard_DAMABIS'!$P$5,'3_Ventas_Diarias'!$A$11:$A$610,"<="&'4_Dashboard_DAMABIS'!$P$6)) | M22: =IF($H22="","",N($K22)+ROW()/1000000)
H23: =IF('2_Control_de_Stock'!$A$30="","",'2_Control_de_Stock'!$A$30) | I23: =IF('2_Control_de_Stock'!$A$30="","",'2_Control_de_Stock'!$B$30) | J23: =IF($H23="","",SUMIFS('3_Ventas_Diarias'!$E$11:$E$610,'3_Ventas_Diarias'!$C$11:$C$610,$H23,'3_Ventas_Diarias'!$A$11:$A$610,">="&'4_Dashboard_DAMABIS'!$P$5,'3_Ventas_Diarias'!$A$11:$A$610,"<="&'4_Dashboard_DAMABIS'!$P$6)) | K23: =IF($H23="","",SUMIFS('3_Ventas_Diarias'!$G$11:$G$610,'3_Ventas_Diarias'!$C$11:$C$610,$H23,'3_Ventas_Diarias'!$A$11:$A$610,">="&'4_Dashboard_DAMABIS'!$P$5,'3_Ventas_Diarias'!$A$11:$A$610,"<="&'4_Dashboard_DAMABIS'!$P$6)) | L23: =IF($H23="","",SUMIFS('3_Ventas_Diarias'!$J$11:$J$610,'3_Ventas_Diarias'!$C$11:$C$610,$H23,'3_Ventas_Diarias'!$A$11:$A$610,">="&'4_Dashboard_DAMABIS'!$P$5,'3_Ventas_Diarias'!$A$11:$A$610,"<="&'4_Dashboard_DAMABIS'!$P$6)) | M23: =IF($H23="","",N($K23)+ROW()/1000000)
H24: =IF('2_Control_de_Stock'!$A$31="","",'2_Control_de_Stock'!$A$31) | I24: =IF('2_Control_de_Stock'!$A$31="","",'2_Control_de_Stock'!$B$31) | J24: =IF($H24="","",SUMIFS('3_Ventas_Diarias'!$E$11:$E$610,'3_Ventas_Diarias'!$C$11:$C$610,$H24,'3_Ventas_Diarias'!$A$11:$A$610,">="&'4_Dashboard_DAMABIS'!$P$5,'3_Ventas_Diarias'!$A$11:$A$610,"<="&'4_Dashboard_DAMABIS'!$P$6)) | K24: =IF($H24="","",SUMIFS('3_Ventas_Diarias'!$G$11:$G$610,'3_Ventas_Diarias'!$C$11:$C$610,$H24,'3_Ventas_Diarias'!$A$11:$A$610,">="&'4_Dashboard_DAMABIS'!$P$5,'3_Ventas_Diarias'!$A$11:$A$610,"<="&'4_Dashboard_DAMABIS'!$P$6)) | L24: =IF($H24="","",SUMIFS('3_Ventas_Diarias'!$J$11:$J$610,'3_Ventas_Diarias'!$C$11:$C$610,$H24,'3_Ventas_Diarias'!$A$11:$A$610,">="&'4_Dashboard_DAMABIS'!$P$5,'3_Ventas_Diarias'!$A$11:$A$610,"<="&'4_Dashboard_DAMABIS'!$P$6)) | M24: =IF($H24="","",N($K24)+ROW()/1000000)
H25: =IF('2_Control_de_Stock'!$A$32="","",'2_Control_de_Stock'!$A$32) | I25: =IF('2_Control_de_Stock'!$A$32="","",'2_Control_de_Stock'!$B$32) | J25: =IF($H25="","",SUMIFS('3_Ventas_Diarias'!$E$11:$E$610,'3_Ventas_Diarias'!$C$11:$C$610,$H25,'3_Ventas_Diarias'!$A$11:$A$610,">="&'4_Dashboard_DAMABIS'!$P$5,'3_Ventas_Diarias'!$A$11:$A$610,"<="&'4_Dashboard_DAMABIS'!$P$6)) | K25: =IF($H25="","",SUMIFS('3_Ventas_Diarias'!$G$11:$G$610,'3_Ventas_Diarias'!$C$11:$C$610,$H25,'3_Ventas_Diarias'!$A$11:$A$610,">="&'4_Dashboard_DAMABIS'!$P$5,'3_Ventas_Diarias'!$A$11:$A$610,"<="&'4_Dashboard_DAMABIS'!$P$6)) | L25: =IF($H25="","",SUMIFS('3_Ventas_Diarias'!$J$11:$J$610,'3_Ventas_Diarias'!$C$11:$C$610,$H25,'3_Ventas_Diarias'!$A$11:$A$610,">="&'4_Dashboard_DAMABIS'!$P$5,'3_Ventas_Diarias'!$A$11:$A$610,"<="&'4_Dashboard_DAMABIS'!$P$6)) | M25: =IF($H25="","",N($K25)+ROW()/1000000)
H26: =IF('2_Control_de_Stock'!$A$33="","",'2_Control_de_Stock'!$A$33) | I26: =IF('2_Control_de_Stock'!$A$33="","",'2_Control_de_Stock'!$B$33) | J26: =IF($H26="","",SUMIFS('3_Ventas_Diarias'!$E$11:$E$610,'3_Ventas_Diarias'!$C$11:$C$610,$H26,'3_Ventas_Diarias'!$A$11:$A$610,">="&'4_Dashboard_DAMABIS'!$P$5,'3_Ventas_Diarias'!$A$11:$A$610,"<="&'4_Dashboard_DAMABIS'!$P$6)) | K26: =IF($H26="","",SUMIFS('3_Ventas_Diarias'!$G$11:$G$610,'3_Ventas_Diarias'!$C$11:$C$610,$H26,'3_Ventas_Diarias'!$A$11:$A$610,">="&'4_Dashboard_DAMABIS'!$P$5,'3_Ventas_Diarias'!$A$11:$A$610,"<="&'4_Dashboard_DAMABIS'!$P$6)) | L26: =IF($H26="","",SUMIFS('3_Ventas_Diarias'!$J$11:$J$610,'3_Ventas_Diarias'!$C$11:$C$610,$H26,'3_Ventas_Diarias'!$A$11:$A$610,">="&'4_Dashboard_DAMABIS'!$P$5,'3_Ventas_Diarias'!$A$11:$A$610,"<="&'4_Dashboard_DAMABIS'!$P$6)) | M26: =IF($H26="","",N($K26)+ROW()/1000000)
H27: =IF('2_Control_de_Stock'!$A$34="","",'2_Control_de_Stock'!$A$34) | I27: =IF('2_Control_de_Stock'!$A$34="","",'2_Control_de_Stock'!$B$34) | J27: =IF($H27="","",SUMIFS('3_Ventas_Diarias'!$E$11:$E$610,'3_Ventas_Diarias'!$C$11:$C$610,$H27,'3_Ventas_Diarias'!$A$11:$A$610,">="&'4_Dashboard_DAMABIS'!$P$5,'3_Ventas_Diarias'!$A$11:$A$610,"<="&'4_Dashboard_DAMABIS'!$P$6)) | K27: =IF($H27="","",SUMIFS('3_Ventas_Diarias'!$G$11:$G$610,'3_Ventas_Diarias'!$C$11:$C$610,$H27,'3_Ventas_Diarias'!$A$11:$A$610,">="&'4_Dashboard_DAMABIS'!$P$5,'3_Ventas_Diarias'!$A$11:$A$610,"<="&'4_Dashboard_DAMABIS'!$P$6)) | L27: =IF($H27="","",SUMIFS('3_Ventas_Diarias'!$J$11:$J$610,'3_Ventas_Diarias'!$C$11:$C$610,$H27,'3_Ventas_Diarias'!$A$11:$A$610,">="&'4_Dashboard_DAMABIS'!$P$5,'3_Ventas_Diarias'!$A$11:$A$610,"<="&'4_Dashboard_DAMABIS'!$P$6)) | M27: =IF($H27="","",N($K27)+ROW()/1000000)
H28: =IF('2_Control_de_Stock'!$A$35="","",'2_Control_de_Stock'!$A$35) | I28: =IF('2_Control_de_Stock'!$A$35="","",'2_Control_de_Stock'!$B$35) | J28: =IF($H28="","",SUMIFS('3_Ventas_Diarias'!$E$11:$E$610,'3_Ventas_Diarias'!$C$11:$C$610,$H28,'3_Ventas_Diarias'!$A$11:$A$610,">="&'4_Dashboard_DAMABIS'!$P$5,'3_Ventas_Diarias'!$A$11:$A$610,"<="&'4_Dashboard_DAMABIS'!$P$6)) | K28: =IF($H28="","",SUMIFS('3_Ventas_Diarias'!$G$11:$G$610,'3_Ventas_Diarias'!$C$11:$C$610,$H28,'3_Ventas_Diarias'!$A$11:$A$610,">="&'4_Dashboard_DAMABIS'!$P$5,'3_Ventas_Diarias'!$A$11:$A$610,"<="&'4_Dashboard_DAMABIS'!$P$6)) | L28: =IF($H28="","",SUMIFS('3_Ventas_Diarias'!$J$11:$J$610,'3_Ventas_Diarias'!$C$11:$C$610,$H28,'3_Ventas_Diarias'!$A$11:$A$610,">="&'4_Dashboard_DAMABIS'!$P$5,'3_Ventas_Diarias'!$A$11:$A$610,"<="&'4_Dashboard_DAMABIS'!$P$6)) | M28: =IF($H28="","",N($K28)+ROW()/1000000)
H29: =IF('2_Control_de_Stock'!$A$36="","",'2_Control_de_Stock'!$A$36) | I29: =IF('2_Control_de_Stock'!$A$36="","",'2_Control_de_Stock'!$B$36) | J29: =IF($H29="","",SUMIFS('3_Ventas_Diarias'!$E$11:$E$610,'3_Ventas_Diarias'!$C$11:$C$610,$H29,'3_Ventas_Diarias'!$A$11:$A$610,">="&'4_Dashboard_DAMABIS'!$P$5,'3_Ventas_Diarias'!$A$11:$A$610,"<="&'4_Dashboard_DAMABIS'!$P$6)) | K29: =IF($H29="","",SUMIFS('3_Ventas_Diarias'!$G$11:$G$610,'3_Ventas_Diarias'!$C$11:$C$610,$H29,'3_Ventas_Diarias'!$A$11:$A$610,">="&'4_Dashboard_DAMABIS'!$P$5,'3_Ventas_Diarias'!$A$11:$A$610,"<="&'4_Dashboard_DAMABIS'!$P$6)) | L29: =IF($H29="","",SUMIFS('3_Ventas_Diarias'!$J$11:$J$610,'3_Ventas_Diarias'!$C$11:$C$610,$H29,'3_Ventas_Diarias'!$A$11:$A$610,">="&'4_Dashboard_DAMABIS'!$P$5,'3_Ventas_Diarias'!$A$11:$A$610,"<="&'4_Dashboard_DAMABIS'!$P$6)) | M29: =IF($H29="","",N($K29)+ROW()/1000000)
H30: =IF('2_Control_de_Stock'!$A$37="","",'2_Control_de_Stock'!$A$37) | I30: =IF('2_Control_de_Stock'!$A$37="","",'2_Control_de_Stock'!$B$37) | J30: =IF($H30="","",SUMIFS('3_Ventas_Diarias'!$E$11:$E$610,'3_Ventas_Diarias'!$C$11:$C$610,$H30,'3_Ventas_Diarias'!$A$11:$A$610,">="&'4_Dashboard_DAMABIS'!$P$5,'3_Ventas_Diarias'!$A$11:$A$610,"<="&'4_Dashboard_DAMABIS'!$P$6)) | K30: =IF($H30="","",SUMIFS('3_Ventas_Diarias'!$G$11:$G$610,'3_Ventas_Diarias'!$C$11:$C$610,$H30,'3_Ventas_Diarias'!$A$11:$A$610,">="&'4_Dashboard_DAMABIS'!$P$5,'3_Ventas_Diarias'!$A$11:$A$610,"<="&'4_Dashboard_DAMABIS'!$P$6)) | L30: =IF($H30="","",SUMIFS('3_Ventas_Diarias'!$J$11:$J$610,'3_Ventas_Diarias'!$C$11:$C$610,$H30,'3_Ventas_Diarias'!$A$11:$A$610,">="&'4_Dashboard_DAMABIS'!$P$5,'3_Ventas_Diarias'!$A$11:$A$610,"<="&'4_Dashboard_DAMABIS'!$P$6)) | M30: =IF($H30="","",N($K30)+ROW()/1000000)
H31: =IF('2_Control_de_Stock'!$A$38="","",'2_Control_de_Stock'!$A$38) | I31: =IF('2_Control_de_Stock'!$A$38="","",'2_Control_de_Stock'!$B$38) | J31: =IF($H31="","",SUMIFS('3_Ventas_Diarias'!$E$11:$E$610,'3_Ventas_Diarias'!$C$11:$C$610,$H31,'3_Ventas_Diarias'!$A$11:$A$610,">="&'4_Dashboard_DAMABIS'!$P$5,'3_Ventas_Diarias'!$A$11:$A$610,"<="&'4_Dashboard_DAMABIS'!$P$6)) | K31: =IF($H31="","",SUMIFS('3_Ventas_Diarias'!$G$11:$G$610,'3_Ventas_Diarias'!$C$11:$C$610,$H31,'3_Ventas_Diarias'!$A$11:$A$610,">="&'4_Dashboard_DAMABIS'!$P$5,'3_Ventas_Diarias'!$A$11:$A$610,"<="&'4_Dashboard_DAMABIS'!$P$6)) | L31: =IF($H31="","",SUMIFS('3_Ventas_Diarias'!$J$11:$J$610,'3_Ventas_Diarias'!$C$11:$C$610,$H31,'3_Ventas_Diarias'!$A$11:$A$610,">="&'4_Dashboard_DAMABIS'!$P$5,'3_Ventas_Diarias'!$A$11:$A$610,"<="&'4_Dashboard_DAMABIS'!$P$6)) | M31: =IF($H31="","",N($K31)+ROW()/1000000)
H32: =IF('2_Control_de_Stock'!$A$39="","",'2_Control_de_Stock'!$A$39) | I32: =IF('2_Control_de_Stock'!$A$39="","",'2_Control_de_Stock'!$B$39) | J32: =IF($H32="","",SUMIFS('3_Ventas_Diarias'!$E$11:$E$610,'3_Ventas_Diarias'!$C$11:$C$610,$H32,'3_Ventas_Diarias'!$A$11:$A$610,">="&'4_Dashboard_DAMABIS'!$P$5,'3_Ventas_Diarias'!$A$11:$A$610,"<="&'4_Dashboard_DAMABIS'!$P$6)) | K32: =IF($H32="","",SUMIFS('3_Ventas_Diarias'!$G$11:$G$610,'3_Ventas_Diarias'!$C$11:$C$610,$H32,'3_Ventas_Diarias'!$A$11:$A$610,">="&'4_Dashboard_DAMABIS'!$P$5,'3_Ventas_Diarias'!$A$11:$A$610,"<="&'4_Dashboard_DAMABIS'!$P$6)) | L32: =IF($H32="","",SUMIFS('3_Ventas_Diarias'!$J$11:$J$610,'3_Ventas_Diarias'!$C$11:$C$610,$H32,'3_Ventas_Diarias'!$A$11:$A$610,">="&'4_Dashboard_DAMABIS'!$P$5,'3_Ventas_Diarias'!$A$11:$A$610,"<="&'4_Dashboard_DAMABIS'!$P$6)) | M32: =IF($H32="","",N($K32)+ROW()/1000000)
H33: =IF('2_Control_de_Stock'!$A$40="","",'2_Control_de_Stock'!$A$40) | I33: =IF('2_Control_de_Stock'!$A$40="","",'2_Control_de_Stock'!$B$40) | J33: =IF($H33="","",SUMIFS('3_Ventas_Diarias'!$E$11:$E$610,'3_Ventas_Diarias'!$C$11:$C$610,$H33,'3_Ventas_Diarias'!$A$11:$A$610,">="&'4_Dashboard_DAMABIS'!$P$5,'3_Ventas_Diarias'!$A$11:$A$610,"<="&'4_Dashboard_DAMABIS'!$P$6)) | K33: =IF($H33="","",SUMIFS('3_Ventas_Diarias'!$G$11:$G$610,'3_Ventas_Diarias'!$C$11:$C$610,$H33,'3_Ventas_Diarias'!$A$11:$A$610,">="&'4_Dashboard_DAMABIS'!$P$5,'3_Ventas_Diarias'!$A$11:$A$610,"<="&'4_Dashboard_DAMABIS'!$P$6)) | L33: =IF($H33="","",SUMIFS('3_Ventas_Diarias'!$J$11:$J$610,'3_Ventas_Diarias'!$C$11:$C$610,$H33,'3_Ventas_Diarias'!$A$11:$A$610,">="&'4_Dashboard_DAMABIS'!$P$5,'3_Ventas_Diarias'!$A$11:$A$610,"<="&'4_Dashboard_DAMABIS'!$P$6)) | M33: =IF($H33="","",N($K33)+ROW()/1000000)
H34: =IF('2_Control_de_Stock'!$A$41="","",'2_Control_de_Stock'!$A$41) | I34: =IF('2_Control_de_Stock'!$A$41="","",'2_Control_de_Stock'!$B$41) | J34: =IF($H34="","",SUMIFS('3_Ventas_Diarias'!$E$11:$E$610,'3_Ventas_Diarias'!$C$11:$C$610,$H34,'3_Ventas_Diarias'!$A$11:$A$610,">="&'4_Dashboard_DAMABIS'!$P$5,'3_Ventas_Diarias'!$A$11:$A$610,"<="&'4_Dashboard_DAMABIS'!$P$6)) | K34: =IF($H34="","",SUMIFS('3_Ventas_Diarias'!$G$11:$G$610,'3_Ventas_Diarias'!$C$11:$C$610,$H34,'3_Ventas_Diarias'!$A$11:$A$610,">="&'4_Dashboard_DAMABIS'!$P$5,'3_Ventas_Diarias'!$A$11:$A$610,"<="&'4_Dashboard_DAMABIS'!$P$6)) | L34: =IF($H34="","",SUMIFS('3_Ventas_Diarias'!$J$11:$J$610,'3_Ventas_Diarias'!$C$11:$C$610,$H34,'3_Ventas_Diarias'!$A$11:$A$610,">="&'4_Dashboard_DAMABIS'!$P$5,'3_Ventas_Diarias'!$A$11:$A$610,"<="&'4_Dashboard_DAMABIS'!$P$6)) | M34: =IF($H34="","",N($K34)+ROW()/1000000)
H35: =IF('2_Control_de_Stock'!$A$42="","",'2_Control_de_Stock'!$A$42) | I35: =IF('2_Control_de_Stock'!$A$42="","",'2_Control_de_Stock'!$B$42) | J35: =IF($H35="","",SUMIFS('3_Ventas_Diarias'!$E$11:$E$610,'3_Ventas_Diarias'!$C$11:$C$610,$H35,'3_Ventas_Diarias'!$A$11:$A$610,">="&'4_Dashboard_DAMABIS'!$P$5,'3_Ventas_Diarias'!$A$11:$A$610,"<="&'4_Dashboard_DAMABIS'!$P$6)) | K35: =IF($H35="","",SUMIFS('3_Ventas_Diarias'!$G$11:$G$610,'3_Ventas_Diarias'!$C$11:$C$610,$H35,'3_Ventas_Diarias'!$A$11:$A$610,">="&'4_Dashboard_DAMABIS'!$P$5,'3_Ventas_Diarias'!$A$11:$A$610,"<="&'4_Dashboard_DAMABIS'!$P$6)) | L35: =IF($H35="","",SUMIFS('3_Ventas_Diarias'!$J$11:$J$610,'3_Ventas_Diarias'!$C$11:$C$610,$H35,'3_Ventas_Diarias'!$A$11:$A$610,">="&'4_Dashboard_DAMABIS'!$P$5,'3_Ventas_Diarias'!$A$11:$A$610,"<="&'4_Dashboard_DAMABIS'!$P$6)) | M35: =IF($H35="","",N($K35)+ROW()/1000000)
H36: =IF('2_Control_de_Stock'!$A$43="","",'2_Control_de_Stock'!$A$43) | I36: =IF('2_Control_de_Stock'!$A$43="","",'2_Control_de_Stock'!$B$43) | J36: =IF($H36="","",SUMIFS('3_Ventas_Diarias'!$E$11:$E$610,'3_Ventas_Diarias'!$C$11:$C$610,$H36,'3_Ventas_Diarias'!$A$11:$A$610,">="&'4_Dashboard_DAMABIS'!$P$5,'3_Ventas_Diarias'!$A$11:$A$610,"<="&'4_Dashboard_DAMABIS'!$P$6)) | K36: =IF($H36="","",SUMIFS('3_Ventas_Diarias'!$G$11:$G$610,'3_Ventas_Diarias'!$C$11:$C$610,$H36,'3_Ventas_Diarias'!$A$11:$A$610,">="&'4_Dashboard_DAMABIS'!$P$5,'3_Ventas_Diarias'!$A$11:$A$610,"<="&'4_Dashboard_DAMABIS'!$P$6)) | L36: =IF($H36="","",SUMIFS('3_Ventas_Diarias'!$J$11:$J$610,'3_Ventas_Diarias'!$C$11:$C$610,$H36,'3_Ventas_Diarias'!$A$11:$A$610,">="&'4_Dashboard_DAMABIS'!$P$5,'3_Ventas_Diarias'!$A$11:$A$610,"<="&'4_Dashboard_DAMABIS'!$P$6)) | M36: =IF($H36="","",N($K36)+ROW()/1000000)
H37: =IF('2_Control_de_Stock'!$A$44="","",'2_Control_de_Stock'!$A$44) | I37: =IF('2_Control_de_Stock'!$A$44="","",'2_Control_de_Stock'!$B$44) | J37: =IF($H37="","",SUMIFS('3_Ventas_Diarias'!$E$11:$E$610,'3_Ventas_Diarias'!$C$11:$C$610,$H37,'3_Ventas_Diarias'!$A$11:$A$610,">="&'4_Dashboard_DAMABIS'!$P$5,'3_Ventas_Diarias'!$A$11:$A$610,"<="&'4_Dashboard_DAMABIS'!$P$6)) | K37: =IF($H37="","",SUMIFS('3_Ventas_Diarias'!$G$11:$G$610,'3_Ventas_Diarias'!$C$11:$C$610,$H37,'3_Ventas_Diarias'!$A$11:$A$610,">="&'4_Dashboard_DAMABIS'!$P$5,'3_Ventas_Diarias'!$A$11:$A$610,"<="&'4_Dashboard_DAMABIS'!$P$6)) | L37: =IF($H37="","",SUMIFS('3_Ventas_Diarias'!$J$11:$J$610,'3_Ventas_Diarias'!$C$11:$C$610,$H37,'3_Ventas_Diarias'!$A$11:$A$610,">="&'4_Dashboard_DAMABIS'!$P$5,'3_Ventas_Diarias'!$A$11:$A$610,"<="&'4_Dashboard_DAMABIS'!$P$6)) | M37: =IF($H37="","",N($K37)+ROW()/1000000)
H38: =IF('2_Control_de_Stock'!$A$45="","",'2_Control_de_Stock'!$A$45) | I38: =IF('2_Control_de_Stock'!$A$45="","",'2_Control_de_Stock'!$B$45) | J38: =IF($H38="","",SUMIFS('3_Ventas_Diarias'!$E$11:$E$610,'3_Ventas_Diarias'!$C$11:$C$610,$H38,'3_Ventas_Diarias'!$A$11:$A$610,">="&'4_Dashboard_DAMABIS'!$P$5,'3_Ventas_Diarias'!$A$11:$A$610,"<="&'4_Dashboard_DAMABIS'!$P$6)) | K38: =IF($H38="","",SUMIFS('3_Ventas_Diarias'!$G$11:$G$610,'3_Ventas_Diarias'!$C$11:$C$610,$H38,'3_Ventas_Diarias'!$A$11:$A$610,">="&'4_Dashboard_DAMABIS'!$P$5,'3_Ventas_Diarias'!$A$11:$A$610,"<="&'4_Dashboard_DAMABIS'!$P$6)) | L38: =IF($H38="","",SUMIFS('3_Ventas_Diarias'!$J$11:$J$610,'3_Ventas_Diarias'!$C$11:$C$610,$H38,'3_Ventas_Diarias'!$A$11:$A$610,">="&'4_Dashboard_DAMABIS'!$P$5,'3_Ventas_Diarias'!$A$11:$A$610,"<="&'4_Dashboard_DAMABIS'!$P$6)) | M38: =IF($H38="","",N($K38)+ROW()/1000000)
H39: =IF('2_Control_de_Stock'!$A$46="","",'2_Control_de_Stock'!$A$46) | I39: =IF('2_Control_de_Stock'!$A$46="","",'2_Control_de_Stock'!$B$46) | J39: =IF($H39="","",SUMIFS('3_Ventas_Diarias'!$E$11:$E$610,'3_Ventas_Diarias'!$C$11:$C$610,$H39,'3_Ventas_Diarias'!$A$11:$A$610,">="&'4_Dashboard_DAMABIS'!$P$5,'3_Ventas_Diarias'!$A$11:$A$610,"<="&'4_Dashboard_DAMABIS'!$P$6)) | K39: =IF($H39="","",SUMIFS('3_Ventas_Diarias'!$G$11:$G$610,'3_Ventas_Diarias'!$C$11:$C$610,$H39,'3_Ventas_Diarias'!$A$11:$A$610,">="&'4_Dashboard_DAMABIS'!$P$5,'3_Ventas_Diarias'!$A$11:$A$610,"<="&'4_Dashboard_DAMABIS'!$P$6)) | L39: =IF($H39="","",SUMIFS('3_Ventas_Diarias'!$J$11:$J$610,'3_Ventas_Diarias'!$C$11:$C$610,$H39,'3_Ventas_Diarias'!$A$11:$A$610,">="&'4_Dashboard_DAMABIS'!$P$5,'3_Ventas_Diarias'!$A$11:$A$610,"<="&'4_Dashboard_DAMABIS'!$P$6)) | M39: =IF($H39="","",N($K39)+ROW()/1000000)
H40: =IF('2_Control_de_Stock'!$A$47="","",'2_Control_de_Stock'!$A$47) | I40: =IF('2_Control_de_Stock'!$A$47="","",'2_Control_de_Stock'!$B$47) | J40: =IF($H40="","",SUMIFS('3_Ventas_Diarias'!$E$11:$E$610,'3_Ventas_Diarias'!$C$11:$C$610,$H40,'3_Ventas_Diarias'!$A$11:$A$610,">="&'4_Dashboard_DAMABIS'!$P$5,'3_Ventas_Diarias'!$A$11:$A$610,"<="&'4_Dashboard_DAMABIS'!$P$6)) | K40: =IF($H40="","",SUMIFS('3_Ventas_Diarias'!$G$11:$G$610,'3_Ventas_Diarias'!$C$11:$C$610,$H40,'3_Ventas_Diarias'!$A$11:$A$610,">="&'4_Dashboard_DAMABIS'!$P$5,'3_Ventas_Diarias'!$A$11:$A$610,"<="&'4_Dashboard_DAMABIS'!$P$6)) | L40: =IF($H40="","",SUMIFS('3_Ventas_Diarias'!$J$11:$J$610,'3_Ventas_Diarias'!$C$11:$C$610,$H40,'3_Ventas_Diarias'!$A$11:$A$610,">="&'4_Dashboard_DAMABIS'!$P$5,'3_Ventas_Diarias'!$A$11:$A$610,"<="&'4_Dashboard_DAMABIS'!$P$6)) | M40: =IF($H40="","",N($K40)+ROW()/1000000)
H41: =IF('2_Control_de_Stock'!$A$48="","",'2_Control_de_Stock'!$A$48) | I41: =IF('2_Control_de_Stock'!$A$48="","",'2_Control_de_Stock'!$B$48) | J41: =IF($H41="","",SUMIFS('3_Ventas_Diarias'!$E$11:$E$610,'3_Ventas_Diarias'!$C$11:$C$610,$H41,'3_Ventas_Diarias'!$A$11:$A$610,">="&'4_Dashboard_DAMABIS'!$P$5,'3_Ventas_Diarias'!$A$11:$A$610,"<="&'4_Dashboard_DAMABIS'!$P$6)) | K41: =IF($H41="","",SUMIFS('3_Ventas_Diarias'!$G$11:$G$610,'3_Ventas_Diarias'!$C$11:$C$610,$H41,'3_Ventas_Diarias'!$A$11:$A$610,">="&'4_Dashboard_DAMABIS'!$P$5,'3_Ventas_Diarias'!$A$11:$A$610,"<="&'4_Dashboard_DAMABIS'!$P$6)) | L41: =IF($H41="","",SUMIFS('3_Ventas_Diarias'!$J$11:$J$610,'3_Ventas_Diarias'!$C$11:$C$610,$H41,'3_Ventas_Diarias'!$A$11:$A$610,">="&'4_Dashboard_DAMABIS'!$P$5,'3_Ventas_Diarias'!$A$11:$A$610,"<="&'4_Dashboard_DAMABIS'!$P$6)) | M41: =IF($H41="","",N($K41)+ROW()/1000000)
H42: =IF('2_Control_de_Stock'!$A$49="","",'2_Control_de_Stock'!$A$49) | I42: =IF('2_Control_de_Stock'!$A$49="","",'2_Control_de_Stock'!$B$49) | J42: =IF($H42="","",SUMIFS('3_Ventas_Diarias'!$E$11:$E$610,'3_Ventas_Diarias'!$C$11:$C$610,$H42,'3_Ventas_Diarias'!$A$11:$A$610,">="&'4_Dashboard_DAMABIS'!$P$5,'3_Ventas_Diarias'!$A$11:$A$610,"<="&'4_Dashboard_DAMABIS'!$P$6)) | K42: =IF($H42="","",SUMIFS('3_Ventas_Diarias'!$G$11:$G$610,'3_Ventas_Diarias'!$C$11:$C$610,$H42,'3_Ventas_Diarias'!$A$11:$A$610,">="&'4_Dashboard_DAMABIS'!$P$5,'3_Ventas_Diarias'!$A$11:$A$610,"<="&'4_Dashboard_DAMABIS'!$P$6)) | L42: =IF($H42="","",SUMIFS('3_Ventas_Diarias'!$J$11:$J$610,'3_Ventas_Diarias'!$C$11:$C$610,$H42,'3_Ventas_Diarias'!$A$11:$A$610,">="&'4_Dashboard_DAMABIS'!$P$5,'3_Ventas_Diarias'!$A$11:$A$610,"<="&'4_Dashboard_DAMABIS'!$P$6)) | M42: =IF($H42="","",N($K42)+ROW()/1000000)
H43: =IF('2_Control_de_Stock'!$A$50="","",'2_Control_de_Stock'!$A$50) | I43: =IF('2_Control_de_Stock'!$A$50="","",'2_Control_de_Stock'!$B$50) | J43: =IF($H43="","",SUMIFS('3_Ventas_Diarias'!$E$11:$E$610,'3_Ventas_Diarias'!$C$11:$C$610,$H43,'3_Ventas_Diarias'!$A$11:$A$610,">="&'4_Dashboard_DAMABIS'!$P$5,'3_Ventas_Diarias'!$A$11:$A$610,"<="&'4_Dashboard_DAMABIS'!$P$6)) | K43: =IF($H43="","",SUMIFS('3_Ventas_Diarias'!$G$11:$G$610,'3_Ventas_Diarias'!$C$11:$C$610,$H43,'3_Ventas_Diarias'!$A$11:$A$610,">="&'4_Dashboard_DAMABIS'!$P$5,'3_Ventas_Diarias'!$A$11:$A$610,"<="&'4_Dashboard_DAMABIS'!$P$6)) | L43: =IF($H43="","",SUMIFS('3_Ventas_Diarias'!$J$11:$J$610,'3_Ventas_Diarias'!$C$11:$C$610,$H43,'3_Ventas_Diarias'!$A$11:$A$610,">="&'4_Dashboard_DAMABIS'!$P$5,'3_Ventas_Diarias'!$A$11:$A$610,"<="&'4_Dashboard_DAMABIS'!$P$6)) | M43: =IF($H43="","",N($K43)+ROW()/1000000)
H44: =IF('2_Control_de_Stock'!$A$51="","",'2_Control_de_Stock'!$A$51) | I44: =IF('2_Control_de_Stock'!$A$51="","",'2_Control_de_Stock'!$B$51) | J44: =IF($H44="","",SUMIFS('3_Ventas_Diarias'!$E$11:$E$610,'3_Ventas_Diarias'!$C$11:$C$610,$H44,'3_Ventas_Diarias'!$A$11:$A$610,">="&'4_Dashboard_DAMABIS'!$P$5,'3_Ventas_Diarias'!$A$11:$A$610,"<="&'4_Dashboard_DAMABIS'!$P$6)) | K44: =IF($H44="","",SUMIFS('3_Ventas_Diarias'!$G$11:$G$610,'3_Ventas_Diarias'!$C$11:$C$610,$H44,'3_Ventas_Diarias'!$A$11:$A$610,">="&'4_Dashboard_DAMABIS'!$P$5,'3_Ventas_Diarias'!$A$11:$A$610,"<="&'4_Dashboard_DAMABIS'!$P$6)) | L44: =IF($H44="","",SUMIFS('3_Ventas_Diarias'!$J$11:$J$610,'3_Ventas_Diarias'!$C$11:$C$610,$H44,'3_Ventas_Diarias'!$A$11:$A$610,">="&'4_Dashboard_DAMABIS'!$P$5,'3_Ventas_Diarias'!$A$11:$A$610,"<="&'4_Dashboard_DAMABIS'!$P$6)) | M44: =IF($H44="","",N($K44)+ROW()/1000000)
H45: =IF('2_Control_de_Stock'!$A$52="","",'2_Control_de_Stock'!$A$52) | I45: =IF('2_Control_de_Stock'!$A$52="","",'2_Control_de_Stock'!$B$52) | J45: =IF($H45="","",SUMIFS('3_Ventas_Diarias'!$E$11:$E$610,'3_Ventas_Diarias'!$C$11:$C$610,$H45,'3_Ventas_Diarias'!$A$11:$A$610,">="&'4_Dashboard_DAMABIS'!$P$5,'3_Ventas_Diarias'!$A$11:$A$610,"<="&'4_Dashboard_DAMABIS'!$P$6)) | K45: =IF($H45="","",SUMIFS('3_Ventas_Diarias'!$G$11:$G$610,'3_Ventas_Diarias'!$C$11:$C$610,$H45,'3_Ventas_Diarias'!$A$11:$A$610,">="&'4_Dashboard_DAMABIS'!$P$5,'3_Ventas_Diarias'!$A$11:$A$610,"<="&'4_Dashboard_DAMABIS'!$P$6)) | L45: =IF($H45="","",SUMIFS('3_Ventas_Diarias'!$J$11:$J$610,'3_Ventas_Diarias'!$C$11:$C$610,$H45,'3_Ventas_Diarias'!$A$11:$A$610,">="&'4_Dashboard_DAMABIS'!$P$5,'3_Ventas_Diarias'!$A$11:$A$610,"<="&'4_Dashboard_DAMABIS'!$P$6)) | M45: =IF($H45="","",N($K45)+ROW()/1000000)
H46: =IF('2_Control_de_Stock'!$A$53="","",'2_Control_de_Stock'!$A$53) | I46: =IF('2_Control_de_Stock'!$A$53="","",'2_Control_de_Stock'!$B$53) | J46: =IF($H46="","",SUMIFS('3_Ventas_Diarias'!$E$11:$E$610,'3_Ventas_Diarias'!$C$11:$C$610,$H46,'3_Ventas_Diarias'!$A$11:$A$610,">="&'4_Dashboard_DAMABIS'!$P$5,'3_Ventas_Diarias'!$A$11:$A$610,"<="&'4_Dashboard_DAMABIS'!$P$6)) | K46: =IF($H46="","",SUMIFS('3_Ventas_Diarias'!$G$11:$G$610,'3_Ventas_Diarias'!$C$11:$C$610,$H46,'3_Ventas_Diarias'!$A$11:$A$610,">="&'4_Dashboard_DAMABIS'!$P$5,'3_Ventas_Diarias'!$A$11:$A$610,"<="&'4_Dashboard_DAMABIS'!$P$6)) | L46: =IF($H46="","",SUMIFS('3_Ventas_Diarias'!$J$11:$J$610,'3_Ventas_Diarias'!$C$11:$C$610,$H46,'3_Ventas_Diarias'!$A$11:$A$610,">="&'4_Dashboard_DAMABIS'!$P$5,'3_Ventas_Diarias'!$A$11:$A$610,"<="&'4_Dashboard_DAMABIS'!$P$6)) | M46: =IF($H46="","",N($K46)+ROW()/1000000)
H47: =IF('2_Control_de_Stock'!$A$54="","",'2_Control_de_Stock'!$A$54) | I47: =IF('2_Control_de_Stock'!$A$54="","",'2_Control_de_Stock'!$B$54) | J47: =IF($H47="","",SUMIFS('3_Ventas_Diarias'!$E$11:$E$610,'3_Ventas_Diarias'!$C$11:$C$610,$H47,'3_Ventas_Diarias'!$A$11:$A$610,">="&'4_Dashboard_DAMABIS'!$P$5,'3_Ventas_Diarias'!$A$11:$A$610,"<="&'4_Dashboard_DAMABIS'!$P$6)) | K47: =IF($H47="","",SUMIFS('3_Ventas_Diarias'!$G$11:$G$610,'3_Ventas_Diarias'!$C$11:$C$610,$H47,'3_Ventas_Diarias'!$A$11:$A$610,">="&'4_Dashboard_DAMABIS'!$P$5,'3_Ventas_Diarias'!$A$11:$A$610,"<="&'4_Dashboard_DAMABIS'!$P$6)) | L47: =IF($H47="","",SUMIFS('3_Ventas_Diarias'!$J$11:$J$610,'3_Ventas_Diarias'!$C$11:$C$610,$H47,'3_Ventas_Diarias'!$A$11:$A$610,">="&'4_Dashboard_DAMABIS'!$P$5,'3_Ventas_Diarias'!$A$11:$A$610,"<="&'4_Dashboard_DAMABIS'!$P$6)) | M47: =IF($H47="","",N($K47)+ROW()/1000000)
H48: =IF('2_Control_de_Stock'!$A$55="","",'2_Control_de_Stock'!$A$55) | I48: =IF('2_Control_de_Stock'!$A$55="","",'2_Control_de_Stock'!$B$55) | J48: =IF($H48="","",SUMIFS('3_Ventas_Diarias'!$E$11:$E$610,'3_Ventas_Diarias'!$C$11:$C$610,$H48,'3_Ventas_Diarias'!$A$11:$A$610,">="&'4_Dashboard_DAMABIS'!$P$5,'3_Ventas_Diarias'!$A$11:$A$610,"<="&'4_Dashboard_DAMABIS'!$P$6)) | K48: =IF($H48="","",SUMIFS('3_Ventas_Diarias'!$G$11:$G$610,'3_Ventas_Diarias'!$C$11:$C$610,$H48,'3_Ventas_Diarias'!$A$11:$A$610,">="&'4_Dashboard_DAMABIS'!$P$5,'3_Ventas_Diarias'!$A$11:$A$610,"<="&'4_Dashboard_DAMABIS'!$P$6)) | L48: =IF($H48="","",SUMIFS('3_Ventas_Diarias'!$J$11:$J$610,'3_Ventas_Diarias'!$C$11:$C$610,$H48,'3_Ventas_Diarias'!$A$11:$A$610,">="&'4_Dashboard_DAMABIS'!$P$5,'3_Ventas_Diarias'!$A$11:$A$610,"<="&'4_Dashboard_DAMABIS'!$P$6)) | M48: =IF($H48="","",N($K48)+ROW()/1000000)
H49: =IF('2_Control_de_Stock'!$A$56="","",'2_Control_de_Stock'!$A$56) | I49: =IF('2_Control_de_Stock'!$A$56="","",'2_Control_de_Stock'!$B$56) | J49: =IF($H49="","",SUMIFS('3_Ventas_Diarias'!$E$11:$E$610,'3_Ventas_Diarias'!$C$11:$C$610,$H49,'3_Ventas_Diarias'!$A$11:$A$610,">="&'4_Dashboard_DAMABIS'!$P$5,'3_Ventas_Diarias'!$A$11:$A$610,"<="&'4_Dashboard_DAMABIS'!$P$6)) | K49: =IF($H49="","",SUMIFS('3_Ventas_Diarias'!$G$11:$G$610,'3_Ventas_Diarias'!$C$11:$C$610,$H49,'3_Ventas_Diarias'!$A$11:$A$610,">="&'4_Dashboard_DAMABIS'!$P$5,'3_Ventas_Diarias'!$A$11:$A$610,"<="&'4_Dashboard_DAMABIS'!$P$6)) | L49: =IF($H49="","",SUMIFS('3_Ventas_Diarias'!$J$11:$J$610,'3_Ventas_Diarias'!$C$11:$C$610,$H49,'3_Ventas_Diarias'!$A$11:$A$610,">="&'4_Dashboard_DAMABIS'!$P$5,'3_Ventas_Diarias'!$A$11:$A$610,"<="&'4_Dashboard_DAMABIS'!$P$6)) | M49: =IF($H49="","",N($K49)+ROW()/1000000)
H50: =IF('2_Control_de_Stock'!$A$57="","",'2_Control_de_Stock'!$A$57) | I50: =IF('2_Control_de_Stock'!$A$57="","",'2_Control_de_Stock'!$B$57) | J50: =IF($H50="","",SUMIFS('3_Ventas_Diarias'!$E$11:$E$610,'3_Ventas_Diarias'!$C$11:$C$610,$H50,'3_Ventas_Diarias'!$A$11:$A$610,">="&'4_Dashboard_DAMABIS'!$P$5,'3_Ventas_Diarias'!$A$11:$A$610,"<="&'4_Dashboard_DAMABIS'!$P$6)) | K50: =IF($H50="","",SUMIFS('3_Ventas_Diarias'!$G$11:$G$610,'3_Ventas_Diarias'!$C$11:$C$610,$H50,'3_Ventas_Diarias'!$A$11:$A$610,">="&'4_Dashboard_DAMABIS'!$P$5,'3_Ventas_Diarias'!$A$11:$A$610,"<="&'4_Dashboard_DAMABIS'!$P$6)) | L50: =IF($H50="","",SUMIFS('3_Ventas_Diarias'!$J$11:$J$610,'3_Ventas_Diarias'!$C$11:$C$610,$H50,'3_Ventas_Diarias'!$A$11:$A$610,">="&'4_Dashboard_DAMABIS'!$P$5,'3_Ventas_Diarias'!$A$11:$A$610,"<="&'4_Dashboard_DAMABIS'!$P$6)) | M50: =IF($H50="","",N($K50)+ROW()/1000000)
H51: =IF('2_Control_de_Stock'!$A$58="","",'2_Control_de_Stock'!$A$58) | I51: =IF('2_Control_de_Stock'!$A$58="","",'2_Control_de_Stock'!$B$58) | J51: =IF($H51="","",SUMIFS('3_Ventas_Diarias'!$E$11:$E$610,'3_Ventas_Diarias'!$C$11:$C$610,$H51,'3_Ventas_Diarias'!$A$11:$A$610,">="&'4_Dashboard_DAMABIS'!$P$5,'3_Ventas_Diarias'!$A$11:$A$610,"<="&'4_Dashboard_DAMABIS'!$P$6)) | K51: =IF($H51="","",SUMIFS('3_Ventas_Diarias'!$G$11:$G$610,'3_Ventas_Diarias'!$C$11:$C$610,$H51,'3_Ventas_Diarias'!$A$11:$A$610,">="&'4_Dashboard_DAMABIS'!$P$5,'3_Ventas_Diarias'!$A$11:$A$610,"<="&'4_Dashboard_DAMABIS'!$P$6)) | L51: =IF($H51="","",SUMIFS('3_Ventas_Diarias'!$J$11:$J$610,'3_Ventas_Diarias'!$C$11:$C$610,$H51,'3_Ventas_Diarias'!$A$11:$A$610,">="&'4_Dashboard_DAMABIS'!$P$5,'3_Ventas_Diarias'!$A$11:$A$610,"<="&'4_Dashboard_DAMABIS'!$P$6)) | M51: =IF($H51="","",N($K51)+ROW()/1000000)
H52: =IF('2_Control_de_Stock'!$A$59="","",'2_Control_de_Stock'!$A$59) | I52: =IF('2_Control_de_Stock'!$A$59="","",'2_Control_de_Stock'!$B$59) | J52: =IF($H52="","",SUMIFS('3_Ventas_Diarias'!$E$11:$E$610,'3_Ventas_Diarias'!$C$11:$C$610,$H52,'3_Ventas_Diarias'!$A$11:$A$610,">="&'4_Dashboard_DAMABIS'!$P$5,'3_Ventas_Diarias'!$A$11:$A$610,"<="&'4_Dashboard_DAMABIS'!$P$6)) | K52: =IF($H52="","",SUMIFS('3_Ventas_Diarias'!$G$11:$G$610,'3_Ventas_Diarias'!$C$11:$C$610,$H52,'3_Ventas_Diarias'!$A$11:$A$610,">="&'4_Dashboard_DAMABIS'!$P$5,'3_Ventas_Diarias'!$A$11:$A$610,"<="&'4_Dashboard_DAMABIS'!$P$6)) | L52: =IF($H52="","",SUMIFS('3_Ventas_Diarias'!$J$11:$J$610,'3_Ventas_Diarias'!$C$11:$C$610,$H52,'3_Ventas_Diarias'!$A$11:$A$610,">="&'4_Dashboard_DAMABIS'!$P$5,'3_Ventas_Diarias'!$A$11:$A$610,"<="&'4_Dashboard_DAMABIS'!$P$6)) | M52: =IF($H52="","",N($K52)+ROW()/1000000)
H53: =IF('2_Control_de_Stock'!$A$60="","",'2_Control_de_Stock'!$A$60) | I53: =IF('2_Control_de_Stock'!$A$60="","",'2_Control_de_Stock'!$B$60) | J53: =IF($H53="","",SUMIFS('3_Ventas_Diarias'!$E$11:$E$610,'3_Ventas_Diarias'!$C$11:$C$610,$H53,'3_Ventas_Diarias'!$A$11:$A$610,">="&'4_Dashboard_DAMABIS'!$P$5,'3_Ventas_Diarias'!$A$11:$A$610,"<="&'4_Dashboard_DAMABIS'!$P$6)) | K53: =IF($H53="","",SUMIFS('3_Ventas_Diarias'!$G$11:$G$610,'3_Ventas_Diarias'!$C$11:$C$610,$H53,'3_Ventas_Diarias'!$A$11:$A$610,">="&'4_Dashboard_DAMABIS'!$P$5,'3_Ventas_Diarias'!$A$11:$A$610,"<="&'4_Dashboard_DAMABIS'!$P$6)) | L53: =IF($H53="","",SUMIFS('3_Ventas_Diarias'!$J$11:$J$610,'3_Ventas_Diarias'!$C$11:$C$610,$H53,'3_Ventas_Diarias'!$A$11:$A$610,">="&'4_Dashboard_DAMABIS'!$P$5,'3_Ventas_Diarias'!$A$11:$A$610,"<="&'4_Dashboard_DAMABIS'!$P$6)) | M53: =IF($H53="","",N($K53)+ROW()/1000000)
H54: =IF('2_Control_de_Stock'!$A$61="","",'2_Control_de_Stock'!$A$61) | I54: =IF('2_Control_de_Stock'!$A$61="","",'2_Control_de_Stock'!$B$61) | J54: =IF($H54="","",SUMIFS('3_Ventas_Diarias'!$E$11:$E$610,'3_Ventas_Diarias'!$C$11:$C$610,$H54,'3_Ventas_Diarias'!$A$11:$A$610,">="&'4_Dashboard_DAMABIS'!$P$5,'3_Ventas_Diarias'!$A$11:$A$610,"<="&'4_Dashboard_DAMABIS'!$P$6)) | K54: =IF($H54="","",SUMIFS('3_Ventas_Diarias'!$G$11:$G$610,'3_Ventas_Diarias'!$C$11:$C$610,$H54,'3_Ventas_Diarias'!$A$11:$A$610,">="&'4_Dashboard_DAMABIS'!$P$5,'3_Ventas_Diarias'!$A$11:$A$610,"<="&'4_Dashboard_DAMABIS'!$P$6)) | L54: =IF($H54="","",SUMIFS('3_Ventas_Diarias'!$J$11:$J$610,'3_Ventas_Diarias'!$C$11:$C$610,$H54,'3_Ventas_Diarias'!$A$11:$A$610,">="&'4_Dashboard_DAMABIS'!$P$5,'3_Ventas_Diarias'!$A$11:$A$610,"<="&'4_Dashboard_DAMABIS'!$P$6)) | M54: =IF($H54="","",N($K54)+ROW()/1000000)
H55: =IF('2_Control_de_Stock'!$A$62="","",'2_Control_de_Stock'!$A$62) | I55: =IF('2_Control_de_Stock'!$A$62="","",'2_Control_de_Stock'!$B$62) | J55: =IF($H55="","",SUMIFS('3_Ventas_Diarias'!$E$11:$E$610,'3_Ventas_Diarias'!$C$11:$C$610,$H55,'3_Ventas_Diarias'!$A$11:$A$610,">="&'4_Dashboard_DAMABIS'!$P$5,'3_Ventas_Diarias'!$A$11:$A$610,"<="&'4_Dashboard_DAMABIS'!$P$6)) | K55: =IF($H55="","",SUMIFS('3_Ventas_Diarias'!$G$11:$G$610,'3_Ventas_Diarias'!$C$11:$C$610,$H55,'3_Ventas_Diarias'!$A$11:$A$610,">="&'4_Dashboard_DAMABIS'!$P$5,'3_Ventas_Diarias'!$A$11:$A$610,"<="&'4_Dashboard_DAMABIS'!$P$6)) | L55: =IF($H55="","",SUMIFS('3_Ventas_Diarias'!$J$11:$J$610,'3_Ventas_Diarias'!$C$11:$C$610,$H55,'3_Ventas_Diarias'!$A$11:$A$610,">="&'4_Dashboard_DAMABIS'!$P$5,'3_Ventas_Diarias'!$A$11:$A$610,"<="&'4_Dashboard_DAMABIS'!$P$6)) | M55: =IF($H55="","",N($K55)+ROW()/1000000)
H56: =IF('2_Control_de_Stock'!$A$63="","",'2_Control_de_Stock'!$A$63) | I56: =IF('2_Control_de_Stock'!$A$63="","",'2_Control_de_Stock'!$B$63) | J56: =IF($H56="","",SUMIFS('3_Ventas_Diarias'!$E$11:$E$610,'3_Ventas_Diarias'!$C$11:$C$610,$H56,'3_Ventas_Diarias'!$A$11:$A$610,">="&'4_Dashboard_DAMABIS'!$P$5,'3_Ventas_Diarias'!$A$11:$A$610,"<="&'4_Dashboard_DAMABIS'!$P$6)) | K56: =IF($H56="","",SUMIFS('3_Ventas_Diarias'!$G$11:$G$610,'3_Ventas_Diarias'!$C$11:$C$610,$H56,'3_Ventas_Diarias'!$A$11:$A$610,">="&'4_Dashboard_DAMABIS'!$P$5,'3_Ventas_Diarias'!$A$11:$A$610,"<="&'4_Dashboard_DAMABIS'!$P$6)) | L56: =IF($H56="","",SUMIFS('3_Ventas_Diarias'!$J$11:$J$610,'3_Ventas_Diarias'!$C$11:$C$610,$H56,'3_Ventas_Diarias'!$A$11:$A$610,">="&'4_Dashboard_DAMABIS'!$P$5,'3_Ventas_Diarias'!$A$11:$A$610,"<="&'4_Dashboard_DAMABIS'!$P$6)) | M56: =IF($H56="","",N($K56)+ROW()/1000000)
H57: =IF('2_Control_de_Stock'!$A$64="","",'2_Control_de_Stock'!$A$64) | I57: =IF('2_Control_de_Stock'!$A$64="","",'2_Control_de_Stock'!$B$64) | J57: =IF($H57="","",SUMIFS('3_Ventas_Diarias'!$E$11:$E$610,'3_Ventas_Diarias'!$C$11:$C$610,$H57,'3_Ventas_Diarias'!$A$11:$A$610,">="&'4_Dashboard_DAMABIS'!$P$5,'3_Ventas_Diarias'!$A$11:$A$610,"<="&'4_Dashboard_DAMABIS'!$P$6)) | K57: =IF($H57="","",SUMIFS('3_Ventas_Diarias'!$G$11:$G$610,'3_Ventas_Diarias'!$C$11:$C$610,$H57,'3_Ventas_Diarias'!$A$11:$A$610,">="&'4_Dashboard_DAMABIS'!$P$5,'3_Ventas_Diarias'!$A$11:$A$610,"<="&'4_Dashboard_DAMABIS'!$P$6)) | L57: =IF($H57="","",SUMIFS('3_Ventas_Diarias'!$J$11:$J$610,'3_Ventas_Diarias'!$C$11:$C$610,$H57,'3_Ventas_Diarias'!$A$11:$A$610,">="&'4_Dashboard_DAMABIS'!$P$5,'3_Ventas_Diarias'!$A$11:$A$610,"<="&'4_Dashboard_DAMABIS'!$P$6)) | M57: =IF($H57="","",N($K57)+ROW()/1000000)
H58: =IF('2_Control_de_Stock'!$A$65="","",'2_Control_de_Stock'!$A$65) | I58: =IF('2_Control_de_Stock'!$A$65="","",'2_Control_de_Stock'!$B$65) | J58: =IF($H58="","",SUMIFS('3_Ventas_Diarias'!$E$11:$E$610,'3_Ventas_Diarias'!$C$11:$C$610,$H58,'3_Ventas_Diarias'!$A$11:$A$610,">="&'4_Dashboard_DAMABIS'!$P$5,'3_Ventas_Diarias'!$A$11:$A$610,"<="&'4_Dashboard_DAMABIS'!$P$6)) | K58: =IF($H58="","",SUMIFS('3_Ventas_Diarias'!$G$11:$G$610,'3_Ventas_Diarias'!$C$11:$C$610,$H58,'3_Ventas_Diarias'!$A$11:$A$610,">="&'4_Dashboard_DAMABIS'!$P$5,'3_Ventas_Diarias'!$A$11:$A$610,"<="&'4_Dashboard_DAMABIS'!$P$6)) | L58: =IF($H58="","",SUMIFS('3_Ventas_Diarias'!$J$11:$J$610,'3_Ventas_Diarias'!$C$11:$C$610,$H58,'3_Ventas_Diarias'!$A$11:$A$610,">="&'4_Dashboard_DAMABIS'!$P$5,'3_Ventas_Diarias'!$A$11:$A$610,"<="&'4_Dashboard_DAMABIS'!$P$6)) | M58: =IF($H58="","",N($K58)+ROW()/1000000)
H59: =IF('2_Control_de_Stock'!$A$66="","",'2_Control_de_Stock'!$A$66) | I59: =IF('2_Control_de_Stock'!$A$66="","",'2_Control_de_Stock'!$B$66) | J59: =IF($H59="","",SUMIFS('3_Ventas_Diarias'!$E$11:$E$610,'3_Ventas_Diarias'!$C$11:$C$610,$H59,'3_Ventas_Diarias'!$A$11:$A$610,">="&'4_Dashboard_DAMABIS'!$P$5,'3_Ventas_Diarias'!$A$11:$A$610,"<="&'4_Dashboard_DAMABIS'!$P$6)) | K59: =IF($H59="","",SUMIFS('3_Ventas_Diarias'!$G$11:$G$610,'3_Ventas_Diarias'!$C$11:$C$610,$H59,'3_Ventas_Diarias'!$A$11:$A$610,">="&'4_Dashboard_DAMABIS'!$P$5,'3_Ventas_Diarias'!$A$11:$A$610,"<="&'4_Dashboard_DAMABIS'!$P$6)) | L59: =IF($H59="","",SUMIFS('3_Ventas_Diarias'!$J$11:$J$610,'3_Ventas_Diarias'!$C$11:$C$610,$H59,'3_Ventas_Diarias'!$A$11:$A$610,">="&'4_Dashboard_DAMABIS'!$P$5,'3_Ventas_Diarias'!$A$11:$A$610,"<="&'4_Dashboard_DAMABIS'!$P$6)) | M59: =IF($H59="","",N($K59)+ROW()/1000000)
H60: =IF('2_Control_de_Stock'!$A$67="","",'2_Control_de_Stock'!$A$67) | I60: =IF('2_Control_de_Stock'!$A$67="","",'2_Control_de_Stock'!$B$67) | J60: =IF($H60="","",SUMIFS('3_Ventas_Diarias'!$E$11:$E$610,'3_Ventas_Diarias'!$C$11:$C$610,$H60,'3_Ventas_Diarias'!$A$11:$A$610,">="&'4_Dashboard_DAMABIS'!$P$5,'3_Ventas_Diarias'!$A$11:$A$610,"<="&'4_Dashboard_DAMABIS'!$P$6)) | K60: =IF($H60="","",SUMIFS('3_Ventas_Diarias'!$G$11:$G$610,'3_Ventas_Diarias'!$C$11:$C$610,$H60,'3_Ventas_Diarias'!$A$11:$A$610,">="&'4_Dashboard_DAMABIS'!$P$5,'3_Ventas_Diarias'!$A$11:$A$610,"<="&'4_Dashboard_DAMABIS'!$P$6)) | L60: =IF($H60="","",SUMIFS('3_Ventas_Diarias'!$J$11:$J$610,'3_Ventas_Diarias'!$C$11:$C$610,$H60,'3_Ventas_Diarias'!$A$11:$A$610,">="&'4_Dashboard_DAMABIS'!$P$5,'3_Ventas_Diarias'!$A$11:$A$610,"<="&'4_Dashboard_DAMABIS'!$P$6)) | M60: =IF($H60="","",N($K60)+ROW()/1000000)
H61: =IF('2_Control_de_Stock'!$A$68="","",'2_Control_de_Stock'!$A$68) | I61: =IF('2_Control_de_Stock'!$A$68="","",'2_Control_de_Stock'!$B$68) | J61: =IF($H61="","",SUMIFS('3_Ventas_Diarias'!$E$11:$E$610,'3_Ventas_Diarias'!$C$11:$C$610,$H61,'3_Ventas_Diarias'!$A$11:$A$610,">="&'4_Dashboard_DAMABIS'!$P$5,'3_Ventas_Diarias'!$A$11:$A$610,"<="&'4_Dashboard_DAMABIS'!$P$6)) | K61: =IF($H61="","",SUMIFS('3_Ventas_Diarias'!$G$11:$G$610,'3_Ventas_Diarias'!$C$11:$C$610,$H61,'3_Ventas_Diarias'!$A$11:$A$610,">="&'4_Dashboard_DAMABIS'!$P$5,'3_Ventas_Diarias'!$A$11:$A$610,"<="&'4_Dashboard_DAMABIS'!$P$6)) | L61: =IF($H61="","",SUMIFS('3_Ventas_Diarias'!$J$11:$J$610,'3_Ventas_Diarias'!$C$11:$C$610,$H61,'3_Ventas_Diarias'!$A$11:$A$610,">="&'4_Dashboard_DAMABIS'!$P$5,'3_Ventas_Diarias'!$A$11:$A$610,"<="&'4_Dashboard_DAMABIS'!$P$6)) | M61: =IF($H61="","",N($K61)+ROW()/1000000)
H62: =IF('2_Control_de_Stock'!$A$69="","",'2_Control_de_Stock'!$A$69) | I62: =IF('2_Control_de_Stock'!$A$69="","",'2_Control_de_Stock'!$B$69) | J62: =IF($H62="","",SUMIFS('3_Ventas_Diarias'!$E$11:$E$610,'3_Ventas_Diarias'!$C$11:$C$610,$H62,'3_Ventas_Diarias'!$A$11:$A$610,">="&'4_Dashboard_DAMABIS'!$P$5,'3_Ventas_Diarias'!$A$11:$A$610,"<="&'4_Dashboard_DAMABIS'!$P$6)) | K62: =IF($H62="","",SUMIFS('3_Ventas_Diarias'!$G$11:$G$610,'3_Ventas_Diarias'!$C$11:$C$610,$H62,'3_Ventas_Diarias'!$A$11:$A$610,">="&'4_Dashboard_DAMABIS'!$P$5,'3_Ventas_Diarias'!$A$11:$A$610,"<="&'4_Dashboard_DAMABIS'!$P$6)) | L62: =IF($H62="","",SUMIFS('3_Ventas_Diarias'!$J$11:$J$610,'3_Ventas_Diarias'!$C$11:$C$610,$H62,'3_Ventas_Diarias'!$A$11:$A$610,">="&'4_Dashboard_DAMABIS'!$P$5,'3_Ventas_Diarias'!$A$11:$A$610,"<="&'4_Dashboard_DAMABIS'!$P$6)) | M62: =IF($H62="","",N($K62)+ROW()/1000000)
H63: =IF('2_Control_de_Stock'!$A$70="","",'2_Control_de_Stock'!$A$70) | I63: =IF('2_Control_de_Stock'!$A$70="","",'2_Control_de_Stock'!$B$70) | J63: =IF($H63="","",SUMIFS('3_Ventas_Diarias'!$E$11:$E$610,'3_Ventas_Diarias'!$C$11:$C$610,$H63,'3_Ventas_Diarias'!$A$11:$A$610,">="&'4_Dashboard_DAMABIS'!$P$5,'3_Ventas_Diarias'!$A$11:$A$610,"<="&'4_Dashboard_DAMABIS'!$P$6)) | K63: =IF($H63="","",SUMIFS('3_Ventas_Diarias'!$G$11:$G$610,'3_Ventas_Diarias'!$C$11:$C$610,$H63,'3_Ventas_Diarias'!$A$11:$A$610,">="&'4_Dashboard_DAMABIS'!$P$5,'3_Ventas_Diarias'!$A$11:$A$610,"<="&'4_Dashboard_DAMABIS'!$P$6)) | L63: =IF($H63="","",SUMIFS('3_Ventas_Diarias'!$J$11:$J$610,'3_Ventas_Diarias'!$C$11:$C$610,$H63,'3_Ventas_Diarias'!$A$11:$A$610,">="&'4_Dashboard_DAMABIS'!$P$5,'3_Ventas_Diarias'!$A$11:$A$610,"<="&'4_Dashboard_DAMABIS'!$P$6)) | M63: =IF($H63="","",N($K63)+ROW()/1000000)
H64: =IF('2_Control_de_Stock'!$A$71="","",'2_Control_de_Stock'!$A$71) | I64: =IF('2_Control_de_Stock'!$A$71="","",'2_Control_de_Stock'!$B$71) | J64: =IF($H64="","",SUMIFS('3_Ventas_Diarias'!$E$11:$E$610,'3_Ventas_Diarias'!$C$11:$C$610,$H64,'3_Ventas_Diarias'!$A$11:$A$610,">="&'4_Dashboard_DAMABIS'!$P$5,'3_Ventas_Diarias'!$A$11:$A$610,"<="&'4_Dashboard_DAMABIS'!$P$6)) | K64: =IF($H64="","",SUMIFS('3_Ventas_Diarias'!$G$11:$G$610,'3_Ventas_Diarias'!$C$11:$C$610,$H64,'3_Ventas_Diarias'!$A$11:$A$610,">="&'4_Dashboard_DAMABIS'!$P$5,'3_Ventas_Diarias'!$A$11:$A$610,"<="&'4_Dashboard_DAMABIS'!$P$6)) | L64: =IF($H64="","",SUMIFS('3_Ventas_Diarias'!$J$11:$J$610,'3_Ventas_Diarias'!$C$11:$C$610,$H64,'3_Ventas_Diarias'!$A$11:$A$610,">="&'4_Dashboard_DAMABIS'!$P$5,'3_Ventas_Diarias'!$A$11:$A$610,"<="&'4_Dashboard_DAMABIS'!$P$6)) | M64: =IF($H64="","",N($K64)+ROW()/1000000)
H65: =IF('2_Control_de_Stock'!$A$72="","",'2_Control_de_Stock'!$A$72) | I65: =IF('2_Control_de_Stock'!$A$72="","",'2_Control_de_Stock'!$B$72) | J65: =IF($H65="","",SUMIFS('3_Ventas_Diarias'!$E$11:$E$610,'3_Ventas_Diarias'!$C$11:$C$610,$H65,'3_Ventas_Diarias'!$A$11:$A$610,">="&'4_Dashboard_DAMABIS'!$P$5,'3_Ventas_Diarias'!$A$11:$A$610,"<="&'4_Dashboard_DAMABIS'!$P$6)) | K65: =IF($H65="","",SUMIFS('3_Ventas_Diarias'!$G$11:$G$610,'3_Ventas_Diarias'!$C$11:$C$610,$H65,'3_Ventas_Diarias'!$A$11:$A$610,">="&'4_Dashboard_DAMABIS'!$P$5,'3_Ventas_Diarias'!$A$11:$A$610,"<="&'4_Dashboard_DAMABIS'!$P$6)) | L65: =IF($H65="","",SUMIFS('3_Ventas_Diarias'!$J$11:$J$610,'3_Ventas_Diarias'!$C$11:$C$610,$H65,'3_Ventas_Diarias'!$A$11:$A$610,">="&'4_Dashboard_DAMABIS'!$P$5,'3_Ventas_Diarias'!$A$11:$A$610,"<="&'4_Dashboard_DAMABIS'!$P$6)) | M65: =IF($H65="","",N($K65)+ROW()/1000000)
H66: =IF('2_Control_de_Stock'!$A$73="","",'2_Control_de_Stock'!$A$73) | I66: =IF('2_Control_de_Stock'!$A$73="","",'2_Control_de_Stock'!$B$73) | J66: =IF($H66="","",SUMIFS('3_Ventas_Diarias'!$E$11:$E$610,'3_Ventas_Diarias'!$C$11:$C$610,$H66,'3_Ventas_Diarias'!$A$11:$A$610,">="&'4_Dashboard_DAMABIS'!$P$5,'3_Ventas_Diarias'!$A$11:$A$610,"<="&'4_Dashboard_DAMABIS'!$P$6)) | K66: =IF($H66="","",SUMIFS('3_Ventas_Diarias'!$G$11:$G$610,'3_Ventas_Diarias'!$C$11:$C$610,$H66,'3_Ventas_Diarias'!$A$11:$A$610,">="&'4_Dashboard_DAMABIS'!$P$5,'3_Ventas_Diarias'!$A$11:$A$610,"<="&'4_Dashboard_DAMABIS'!$P$6)) | L66: =IF($H66="","",SUMIFS('3_Ventas_Diarias'!$J$11:$J$610,'3_Ventas_Diarias'!$C$11:$C$610,$H66,'3_Ventas_Diarias'!$A$11:$A$610,">="&'4_Dashboard_DAMABIS'!$P$5,'3_Ventas_Diarias'!$A$11:$A$610,"<="&'4_Dashboard_DAMABIS'!$P$6)) | M66: =IF($H66="","",N($K66)+ROW()/1000000)
H67: =IF('2_Control_de_Stock'!$A$74="","",'2_Control_de_Stock'!$A$74) | I67: =IF('2_Control_de_Stock'!$A$74="","",'2_Control_de_Stock'!$B$74) | J67: =IF($H67="","",SUMIFS('3_Ventas_Diarias'!$E$11:$E$610,'3_Ventas_Diarias'!$C$11:$C$610,$H67,'3_Ventas_Diarias'!$A$11:$A$610,">="&'4_Dashboard_DAMABIS'!$P$5,'3_Ventas_Diarias'!$A$11:$A$610,"<="&'4_Dashboard_DAMABIS'!$P$6)) | K67: =IF($H67="","",SUMIFS('3_Ventas_Diarias'!$G$11:$G$610,'3_Ventas_Diarias'!$C$11:$C$610,$H67,'3_Ventas_Diarias'!$A$11:$A$610,">="&'4_Dashboard_DAMABIS'!$P$5,'3_Ventas_Diarias'!$A$11:$A$610,"<="&'4_Dashboard_DAMABIS'!$P$6)) | L67: =IF($H67="","",SUMIFS('3_Ventas_Diarias'!$J$11:$J$610,'3_Ventas_Diarias'!$C$11:$C$610,$H67,'3_Ventas_Diarias'!$A$11:$A$610,">="&'4_Dashboard_DAMABIS'!$P$5,'3_Ventas_Diarias'!$A$11:$A$610,"<="&'4_Dashboard_DAMABIS'!$P$6)) | M67: =IF($H67="","",N($K67)+ROW()/1000000)
H68: =IF('2_Control_de_Stock'!$A$75="","",'2_Control_de_Stock'!$A$75) | I68: =IF('2_Control_de_Stock'!$A$75="","",'2_Control_de_Stock'!$B$75) | J68: =IF($H68="","",SUMIFS('3_Ventas_Diarias'!$E$11:$E$610,'3_Ventas_Diarias'!$C$11:$C$610,$H68,'3_Ventas_Diarias'!$A$11:$A$610,">="&'4_Dashboard_DAMABIS'!$P$5,'3_Ventas_Diarias'!$A$11:$A$610,"<="&'4_Dashboard_DAMABIS'!$P$6)) | K68: =IF($H68="","",SUMIFS('3_Ventas_Diarias'!$G$11:$G$610,'3_Ventas_Diarias'!$C$11:$C$610,$H68,'3_Ventas_Diarias'!$A$11:$A$610,">="&'4_Dashboard_DAMABIS'!$P$5,'3_Ventas_Diarias'!$A$11:$A$610,"<="&'4_Dashboard_DAMABIS'!$P$6)) | L68: =IF($H68="","",SUMIFS('3_Ventas_Diarias'!$J$11:$J$610,'3_Ventas_Diarias'!$C$11:$C$610,$H68,'3_Ventas_Diarias'!$A$11:$A$610,">="&'4_Dashboard_DAMABIS'!$P$5,'3_Ventas_Diarias'!$A$11:$A$610,"<="&'4_Dashboard_DAMABIS'!$P$6)) | M68: =IF($H68="","",N($K68)+ROW()/1000000)
H69: =IF('2_Control_de_Stock'!$A$76="","",'2_Control_de_Stock'!$A$76) | I69: =IF('2_Control_de_Stock'!$A$76="","",'2_Control_de_Stock'!$B$76) | J69: =IF($H69="","",SUMIFS('3_Ventas_Diarias'!$E$11:$E$610,'3_Ventas_Diarias'!$C$11:$C$610,$H69,'3_Ventas_Diarias'!$A$11:$A$610,">="&'4_Dashboard_DAMABIS'!$P$5,'3_Ventas_Diarias'!$A$11:$A$610,"<="&'4_Dashboard_DAMABIS'!$P$6)) | K69: =IF($H69="","",SUMIFS('3_Ventas_Diarias'!$G$11:$G$610,'3_Ventas_Diarias'!$C$11:$C$610,$H69,'3_Ventas_Diarias'!$A$11:$A$610,">="&'4_Dashboard_DAMABIS'!$P$5,'3_Ventas_Diarias'!$A$11:$A$610,"<="&'4_Dashboard_DAMABIS'!$P$6)) | L69: =IF($H69="","",SUMIFS('3_Ventas_Diarias'!$J$11:$J$610,'3_Ventas_Diarias'!$C$11:$C$610,$H69,'3_Ventas_Diarias'!$A$11:$A$610,">="&'4_Dashboard_DAMABIS'!$P$5,'3_Ventas_Diarias'!$A$11:$A$610,"<="&'4_Dashboard_DAMABIS'!$P$6)) | M69: =IF($H69="","",N($K69)+ROW()/1000000)
H70: =IF('2_Control_de_Stock'!$A$77="","",'2_Control_de_Stock'!$A$77) | I70: =IF('2_Control_de_Stock'!$A$77="","",'2_Control_de_Stock'!$B$77) | J70: =IF($H70="","",SUMIFS('3_Ventas_Diarias'!$E$11:$E$610,'3_Ventas_Diarias'!$C$11:$C$610,$H70,'3_Ventas_Diarias'!$A$11:$A$610,">="&'4_Dashboard_DAMABIS'!$P$5,'3_Ventas_Diarias'!$A$11:$A$610,"<="&'4_Dashboard_DAMABIS'!$P$6)) | K70: =IF($H70="","",SUMIFS('3_Ventas_Diarias'!$G$11:$G$610,'3_Ventas_Diarias'!$C$11:$C$610,$H70,'3_Ventas_Diarias'!$A$11:$A$610,">="&'4_Dashboard_DAMABIS'!$P$5,'3_Ventas_Diarias'!$A$11:$A$610,"<="&'4_Dashboard_DAMABIS'!$P$6)) | L70: =IF($H70="","",SUMIFS('3_Ventas_Diarias'!$J$11:$J$610,'3_Ventas_Diarias'!$C$11:$C$610,$H70,'3_Ventas_Diarias'!$A$11:$A$610,">="&'4_Dashboard_DAMABIS'!$P$5,'3_Ventas_Diarias'!$A$11:$A$610,"<="&'4_Dashboard_DAMABIS'!$P$6)) | M70: =IF($H70="","",N($K70)+ROW()/1000000)
H71: =IF('2_Control_de_Stock'!$A$78="","",'2_Control_de_Stock'!$A$78) | I71: =IF('2_Control_de_Stock'!$A$78="","",'2_Control_de_Stock'!$B$78) | J71: =IF($H71="","",SUMIFS('3_Ventas_Diarias'!$E$11:$E$610,'3_Ventas_Diarias'!$C$11:$C$610,$H71,'3_Ventas_Diarias'!$A$11:$A$610,">="&'4_Dashboard_DAMABIS'!$P$5,'3_Ventas_Diarias'!$A$11:$A$610,"<="&'4_Dashboard_DAMABIS'!$P$6)) | K71: =IF($H71="","",SUMIFS('3_Ventas_Diarias'!$G$11:$G$610,'3_Ventas_Diarias'!$C$11:$C$610,$H71,'3_Ventas_Diarias'!$A$11:$A$610,">="&'4_Dashboard_DAMABIS'!$P$5,'3_Ventas_Diarias'!$A$11:$A$610,"<="&'4_Dashboard_DAMABIS'!$P$6)) | L71: =IF($H71="","",SUMIFS('3_Ventas_Diarias'!$J$11:$J$610,'3_Ventas_Diarias'!$C$11:$C$610,$H71,'3_Ventas_Diarias'!$A$11:$A$610,">="&'4_Dashboard_DAMABIS'!$P$5,'3_Ventas_Diarias'!$A$11:$A$610,"<="&'4_Dashboard_DAMABIS'!$P$6)) | M71: =IF($H71="","",N($K71)+ROW()/1000000)
H72: =IF('2_Control_de_Stock'!$A$79="","",'2_Control_de_Stock'!$A$79) | I72: =IF('2_Control_de_Stock'!$A$79="","",'2_Control_de_Stock'!$B$79) | J72: =IF($H72="","",SUMIFS('3_Ventas_Diarias'!$E$11:$E$610,'3_Ventas_Diarias'!$C$11:$C$610,$H72,'3_Ventas_Diarias'!$A$11:$A$610,">="&'4_Dashboard_DAMABIS'!$P$5,'3_Ventas_Diarias'!$A$11:$A$610,"<="&'4_Dashboard_DAMABIS'!$P$6)) | K72: =IF($H72="","",SUMIFS('3_Ventas_Diarias'!$G$11:$G$610,'3_Ventas_Diarias'!$C$11:$C$610,$H72,'3_Ventas_Diarias'!$A$11:$A$610,">="&'4_Dashboard_DAMABIS'!$P$5,'3_Ventas_Diarias'!$A$11:$A$610,"<="&'4_Dashboard_DAMABIS'!$P$6)) | L72: =IF($H72="","",SUMIFS('3_Ventas_Diarias'!$J$11:$J$610,'3_Ventas_Diarias'!$C$11:$C$610,$H72,'3_Ventas_Diarias'!$A$11:$A$610,">="&'4_Dashboard_DAMABIS'!$P$5,'3_Ventas_Diarias'!$A$11:$A$610,"<="&'4_Dashboard_DAMABIS'!$P$6)) | M72: =IF($H72="","",N($K72)+ROW()/1000000)
H73: =IF('2_Control_de_Stock'!$A$80="","",'2_Control_de_Stock'!$A$80) | I73: =IF('2_Control_de_Stock'!$A$80="","",'2_Control_de_Stock'!$B$80) | J73: =IF($H73="","",SUMIFS('3_Ventas_Diarias'!$E$11:$E$610,'3_Ventas_Diarias'!$C$11:$C$610,$H73,'3_Ventas_Diarias'!$A$11:$A$610,">="&'4_Dashboard_DAMABIS'!$P$5,'3_Ventas_Diarias'!$A$11:$A$610,"<="&'4_Dashboard_DAMABIS'!$P$6)) | K73: =IF($H73="","",SUMIFS('3_Ventas_Diarias'!$G$11:$G$610,'3_Ventas_Diarias'!$C$11:$C$610,$H73,'3_Ventas_Diarias'!$A$11:$A$610,">="&'4_Dashboard_DAMABIS'!$P$5,'3_Ventas_Diarias'!$A$11:$A$610,"<="&'4_Dashboard_DAMABIS'!$P$6)) | L73: =IF($H73="","",SUMIFS('3_Ventas_Diarias'!$J$11:$J$610,'3_Ventas_Diarias'!$C$11:$C$610,$H73,'3_Ventas_Diarias'!$A$11:$A$610,">="&'4_Dashboard_DAMABIS'!$P$5,'3_Ventas_Diarias'!$A$11:$A$610,"<="&'4_Dashboard_DAMABIS'!$P$6)) | M73: =IF($H73="","",N($K73)+ROW()/1000000)
H74: =IF('2_Control_de_Stock'!$A$81="","",'2_Control_de_Stock'!$A$81) | I74: =IF('2_Control_de_Stock'!$A$81="","",'2_Control_de_Stock'!$B$81) | J74: =IF($H74="","",SUMIFS('3_Ventas_Diarias'!$E$11:$E$610,'3_Ventas_Diarias'!$C$11:$C$610,$H74,'3_Ventas_Diarias'!$A$11:$A$610,">="&'4_Dashboard_DAMABIS'!$P$5,'3_Ventas_Diarias'!$A$11:$A$610,"<="&'4_Dashboard_DAMABIS'!$P$6)) | K74: =IF($H74="","",SUMIFS('3_Ventas_Diarias'!$G$11:$G$610,'3_Ventas_Diarias'!$C$11:$C$610,$H74,'3_Ventas_Diarias'!$A$11:$A$610,">="&'4_Dashboard_DAMABIS'!$P$5,'3_Ventas_Diarias'!$A$11:$A$610,"<="&'4_Dashboard_DAMABIS'!$P$6)) | L74: =IF($H74="","",SUMIFS('3_Ventas_Diarias'!$J$11:$J$610,'3_Ventas_Diarias'!$C$11:$C$610,$H74,'3_Ventas_Diarias'!$A$11:$A$610,">="&'4_Dashboard_DAMABIS'!$P$5,'3_Ventas_Diarias'!$A$11:$A$610,"<="&'4_Dashboard_DAMABIS'!$P$6)) | M74: =IF($H74="","",N($K74)+ROW()/1000000)
H75: =IF('2_Control_de_Stock'!$A$82="","",'2_Control_de_Stock'!$A$82) | I75: =IF('2_Control_de_Stock'!$A$82="","",'2_Control_de_Stock'!$B$82) | J75: =IF($H75="","",SUMIFS('3_Ventas_Diarias'!$E$11:$E$610,'3_Ventas_Diarias'!$C$11:$C$610,$H75,'3_Ventas_Diarias'!$A$11:$A$610,">="&'4_Dashboard_DAMABIS'!$P$5,'3_Ventas_Diarias'!$A$11:$A$610,"<="&'4_Dashboard_DAMABIS'!$P$6)) | K75: =IF($H75="","",SUMIFS('3_Ventas_Diarias'!$G$11:$G$610,'3_Ventas_Diarias'!$C$11:$C$610,$H75,'3_Ventas_Diarias'!$A$11:$A$610,">="&'4_Dashboard_DAMABIS'!$P$5,'3_Ventas_Diarias'!$A$11:$A$610,"<="&'4_Dashboard_DAMABIS'!$P$6)) | L75: =IF($H75="","",SUMIFS('3_Ventas_Diarias'!$J$11:$J$610,'3_Ventas_Diarias'!$C$11:$C$610,$H75,'3_Ventas_Diarias'!$A$11:$A$610,">="&'4_Dashboard_DAMABIS'!$P$5,'3_Ventas_Diarias'!$A$11:$A$610,"<="&'4_Dashboard_DAMABIS'!$P$6)) | M75: =IF($H75="","",N($K75)+ROW()/1000000)
H76: =IF('2_Control_de_Stock'!$A$83="","",'2_Control_de_Stock'!$A$83) | I76: =IF('2_Control_de_Stock'!$A$83="","",'2_Control_de_Stock'!$B$83) | J76: =IF($H76="","",SUMIFS('3_Ventas_Diarias'!$E$11:$E$610,'3_Ventas_Diarias'!$C$11:$C$610,$H76,'3_Ventas_Diarias'!$A$11:$A$610,">="&'4_Dashboard_DAMABIS'!$P$5,'3_Ventas_Diarias'!$A$11:$A$610,"<="&'4_Dashboard_DAMABIS'!$P$6)) | K76: =IF($H76="","",SUMIFS('3_Ventas_Diarias'!$G$11:$G$610,'3_Ventas_Diarias'!$C$11:$C$610,$H76,'3_Ventas_Diarias'!$A$11:$A$610,">="&'4_Dashboard_DAMABIS'!$P$5,'3_Ventas_Diarias'!$A$11:$A$610,"<="&'4_Dashboard_DAMABIS'!$P$6)) | L76: =IF($H76="","",SUMIFS('3_Ventas_Diarias'!$J$11:$J$610,'3_Ventas_Diarias'!$C$11:$C$610,$H76,'3_Ventas_Diarias'!$A$11:$A$610,">="&'4_Dashboard_DAMABIS'!$P$5,'3_Ventas_Diarias'!$A$11:$A$610,"<="&'4_Dashboard_DAMABIS'!$P$6)) | M76: =IF($H76="","",N($K76)+ROW()/1000000)
H77: =IF('2_Control_de_Stock'!$A$84="","",'2_Control_de_Stock'!$A$84) | I77: =IF('2_Control_de_Stock'!$A$84="","",'2_Control_de_Stock'!$B$84) | J77: =IF($H77="","",SUMIFS('3_Ventas_Diarias'!$E$11:$E$610,'3_Ventas_Diarias'!$C$11:$C$610,$H77,'3_Ventas_Diarias'!$A$11:$A$610,">="&'4_Dashboard_DAMABIS'!$P$5,'3_Ventas_Diarias'!$A$11:$A$610,"<="&'4_Dashboard_DAMABIS'!$P$6)) | K77: =IF($H77="","",SUMIFS('3_Ventas_Diarias'!$G$11:$G$610,'3_Ventas_Diarias'!$C$11:$C$610,$H77,'3_Ventas_Diarias'!$A$11:$A$610,">="&'4_Dashboard_DAMABIS'!$P$5,'3_Ventas_Diarias'!$A$11:$A$610,"<="&'4_Dashboard_DAMABIS'!$P$6)) | L77: =IF($H77="","",SUMIFS('3_Ventas_Diarias'!$J$11:$J$610,'3_Ventas_Diarias'!$C$11:$C$610,$H77,'3_Ventas_Diarias'!$A$11:$A$610,">="&'4_Dashboard_DAMABIS'!$P$5,'3_Ventas_Diarias'!$A$11:$A$610,"<="&'4_Dashboard_DAMABIS'!$P$6)) | M77: =IF($H77="","",N($K77)+ROW()/1000000)
H78: =IF('2_Control_de_Stock'!$A$85="","",'2_Control_de_Stock'!$A$85) | I78: =IF('2_Control_de_Stock'!$A$85="","",'2_Control_de_Stock'!$B$85) | J78: =IF($H78="","",SUMIFS('3_Ventas_Diarias'!$E$11:$E$610,'3_Ventas_Diarias'!$C$11:$C$610,$H78,'3_Ventas_Diarias'!$A$11:$A$610,">="&'4_Dashboard_DAMABIS'!$P$5,'3_Ventas_Diarias'!$A$11:$A$610,"<="&'4_Dashboard_DAMABIS'!$P$6)) | K78: =IF($H78="","",SUMIFS('3_Ventas_Diarias'!$G$11:$G$610,'3_Ventas_Diarias'!$C$11:$C$610,$H78,'3_Ventas_Diarias'!$A$11:$A$610,">="&'4_Dashboard_DAMABIS'!$P$5,'3_Ventas_Diarias'!$A$11:$A$610,"<="&'4_Dashboard_DAMABIS'!$P$6)) | L78: =IF($H78="","",SUMIFS('3_Ventas_Diarias'!$J$11:$J$610,'3_Ventas_Diarias'!$C$11:$C$610,$H78,'3_Ventas_Diarias'!$A$11:$A$610,">="&'4_Dashboard_DAMABIS'!$P$5,'3_Ventas_Diarias'!$A$11:$A$610,"<="&'4_Dashboard_DAMABIS'!$P$6)) | M78: =IF($H78="","",N($K78)+ROW()/1000000)
H79: =IF('2_Control_de_Stock'!$A$86="","",'2_Control_de_Stock'!$A$86) | I79: =IF('2_Control_de_Stock'!$A$86="","",'2_Control_de_Stock'!$B$86) | J79: =IF($H79="","",SUMIFS('3_Ventas_Diarias'!$E$11:$E$610,'3_Ventas_Diarias'!$C$11:$C$610,$H79,'3_Ventas_Diarias'!$A$11:$A$610,">="&'4_Dashboard_DAMABIS'!$P$5,'3_Ventas_Diarias'!$A$11:$A$610,"<="&'4_Dashboard_DAMABIS'!$P$6)) | K79: =IF($H79="","",SUMIFS('3_Ventas_Diarias'!$G$11:$G$610,'3_Ventas_Diarias'!$C$11:$C$610,$H79,'3_Ventas_Diarias'!$A$11:$A$610,">="&'4_Dashboard_DAMABIS'!$P$5,'3_Ventas_Diarias'!$A$11:$A$610,"<="&'4_Dashboard_DAMABIS'!$P$6)) | L79: =IF($H79="","",SUMIFS('3_Ventas_Diarias'!$J$11:$J$610,'3_Ventas_Diarias'!$C$11:$C$610,$H79,'3_Ventas_Diarias'!$A$11:$A$610,">="&'4_Dashboard_DAMABIS'!$P$5,'3_Ventas_Diarias'!$A$11:$A$610,"<="&'4_Dashboard_DAMABIS'!$P$6)) | M79: =IF($H79="","",N($K79)+ROW()/1000000)
H80: =IF('2_Control_de_Stock'!$A$87="","",'2_Control_de_Stock'!$A$87) | I80: =IF('2_Control_de_Stock'!$A$87="","",'2_Control_de_Stock'!$B$87) | J80: =IF($H80="","",SUMIFS('3_Ventas_Diarias'!$E$11:$E$610,'3_Ventas_Diarias'!$C$11:$C$610,$H80,'3_Ventas_Diarias'!$A$11:$A$610,">="&'4_Dashboard_DAMABIS'!$P$5,'3_Ventas_Diarias'!$A$11:$A$610,"<="&'4_Dashboard_DAMABIS'!$P$6)) | K80: =IF($H80="","",SUMIFS('3_Ventas_Diarias'!$G$11:$G$610,'3_Ventas_Diarias'!$C$11:$C$610,$H80,'3_Ventas_Diarias'!$A$11:$A$610,">="&'4_Dashboard_DAMABIS'!$P$5,'3_Ventas_Diarias'!$A$11:$A$610,"<="&'4_Dashboard_DAMABIS'!$P$6)) | L80: =IF($H80="","",SUMIFS('3_Ventas_Diarias'!$J$11:$J$610,'3_Ventas_Diarias'!$C$11:$C$610,$H80,'3_Ventas_Diarias'!$A$11:$A$610,">="&'4_Dashboard_DAMABIS'!$P$5,'3_Ventas_Diarias'!$A$11:$A$610,"<="&'4_Dashboard_DAMABIS'!$P$6)) | M80: =IF($H80="","",N($K80)+ROW()/1000000)
H81: =IF('2_Control_de_Stock'!$A$88="","",'2_Control_de_Stock'!$A$88) | I81: =IF('2_Control_de_Stock'!$A$88="","",'2_Control_de_Stock'!$B$88) | J81: =IF($H81="","",SUMIFS('3_Ventas_Diarias'!$E$11:$E$610,'3_Ventas_Diarias'!$C$11:$C$610,$H81,'3_Ventas_Diarias'!$A$11:$A$610,">="&'4_Dashboard_DAMABIS'!$P$5,'3_Ventas_Diarias'!$A$11:$A$610,"<="&'4_Dashboard_DAMABIS'!$P$6)) | K81: =IF($H81="","",SUMIFS('3_Ventas_Diarias'!$G$11:$G$610,'3_Ventas_Diarias'!$C$11:$C$610,$H81,'3_Ventas_Diarias'!$A$11:$A$610,">="&'4_Dashboard_DAMABIS'!$P$5,'3_Ventas_Diarias'!$A$11:$A$610,"<="&'4_Dashboard_DAMABIS'!$P$6)) | L81: =IF($H81="","",SUMIFS('3_Ventas_Diarias'!$J$11:$J$610,'3_Ventas_Diarias'!$C$11:$C$610,$H81,'3_Ventas_Diarias'!$A$11:$A$610,">="&'4_Dashboard_DAMABIS'!$P$5,'3_Ventas_Diarias'!$A$11:$A$610,"<="&'4_Dashboard_DAMABIS'!$P$6)) | M81: =IF($H81="","",N($K81)+ROW()/1000000)
H82: =IF('2_Control_de_Stock'!$A$89="","",'2_Control_de_Stock'!$A$89) | I82: =IF('2_Control_de_Stock'!$A$89="","",'2_Control_de_Stock'!$B$89) | J82: =IF($H82="","",SUMIFS('3_Ventas_Diarias'!$E$11:$E$610,'3_Ventas_Diarias'!$C$11:$C$610,$H82,'3_Ventas_Diarias'!$A$11:$A$610,">="&'4_Dashboard_DAMABIS'!$P$5,'3_Ventas_Diarias'!$A$11:$A$610,"<="&'4_Dashboard_DAMABIS'!$P$6)) | K82: =IF($H82="","",SUMIFS('3_Ventas_Diarias'!$G$11:$G$610,'3_Ventas_Diarias'!$C$11:$C$610,$H82,'3_Ventas_Diarias'!$A$11:$A$610,">="&'4_Dashboard_DAMABIS'!$P$5,'3_Ventas_Diarias'!$A$11:$A$610,"<="&'4_Dashboard_DAMABIS'!$P$6)) | L82: =IF($H82="","",SUMIFS('3_Ventas_Diarias'!$J$11:$J$610,'3_Ventas_Diarias'!$C$11:$C$610,$H82,'3_Ventas_Diarias'!$A$11:$A$610,">="&'4_Dashboard_DAMABIS'!$P$5,'3_Ventas_Diarias'!$A$11:$A$610,"<="&'4_Dashboard_DAMABIS'!$P$6)) | M82: =IF($H82="","",N($K82)+ROW()/1000000)
H83: =IF('2_Control_de_Stock'!$A$90="","",'2_Control_de_Stock'!$A$90) | I83: =IF('2_Control_de_Stock'!$A$90="","",'2_Control_de_Stock'!$B$90) | J83: =IF($H83="","",SUMIFS('3_Ventas_Diarias'!$E$11:$E$610,'3_Ventas_Diarias'!$C$11:$C$610,$H83,'3_Ventas_Diarias'!$A$11:$A$610,">="&'4_Dashboard_DAMABIS'!$P$5,'3_Ventas_Diarias'!$A$11:$A$610,"<="&'4_Dashboard_DAMABIS'!$P$6)) | K83: =IF($H83="","",SUMIFS('3_Ventas_Diarias'!$G$11:$G$610,'3_Ventas_Diarias'!$C$11:$C$610,$H83,'3_Ventas_Diarias'!$A$11:$A$610,">="&'4_Dashboard_DAMABIS'!$P$5,'3_Ventas_Diarias'!$A$11:$A$610,"<="&'4_Dashboard_DAMABIS'!$P$6)) | L83: =IF($H83="","",SUMIFS('3_Ventas_Diarias'!$J$11:$J$610,'3_Ventas_Diarias'!$C$11:$C$610,$H83,'3_Ventas_Diarias'!$A$11:$A$610,">="&'4_Dashboard_DAMABIS'!$P$5,'3_Ventas_Diarias'!$A$11:$A$610,"<="&'4_Dashboard_DAMABIS'!$P$6)) | M83: =IF($H83="","",N($K83)+ROW()/1000000)
H84: =IF('2_Control_de_Stock'!$A$91="","",'2_Control_de_Stock'!$A$91) | I84: =IF('2_Control_de_Stock'!$A$91="","",'2_Control_de_Stock'!$B$91) | J84: =IF($H84="","",SUMIFS('3_Ventas_Diarias'!$E$11:$E$610,'3_Ventas_Diarias'!$C$11:$C$610,$H84,'3_Ventas_Diarias'!$A$11:$A$610,">="&'4_Dashboard_DAMABIS'!$P$5,'3_Ventas_Diarias'!$A$11:$A$610,"<="&'4_Dashboard_DAMABIS'!$P$6)) | K84: =IF($H84="","",SUMIFS('3_Ventas_Diarias'!$G$11:$G$610,'3_Ventas_Diarias'!$C$11:$C$610,$H84,'3_Ventas_Diarias'!$A$11:$A$610,">="&'4_Dashboard_DAMABIS'!$P$5,'3_Ventas_Diarias'!$A$11:$A$610,"<="&'4_Dashboard_DAMABIS'!$P$6)) | L84: =IF($H84="","",SUMIFS('3_Ventas_Diarias'!$J$11:$J$610,'3_Ventas_Diarias'!$C$11:$C$610,$H84,'3_Ventas_Diarias'!$A$11:$A$610,">="&'4_Dashboard_DAMABIS'!$P$5,'3_Ventas_Diarias'!$A$11:$A$610,"<="&'4_Dashboard_DAMABIS'!$P$6)) | M84: =IF($H84="","",N($K84)+ROW()/1000000)
H85: =IF('2_Control_de_Stock'!$A$92="","",'2_Control_de_Stock'!$A$92) | I85: =IF('2_Control_de_Stock'!$A$92="","",'2_Control_de_Stock'!$B$92) | J85: =IF($H85="","",SUMIFS('3_Ventas_Diarias'!$E$11:$E$610,'3_Ventas_Diarias'!$C$11:$C$610,$H85,'3_Ventas_Diarias'!$A$11:$A$610,">="&'4_Dashboard_DAMABIS'!$P$5,'3_Ventas_Diarias'!$A$11:$A$610,"<="&'4_Dashboard_DAMABIS'!$P$6)) | K85: =IF($H85="","",SUMIFS('3_Ventas_Diarias'!$G$11:$G$610,'3_Ventas_Diarias'!$C$11:$C$610,$H85,'3_Ventas_Diarias'!$A$11:$A$610,">="&'4_Dashboard_DAMABIS'!$P$5,'3_Ventas_Diarias'!$A$11:$A$610,"<="&'4_Dashboard_DAMABIS'!$P$6)) | L85: =IF($H85="","",SUMIFS('3_Ventas_Diarias'!$J$11:$J$610,'3_Ventas_Diarias'!$C$11:$C$610,$H85,'3_Ventas_Diarias'!$A$11:$A$610,">="&'4_Dashboard_DAMABIS'!$P$5,'3_Ventas_Diarias'!$A$11:$A$610,"<="&'4_Dashboard_DAMABIS'!$P$6)) | M85: =IF($H85="","",N($K85)+ROW()/1000000)
H86: =IF('2_Control_de_Stock'!$A$93="","",'2_Control_de_Stock'!$A$93) | I86: =IF('2_Control_de_Stock'!$A$93="","",'2_Control_de_Stock'!$B$93) | J86: =IF($H86="","",SUMIFS('3_Ventas_Diarias'!$E$11:$E$610,'3_Ventas_Diarias'!$C$11:$C$610,$H86,'3_Ventas_Diarias'!$A$11:$A$610,">="&'4_Dashboard_DAMABIS'!$P$5,'3_Ventas_Diarias'!$A$11:$A$610,"<="&'4_Dashboard_DAMABIS'!$P$6)) | K86: =IF($H86="","",SUMIFS('3_Ventas_Diarias'!$G$11:$G$610,'3_Ventas_Diarias'!$C$11:$C$610,$H86,'3_Ventas_Diarias'!$A$11:$A$610,">="&'4_Dashboard_DAMABIS'!$P$5,'3_Ventas_Diarias'!$A$11:$A$610,"<="&'4_Dashboard_DAMABIS'!$P$6)) | L86: =IF($H86="","",SUMIFS('3_Ventas_Diarias'!$J$11:$J$610,'3_Ventas_Diarias'!$C$11:$C$610,$H86,'3_Ventas_Diarias'!$A$11:$A$610,">="&'4_Dashboard_DAMABIS'!$P$5,'3_Ventas_Diarias'!$A$11:$A$610,"<="&'4_Dashboard_DAMABIS'!$P$6)) | M86: =IF($H86="","",N($K86)+ROW()/1000000)
H87: =IF('2_Control_de_Stock'!$A$94="","",'2_Control_de_Stock'!$A$94) | I87: =IF('2_Control_de_Stock'!$A$94="","",'2_Control_de_Stock'!$B$94) | J87: =IF($H87="","",SUMIFS('3_Ventas_Diarias'!$E$11:$E$610,'3_Ventas_Diarias'!$C$11:$C$610,$H87,'3_Ventas_Diarias'!$A$11:$A$610,">="&'4_Dashboard_DAMABIS'!$P$5,'3_Ventas_Diarias'!$A$11:$A$610,"<="&'4_Dashboard_DAMABIS'!$P$6)) | K87: =IF($H87="","",SUMIFS('3_Ventas_Diarias'!$G$11:$G$610,'3_Ventas_Diarias'!$C$11:$C$610,$H87,'3_Ventas_Diarias'!$A$11:$A$610,">="&'4_Dashboard_DAMABIS'!$P$5,'3_Ventas_Diarias'!$A$11:$A$610,"<="&'4_Dashboard_DAMABIS'!$P$6)) | L87: =IF($H87="","",SUMIFS('3_Ventas_Diarias'!$J$11:$J$610,'3_Ventas_Diarias'!$C$11:$C$610,$H87,'3_Ventas_Diarias'!$A$11:$A$610,">="&'4_Dashboard_DAMABIS'!$P$5,'3_Ventas_Diarias'!$A$11:$A$610,"<="&'4_Dashboard_DAMABIS'!$P$6)) | M87: =IF($H87="","",N($K87)+ROW()/1000000)
H88: =IF('2_Control_de_Stock'!$A$95="","",'2_Control_de_Stock'!$A$95) | I88: =IF('2_Control_de_Stock'!$A$95="","",'2_Control_de_Stock'!$B$95) | J88: =IF($H88="","",SUMIFS('3_Ventas_Diarias'!$E$11:$E$610,'3_Ventas_Diarias'!$C$11:$C$610,$H88,'3_Ventas_Diarias'!$A$11:$A$610,">="&'4_Dashboard_DAMABIS'!$P$5,'3_Ventas_Diarias'!$A$11:$A$610,"<="&'4_Dashboard_DAMABIS'!$P$6)) | K88: =IF($H88="","",SUMIFS('3_Ventas_Diarias'!$G$11:$G$610,'3_Ventas_Diarias'!$C$11:$C$610,$H88,'3_Ventas_Diarias'!$A$11:$A$610,">="&'4_Dashboard_DAMABIS'!$P$5,'3_Ventas_Diarias'!$A$11:$A$610,"<="&'4_Dashboard_DAMABIS'!$P$6)) | L88: =IF($H88="","",SUMIFS('3_Ventas_Diarias'!$J$11:$J$610,'3_Ventas_Diarias'!$C$11:$C$610,$H88,'3_Ventas_Diarias'!$A$11:$A$610,">="&'4_Dashboard_DAMABIS'!$P$5,'3_Ventas_Diarias'!$A$11:$A$610,"<="&'4_Dashboard_DAMABIS'!$P$6)) | M88: =IF($H88="","",N($K88)+ROW()/1000000)
H89: =IF('2_Control_de_Stock'!$A$96="","",'2_Control_de_Stock'!$A$96) | I89: =IF('2_Control_de_Stock'!$A$96="","",'2_Control_de_Stock'!$B$96) | J89: =IF($H89="","",SUMIFS('3_Ventas_Diarias'!$E$11:$E$610,'3_Ventas_Diarias'!$C$11:$C$610,$H89,'3_Ventas_Diarias'!$A$11:$A$610,">="&'4_Dashboard_DAMABIS'!$P$5,'3_Ventas_Diarias'!$A$11:$A$610,"<="&'4_Dashboard_DAMABIS'!$P$6)) | K89: =IF($H89="","",SUMIFS('3_Ventas_Diarias'!$G$11:$G$610,'3_Ventas_Diarias'!$C$11:$C$610,$H89,'3_Ventas_Diarias'!$A$11:$A$610,">="&'4_Dashboard_DAMABIS'!$P$5,'3_Ventas_Diarias'!$A$11:$A$610,"<="&'4_Dashboard_DAMABIS'!$P$6)) | L89: =IF($H89="","",SUMIFS('3_Ventas_Diarias'!$J$11:$J$610,'3_Ventas_Diarias'!$C$11:$C$610,$H89,'3_Ventas_Diarias'!$A$11:$A$610,">="&'4_Dashboard_DAMABIS'!$P$5,'3_Ventas_Diarias'!$A$11:$A$610,"<="&'4_Dashboard_DAMABIS'!$P$6)) | M89: =IF($H89="","",N($K89)+ROW()/1000000)
H90: =IF('2_Control_de_Stock'!$A$97="","",'2_Control_de_Stock'!$A$97) | I90: =IF('2_Control_de_Stock'!$A$97="","",'2_Control_de_Stock'!$B$97) | J90: =IF($H90="","",SUMIFS('3_Ventas_Diarias'!$E$11:$E$610,'3_Ventas_Diarias'!$C$11:$C$610,$H90,'3_Ventas_Diarias'!$A$11:$A$610,">="&'4_Dashboard_DAMABIS'!$P$5,'3_Ventas_Diarias'!$A$11:$A$610,"<="&'4_Dashboard_DAMABIS'!$P$6)) | K90: =IF($H90="","",SUMIFS('3_Ventas_Diarias'!$G$11:$G$610,'3_Ventas_Diarias'!$C$11:$C$610,$H90,'3_Ventas_Diarias'!$A$11:$A$610,">="&'4_Dashboard_DAMABIS'!$P$5,'3_Ventas_Diarias'!$A$11:$A$610,"<="&'4_Dashboard_DAMABIS'!$P$6)) | L90: =IF($H90="","",SUMIFS('3_Ventas_Diarias'!$J$11:$J$610,'3_Ventas_Diarias'!$C$11:$C$610,$H90,'3_Ventas_Diarias'!$A$11:$A$610,">="&'4_Dashboard_DAMABIS'!$P$5,'3_Ventas_Diarias'!$A$11:$A$610,"<="&'4_Dashboard_DAMABIS'!$P$6)) | M90: =IF($H90="","",N($K90)+ROW()/1000000)
H91: =IF('2_Control_de_Stock'!$A$98="","",'2_Control_de_Stock'!$A$98) | I91: =IF('2_Control_de_Stock'!$A$98="","",'2_Control_de_Stock'!$B$98) | J91: =IF($H91="","",SUMIFS('3_Ventas_Diarias'!$E$11:$E$610,'3_Ventas_Diarias'!$C$11:$C$610,$H91,'3_Ventas_Diarias'!$A$11:$A$610,">="&'4_Dashboard_DAMABIS'!$P$5,'3_Ventas_Diarias'!$A$11:$A$610,"<="&'4_Dashboard_DAMABIS'!$P$6)) | K91: =IF($H91="","",SUMIFS('3_Ventas_Diarias'!$G$11:$G$610,'3_Ventas_Diarias'!$C$11:$C$610,$H91,'3_Ventas_Diarias'!$A$11:$A$610,">="&'4_Dashboard_DAMABIS'!$P$5,'3_Ventas_Diarias'!$A$11:$A$610,"<="&'4_Dashboard_DAMABIS'!$P$6)) | L91: =IF($H91="","",SUMIFS('3_Ventas_Diarias'!$J$11:$J$610,'3_Ventas_Diarias'!$C$11:$C$610,$H91,'3_Ventas_Diarias'!$A$11:$A$610,">="&'4_Dashboard_DAMABIS'!$P$5,'3_Ventas_Diarias'!$A$11:$A$610,"<="&'4_Dashboard_DAMABIS'!$P$6)) | M91: =IF($H91="","",N($K91)+ROW()/1000000)
H92: =IF('2_Control_de_Stock'!$A$99="","",'2_Control_de_Stock'!$A$99) | I92: =IF('2_Control_de_Stock'!$A$99="","",'2_Control_de_Stock'!$B$99) | J92: =IF($H92="","",SUMIFS('3_Ventas_Diarias'!$E$11:$E$610,'3_Ventas_Diarias'!$C$11:$C$610,$H92,'3_Ventas_Diarias'!$A$11:$A$610,">="&'4_Dashboard_DAMABIS'!$P$5,'3_Ventas_Diarias'!$A$11:$A$610,"<="&'4_Dashboard_DAMABIS'!$P$6)) | K92: =IF($H92="","",SUMIFS('3_Ventas_Diarias'!$G$11:$G$610,'3_Ventas_Diarias'!$C$11:$C$610,$H92,'3_Ventas_Diarias'!$A$11:$A$610,">="&'4_Dashboard_DAMABIS'!$P$5,'3_Ventas_Diarias'!$A$11:$A$610,"<="&'4_Dashboard_DAMABIS'!$P$6)) | L92: =IF($H92="","",SUMIFS('3_Ventas_Diarias'!$J$11:$J$610,'3_Ventas_Diarias'!$C$11:$C$610,$H92,'3_Ventas_Diarias'!$A$11:$A$610,">="&'4_Dashboard_DAMABIS'!$P$5,'3_Ventas_Diarias'!$A$11:$A$610,"<="&'4_Dashboard_DAMABIS'!$P$6)) | M92: =IF($H92="","",N($K92)+ROW()/1000000)
H93: =IF('2_Control_de_Stock'!$A$100="","",'2_Control_de_Stock'!$A$100) | I93: =IF('2_Control_de_Stock'!$A$100="","",'2_Control_de_Stock'!$B$100) | J93: =IF($H93="","",SUMIFS('3_Ventas_Diarias'!$E$11:$E$610,'3_Ventas_Diarias'!$C$11:$C$610,$H93,'3_Ventas_Diarias'!$A$11:$A$610,">="&'4_Dashboard_DAMABIS'!$P$5,'3_Ventas_Diarias'!$A$11:$A$610,"<="&'4_Dashboard_DAMABIS'!$P$6)) | K93: =IF($H93="","",SUMIFS('3_Ventas_Diarias'!$G$11:$G$610,'3_Ventas_Diarias'!$C$11:$C$610,$H93,'3_Ventas_Diarias'!$A$11:$A$610,">="&'4_Dashboard_DAMABIS'!$P$5,'3_Ventas_Diarias'!$A$11:$A$610,"<="&'4_Dashboard_DAMABIS'!$P$6)) | L93: =IF($H93="","",SUMIFS('3_Ventas_Diarias'!$J$11:$J$610,'3_Ventas_Diarias'!$C$11:$C$610,$H93,'3_Ventas_Diarias'!$A$11:$A$610,">="&'4_Dashboard_DAMABIS'!$P$5,'3_Ventas_Diarias'!$A$11:$A$610,"<="&'4_Dashboard_DAMABIS'!$P$6)) | M93: =IF($H93="","",N($K93)+ROW()/1000000)
H94: =IF('2_Control_de_Stock'!$A$101="","",'2_Control_de_Stock'!$A$101) | I94: =IF('2_Control_de_Stock'!$A$101="","",'2_Control_de_Stock'!$B$101) | J94: =IF($H94="","",SUMIFS('3_Ventas_Diarias'!$E$11:$E$610,'3_Ventas_Diarias'!$C$11:$C$610,$H94,'3_Ventas_Diarias'!$A$11:$A$610,">="&'4_Dashboard_DAMABIS'!$P$5,'3_Ventas_Diarias'!$A$11:$A$610,"<="&'4_Dashboard_DAMABIS'!$P$6)) | K94: =IF($H94="","",SUMIFS('3_Ventas_Diarias'!$G$11:$G$610,'3_Ventas_Diarias'!$C$11:$C$610,$H94,'3_Ventas_Diarias'!$A$11:$A$610,">="&'4_Dashboard_DAMABIS'!$P$5,'3_Ventas_Diarias'!$A$11:$A$610,"<="&'4_Dashboard_DAMABIS'!$P$6)) | L94: =IF($H94="","",SUMIFS('3_Ventas_Diarias'!$J$11:$J$610,'3_Ventas_Diarias'!$C$11:$C$610,$H94,'3_Ventas_Diarias'!$A$11:$A$610,">="&'4_Dashboard_DAMABIS'!$P$5,'3_Ventas_Diarias'!$A$11:$A$610,"<="&'4_Dashboard_DAMABIS'!$P$6)) | M94: =IF($H94="","",N($K94)+ROW()/1000000)
H95: =IF('2_Control_de_Stock'!$A$102="","",'2_Control_de_Stock'!$A$102) | I95: =IF('2_Control_de_Stock'!$A$102="","",'2_Control_de_Stock'!$B$102) | J95: =IF($H95="","",SUMIFS('3_Ventas_Diarias'!$E$11:$E$610,'3_Ventas_Diarias'!$C$11:$C$610,$H95,'3_Ventas_Diarias'!$A$11:$A$610,">="&'4_Dashboard_DAMABIS'!$P$5,'3_Ventas_Diarias'!$A$11:$A$610,"<="&'4_Dashboard_DAMABIS'!$P$6)) | K95: =IF($H95="","",SUMIFS('3_Ventas_Diarias'!$G$11:$G$610,'3_Ventas_Diarias'!$C$11:$C$610,$H95,'3_Ventas_Diarias'!$A$11:$A$610,">="&'4_Dashboard_DAMABIS'!$P$5,'3_Ventas_Diarias'!$A$11:$A$610,"<="&'4_Dashboard_DAMABIS'!$P$6)) | L95: =IF($H95="","",SUMIFS('3_Ventas_Diarias'!$J$11:$J$610,'3_Ventas_Diarias'!$C$11:$C$610,$H95,'3_Ventas_Diarias'!$A$11:$A$610,">="&'4_Dashboard_DAMABIS'!$P$5,'3_Ventas_Diarias'!$A$11:$A$610,"<="&'4_Dashboard_DAMABIS'!$P$6)) | M95: =IF($H95="","",N($K95)+ROW()/1000000)
H96: =IF('2_Control_de_Stock'!$A$103="","",'2_Control_de_Stock'!$A$103) | I96: =IF('2_Control_de_Stock'!$A$103="","",'2_Control_de_Stock'!$B$103) | J96: =IF($H96="","",SUMIFS('3_Ventas_Diarias'!$E$11:$E$610,'3_Ventas_Diarias'!$C$11:$C$610,$H96,'3_Ventas_Diarias'!$A$11:$A$610,">="&'4_Dashboard_DAMABIS'!$P$5,'3_Ventas_Diarias'!$A$11:$A$610,"<="&'4_Dashboard_DAMABIS'!$P$6)) | K96: =IF($H96="","",SUMIFS('3_Ventas_Diarias'!$G$11:$G$610,'3_Ventas_Diarias'!$C$11:$C$610,$H96,'3_Ventas_Diarias'!$A$11:$A$610,">="&'4_Dashboard_DAMABIS'!$P$5,'3_Ventas_Diarias'!$A$11:$A$610,"<="&'4_Dashboard_DAMABIS'!$P$6)) | L96: =IF($H96="","",SUMIFS('3_Ventas_Diarias'!$J$11:$J$610,'3_Ventas_Diarias'!$C$11:$C$610,$H96,'3_Ventas_Diarias'!$A$11:$A$610,">="&'4_Dashboard_DAMABIS'!$P$5,'3_Ventas_Diarias'!$A$11:$A$610,"<="&'4_Dashboard_DAMABIS'!$P$6)) | M96: =IF($H96="","",N($K96)+ROW()/1000000)
H97: =IF('2_Control_de_Stock'!$A$104="","",'2_Control_de_Stock'!$A$104) | I97: =IF('2_Control_de_Stock'!$A$104="","",'2_Control_de_Stock'!$B$104) | J97: =IF($H97="","",SUMIFS('3_Ventas_Diarias'!$E$11:$E$610,'3_Ventas_Diarias'!$C$11:$C$610,$H97,'3_Ventas_Diarias'!$A$11:$A$610,">="&'4_Dashboard_DAMABIS'!$P$5,'3_Ventas_Diarias'!$A$11:$A$610,"<="&'4_Dashboard_DAMABIS'!$P$6)) | K97: =IF($H97="","",SUMIFS('3_Ventas_Diarias'!$G$11:$G$610,'3_Ventas_Diarias'!$C$11:$C$610,$H97,'3_Ventas_Diarias'!$A$11:$A$610,">="&'4_Dashboard_DAMABIS'!$P$5,'3_Ventas_Diarias'!$A$11:$A$610,"<="&'4_Dashboard_DAMABIS'!$P$6)) | L97: =IF($H97="","",SUMIFS('3_Ventas_Diarias'!$J$11:$J$610,'3_Ventas_Diarias'!$C$11:$C$610,$H97,'3_Ventas_Diarias'!$A$11:$A$610,">="&'4_Dashboard_DAMABIS'!$P$5,'3_Ventas_Diarias'!$A$11:$A$610,"<="&'4_Dashboard_DAMABIS'!$P$6)) | M97: =IF($H97="","",N($K97)+ROW()/1000000)
H98: =IF('2_Control_de_Stock'!$A$105="","",'2_Control_de_Stock'!$A$105) | I98: =IF('2_Control_de_Stock'!$A$105="","",'2_Control_de_Stock'!$B$105) | J98: =IF($H98="","",SUMIFS('3_Ventas_Diarias'!$E$11:$E$610,'3_Ventas_Diarias'!$C$11:$C$610,$H98,'3_Ventas_Diarias'!$A$11:$A$610,">="&'4_Dashboard_DAMABIS'!$P$5,'3_Ventas_Diarias'!$A$11:$A$610,"<="&'4_Dashboard_DAMABIS'!$P$6)) | K98: =IF($H98="","",SUMIFS('3_Ventas_Diarias'!$G$11:$G$610,'3_Ventas_Diarias'!$C$11:$C$610,$H98,'3_Ventas_Diarias'!$A$11:$A$610,">="&'4_Dashboard_DAMABIS'!$P$5,'3_Ventas_Diarias'!$A$11:$A$610,"<="&'4_Dashboard_DAMABIS'!$P$6)) | L98: =IF($H98="","",SUMIFS('3_Ventas_Diarias'!$J$11:$J$610,'3_Ventas_Diarias'!$C$11:$C$610,$H98,'3_Ventas_Diarias'!$A$11:$A$610,">="&'4_Dashboard_DAMABIS'!$P$5,'3_Ventas_Diarias'!$A$11:$A$610,"<="&'4_Dashboard_DAMABIS'!$P$6)) | M98: =IF($H98="","",N($K98)+ROW()/1000000)
H99: =IF('2_Control_de_Stock'!$A$106="","",'2_Control_de_Stock'!$A$106) | I99: =IF('2_Control_de_Stock'!$A$106="","",'2_Control_de_Stock'!$B$106) | J99: =IF($H99="","",SUMIFS('3_Ventas_Diarias'!$E$11:$E$610,'3_Ventas_Diarias'!$C$11:$C$610,$H99,'3_Ventas_Diarias'!$A$11:$A$610,">="&'4_Dashboard_DAMABIS'!$P$5,'3_Ventas_Diarias'!$A$11:$A$610,"<="&'4_Dashboard_DAMABIS'!$P$6)) | K99: =IF($H99="","",SUMIFS('3_Ventas_Diarias'!$G$11:$G$610,'3_Ventas_Diarias'!$C$11:$C$610,$H99,'3_Ventas_Diarias'!$A$11:$A$610,">="&'4_Dashboard_DAMABIS'!$P$5,'3_Ventas_Diarias'!$A$11:$A$610,"<="&'4_Dashboard_DAMABIS'!$P$6)) | L99: =IF($H99="","",SUMIFS('3_Ventas_Diarias'!$J$11:$J$610,'3_Ventas_Diarias'!$C$11:$C$610,$H99,'3_Ventas_Diarias'!$A$11:$A$610,">="&'4_Dashboard_DAMABIS'!$P$5,'3_Ventas_Diarias'!$A$11:$A$610,"<="&'4_Dashboard_DAMABIS'!$P$6)) | M99: =IF($H99="","",N($K99)+ROW()/1000000)
H100: =IF('2_Control_de_Stock'!$A$107="","",'2_Control_de_Stock'!$A$107) | I100: =IF('2_Control_de_Stock'!$A$107="","",'2_Control_de_Stock'!$B$107) | J100: =IF($H100="","",SUMIFS('3_Ventas_Diarias'!$E$11:$E$610,'3_Ventas_Diarias'!$C$11:$C$610,$H100,'3_Ventas_Diarias'!$A$11:$A$610,">="&'4_Dashboard_DAMABIS'!$P$5,'3_Ventas_Diarias'!$A$11:$A$610,"<="&'4_Dashboard_DAMABIS'!$P$6)) | K100: =IF($H100="","",SUMIFS('3_Ventas_Diarias'!$G$11:$G$610,'3_Ventas_Diarias'!$C$11:$C$610,$H100,'3_Ventas_Diarias'!$A$11:$A$610,">="&'4_Dashboard_DAMABIS'!$P$5,'3_Ventas_Diarias'!$A$11:$A$610,"<="&'4_Dashboard_DAMABIS'!$P$6)) | L100: =IF($H100="","",SUMIFS('3_Ventas_Diarias'!$J$11:$J$610,'3_Ventas_Diarias'!$C$11:$C$610,$H100,'3_Ventas_Diarias'!$A$11:$A$610,">="&'4_Dashboard_DAMABIS'!$P$5,'3_Ventas_Diarias'!$A$11:$A$610,"<="&'4_Dashboard_DAMABIS'!$P$6)) | M100: =IF($H100="","",N($K100)+ROW()/1000000)
H101: =IF('2_Control_de_Stock'!$A$108="","",'2_Control_de_Stock'!$A$108) | I101: =IF('2_Control_de_Stock'!$A$108="","",'2_Control_de_Stock'!$B$108) | J101: =IF($H101="","",SUMIFS('3_Ventas_Diarias'!$E$11:$E$610,'3_Ventas_Diarias'!$C$11:$C$610,$H101,'3_Ventas_Diarias'!$A$11:$A$610,">="&'4_Dashboard_DAMABIS'!$P$5,'3_Ventas_Diarias'!$A$11:$A$610,"<="&'4_Dashboard_DAMABIS'!$P$6)) | K101: =IF($H101="","",SUMIFS('3_Ventas_Diarias'!$G$11:$G$610,'3_Ventas_Diarias'!$C$11:$C$610,$H101,'3_Ventas_Diarias'!$A$11:$A$610,">="&'4_Dashboard_DAMABIS'!$P$5,'3_Ventas_Diarias'!$A$11:$A$610,"<="&'4_Dashboard_DAMABIS'!$P$6)) | L101: =IF($H101="","",SUMIFS('3_Ventas_Diarias'!$J$11:$J$610,'3_Ventas_Diarias'!$C$11:$C$610,$H101,'3_Ventas_Diarias'!$A$11:$A$610,">="&'4_Dashboard_DAMABIS'!$P$5,'3_Ventas_Diarias'!$A$11:$A$610,"<="&'4_Dashboard_DAMABIS'!$P$6)) | M101: =IF($H101="","",N($K101)+ROW()/1000000)
...

Sheet 1_Compras_e_Inventario_Inicial
A1: DAMABIS · Compras e Inventario Inicial Registro de mercancía ingresada · Librería y Útiles Escolares
A6: 💰 GASTO TOTAL EN COMPRAS | C6: 📦 UNIDADES INGRESADAS | E6: 🧾 N° DE TRANSACCIONES | G6: 🏭 PROVEEDORES | H6: 📊 COSTO UNIT. PROMEDIO
A7: =SUM(I11:I510) | C7: =SUM(G11:G510) | E7: =SUMPRODUCT((B11:B510<>"")/COUNTIF(B11:B510,B11:B510&"")) | G7: =SUMPRODUCT((C11:C510<>"")/COUNTIF(C11:C510,C11:C510&"")) | H7: =IFERROR(SUM(I11:I510)/SUM(G11:G510),0)
A9: ✏️ Celdas en AZUL = captura manual. Celdas en NEGRO = fórmula automática (no escribir). Usa las listas desplegables en Proveedor, SKU y Categoría.
A10: Fecha | B10: ID Transacción | C10: Proveedor | D10: Código/SKU | E10: Descripción del Producto | F10: Categoría | G10: Cantidad Comprada | H10: Costo Unitario | I10: Costo Total
A11: 46236 | B11: C-2026-001 | C11: Distribuidora Lima Papel SAC | D11: PAP-001 | E11: Papel Bond A4 75g (millar) | F11: Papelería | G11: 30 | H11: 13.5 | I11: =IF(OR($G11="",$H11=""),"",$G11*$H11)
A12: 46236 | B12: C-2026-001 | C12: Distribuidora Lima Papel SAC | D12: CUA-010 | E12: Cuaderno A4 cuadriculado 100h | F12: Cuadernos | G12: 120 | H12: 4.2 | I12: =IF(OR($G12="",$H12=""),"",$G12*$H12)
A13: 46237 | B13: C-2026-002 | C13: Importadora Kawaii Perú EIRL | D13: KAW-101 | E13: Set stickers ajolote kawaii | F13: Kawaii/Escolar | G13: 200 | H13: 2.1 | I13: =IF(OR($G13="",$H13=""),"",$G13*$H13)
A14: 46237 | B14: C-2026-002 | C14: Importadora Kawaii Perú EIRL | D14: KAW-102 | E14: Lapicero gel pastel x6 | F14: Kawaii/Escolar | G14: 150 | H14: 5.4 | I14: =IF(OR($G14="",$H14=""),"",$G14*$H14)
A15: 46239 | B15: C-2026-003 | C15: Editorial Andina SAC | D15: LIB-201 | E15: Libro infantil ilustrado | F15: Libros | G15: 60 | H15: 18 | I15: =IF(OR($G15="",$H15=""),"",$G15*$H15)
A16: 46239 | B16: C-2026-003 | C16: Editorial Andina SAC | D16: LIB-202 | E16: Diccionario escolar | F16: Libros | G16: 25 | H16: 22 | I16: =IF(OR($G16="",$H16=""),"",$G16*$H16)
A17: 46242 | B17: C-2026-004 | C17: Arte & Color Distribuciones | D17: ART-301 | E17: Témpera 12 colores | F17: Arte | G17: 80 | H17: 7.8 | I17: =IF(OR($G17="",$H17=""),"",$G17*$H17)
A18: 46242 | B18: C-2026-004 | C18: Arte & Color Distribuciones | D18: ART-302 | E18: Block de dibujo A3 | F18: Arte | G18: 90 | H18: 6.3 | I18: =IF(OR($G18="",$H18=""),"",$G18*$H18)
A19: 46244 | B19: C-2026-005 | C19: Faber Perú SA | D19: ESC-401 | E19: Colores x24 largos | F19: Escritura | G19: 100 | H19: 11.5 | I19: =IF(OR($G19="",$H19=""),"",$G19*$H19)
A20: 46244 | B20: C-2026-005 | C20: Faber Perú SA | D20: ESC-402 | E20: Plumón resaltador pastel x4 | F20: Escritura | G20: 140 | H20: 4.9 | I20: =IF(OR($G20="",$H20=""),"",$G20*$H20)
A21: 46246 | B21: C-2026-006 | C21: Mayorista Mesa Redonda | D21: MOC-501 | E21: Mochila escolar estampada | F21: Mochilas y Loncheras | G21: 8 | H21: 32 | I21: =IF(OR($G21="",$H21=""),"",$G21*$H21)
A22: 46246 | B22: C-2026-006 | C22: Mayorista Mesa Redonda | D22: MOC-502 | E22: Lonchera térmica kawaii | F22: Mochilas y Loncheras | G22: 10 | H22: 21 | I22: =IF(OR($G22="",$H22=""),"",$G22*$H22)
... A30: 46266 | B30: C-2026-013 | C30: Distribuidora Lima Papel SAC | D30: CUA-011 | E30: Cuaderno anillado A5 80h | F30: Cuadernos | G30: 130 | H30: 3.9 | I30: =IF(OR($G30="",$H30=""),"",$G30*$H30)
I31: =IF(OR($G31="",$H31=""),"",$G31*$H31)
I32: =IF(OR($G32="",$H32=""),"",$G32*$H32)
I33: =IF(OR($G33="",$H33=""),"",$G33*$H33)
I34: =IF(OR($G34="",$H34=""),"",$G34*$H34)
I35: =IF(OR($G35="",$H35=""),"",$G35*$H35)
I36: =IF(OR($G36="",$H36=""),"",$G36*$H36)
I37: =IF(OR($G37="",$H37=""),"",$G37*$H37)
I38: =IF(OR($G38="",$H38=""),"",$G38*$H38)
I39: =IF(OR($G39="",$H39=""),"",$G39*$H39)
I40: =IF(OR($G40="",$H40=""),"",$G40*$H40)
I41: =IF(OR($G41="",$H41=""),"",$G41*$H41)
I42: =IF(OR($G42="",$H42=""),"",$G42*$H42)
... I510: =IF(OR($G510="",$H510=""),"",$G510*$H510)

Sheet 2_Control_de_Stock
A1: DAMABIS · Control de Stock Maestro de productos · Cálculo automático de existencias y márgenes
A6: 🧮 SKUs ACTIVOS | C6: 🏦 VALOR INVENTARIO (COSTO) | E6: 💵 VALOR INVENTARIO (VENTA) | G6: 📈 MARGEN PROMEDIO | I6: 🔴 SKUs SIN STOCK | K6: 🟠 SKUs POR REPONER | M6: 📦 UNIDADES EN TIENDA
A7: =COUNTIF(A11:A210,"?*") | C7: =SUM(L11:L210) | E7: =SUM(M11:M210) | G7: =IFERROR((SUM(M11:M210)-SUM(L11:L210))/SUM(M11:M210),0) | I7: =COUNTIF(I11:I210,"*SIN STOCK*") | K7: =COUNTIF(I11:I210,"*REPONER*") | M7: =SUM(G11:G210)
A9: ✏️ Captura manual (azul): SKU · Descripción · Categoría · Stock Inicial · Stock Mínimo · Precio de Venta. ⚙️ El resto se calcula solo desde las hojas 1 y 3.
A10: Código/SKU | B10: Descripción | C10: Categoría | D10: Stock Inicial | E10: Entradas Totales | F10: Salidas Totales | G10: Stock Actual | H10: Stock Mínimo | I10: Alerta de Estado | J10: Costo Promedio Unit. | K10: Precio de Venta | L10: Valor Total a Costo | M10: Valor Total a Venta | N10: % Margen Bruto
A11: PAP-001 | B11: Papel Bond A4 75g (millar) | C11: Papelería | D11: 5 | E11: =IF($A11="","",SUMIFS('1_Compras_e_Inventario_Inicial'!$G$11:$G$510,'1_Compras_e_Inventario_Inicial'!$D$11:$D$510,$A11)) | F11: =IF($A11="","",SUMIFS('3_Ventas_Diarias'!$E$11:$E$610,'3_Ventas_Diarias'!$C$11:$C$610,$A11)) | G11: =IF($A11="","",N($D11)+N($E11)-N($F11)) | H11: 4 | I11: =IF($A11="","",IF($G11<=0,"🔴 SIN STOCK",IF($G11<=$H11,"🟠 REPONER",IF($G11<=$H11*1.5,"🟡 VIGILAR","🟢 OK")))) | J11: =IF($A11="","",IFERROR(SUMIFS('1_Compras_e_Inventario_Inicial'!$I$11:$I$510,'1_Compras_e_Inventario_Inicial'!$D$11:$D$510,$A11)/SUMIFS('1_Compras_e_Inventario_Inicial'!$G$11:$G$510,'1_Compras_e_Inventario_Inicial'!$D$11:$D$510,$A11),0)) | K11: 19.9 | L11: =IF($A11="","",$G11*$J11) | M11: =IF($A11="","",$G11*$K11) | N11: =IF($A11="","",IFERROR(($K11-$J11)/$K11,0))
A12: PAP-002 | B12: Cartulina de colores (pliego) | C12: Papelería | D12: 50 | E12: =IF($A12="","",SUMIFS('1_Compras_e_Inventario_Inicial'!$G$11:$G$510,'1_Compras_e_Inventario_Inicial'!$D$11:$D$510,$A12)) | F12: =IF($A12="","",SUMIFS('3_Ventas_Diarias'!$E$11:$E$610,'3_Ventas_Diarias'!$C$11:$C$610,$A12)) | G12: =IF($A12="","",N($D12)+N($E12)-N($F12)) | H12: 60 | I12: =IF($A12="","",IF($G12<=0,"🔴 SIN STOCK",IF($G12<=$H12,"🟠 REPONER",IF($G12<=$H12*1.5,"🟡 VIGILAR","🟢 OK")))) | J12: =IF($A12="","",IFERROR(SUMIFS('1_Compras_e_Inventario_Inicial'!$I$11:$I$510,'1_Compras_e_Inventario_Inicial'!$D$11:$D$510,$A12)/SUMIFS('1_Compras_e_Inventario_Inicial'!$G$11:$G$510,'1_Compras_e_Inventario_Inicial'!$D$11:$D$510,$A12),0)) | K12: 1.5 | L12: =IF($A12="","",$G12*$J12) | M12: =IF($A12="","",$G12*$K12) | N12: =IF($A12="","",IFERROR(($K12-$J12)/$K12,0))
A13: CUA-010 | B13: Cuaderno A4 cuadriculado 100h | C13: Cuadernos | D13: 20 | E13: =IF($A13="","",SUMIFS('1_Compras_e_Inventario_Inicial'!$G$11:$G$510,'1_Compras_e_Inventario_Inicial'!$D$11:$D$510,$A13)) | F13: =IF($A13="","",SUMIFS('3_Ventas_Diarias'!$E$11:$E$610,'3_Ventas_Diarias'!$C$11:$C$610,$A13)) | G13: =IF($A13="","",N($D13)+N($E13)-N($F13)) | H13: 30 | I13: =IF($A13="","",IF($G13<=0,"🔴 SIN STOCK",IF($G13<=$H13,"🟠 REPONER",IF($G13<=$H13*1.5,"🟡 VIGILAR","🟢 OK")))) | J13: =IF($A13="","",IFERROR(SUMIFS('1_Compras_e_Inventario_Inicial'!$I$11:$I$510,'1_Compras_e_Inventario_Inicial'!$D$11:$D$510,$A13)/SUMIFS('1_Compras_e_Inventario_Inicial'!$G$11:$G$510,'1_Compras_e_Inventario_Inicial'!$D$11:$D$510,$A13),0)) | K13: 6.5 | L13: =IF($A13="","",$G13*$J13) | M13: =IF($A13="","",$G13*$K13) | N13: =IF($A13="","",IFERROR(($K13-$J13)/$K13,0))
A14: CUA-011 | B14: Cuaderno anillado A5 80h | C14: Cuadernos | D14: 15 | E14: =IF($A14="","",SUMIFS('1_Compras_e_Inventario_Inicial'!$G$11:$G$510,'1_Compras_e_Inventario_Inicial'!$D$11:$D$510,$A14)) | F14: =IF($A14="","",SUMIFS('3_Ventas_Diarias'!$E$11:$E$610,'3_Ventas_Diarias'!$C$11:$C$610,$A14)) | G14: =IF($A14="","",N($D14)+N($E14)-N($F14)) | H14: 25 | I14: =IF($A14="","",IF($G14<=0,"🔴 SIN STOCK",IF($G14<=$H14,"🟠 REPONER",IF($G14<=$H14*1.5,"🟡 VIGILAR","🟢 OK")))) | J14: =IF($A14="","",IFERROR(SUMIFS('1_Compras_e_Inventario_Inicial'!$I$11:$I$510,'1_Compras_e_Inventario_Inicial'!$D$11:$D$510,$A14)/SUMIFS('1_Compras_e_Inventario_Inicial'!$G$11:$G$510,'1_Compras_e_Inventario_Inicial'!$D$11:$D$510,$A14),0)) | K14: 5.9 | L14: =IF($A14="","",$G14*$J14) | M14: =IF($A14="","",$G14*$K14) | N14: =IF($A14="","",IFERROR(($K14-$J14)/$K14,0))
A15: KAW-101 | B15: Set stickers ajolote kawaii | C15: Kawaii/Escolar | D15: 30 | E15: =IF($A15="","",SUMIFS('1_Compras_e_Inventario_Inicial'!$G$11:$G$510,'1_Compras_e_Inventario_Inicial'!$D$11:$D$510,$A15)) | F15: =IF($A15="","",SUMIFS('3_Ventas_Diarias'!$E$11:$E$610,'3_Ventas_Diarias'!$C$11:$C$610,$A15)) | G15: =IF($A15="","",N($D15)+N($E15)-N($F15)) | H15: 40 | I15: =IF($A15="","",IF($G15<=0,"🔴 SIN STOCK",IF($G15<=$H15,"🟠 REPONER",IF($G15<=$H15*1.5,"🟡 VIGILAR","🟢 OK")))) | J15: =IF($A15="","",IFERROR(SUMIFS('1_Compras_e_Inventario_Inicial'!$I$11:$I$510,'1_Compras_e_Inventario_Inicial'!$D$11:$D$510,$A15)/SUMIFS('1_Compras_e_Inventario_Inicial'!$G$11:$G$510,'1_Compras_e_Inventario_Inicial'!$D$11:$D$510,$A15),0)) | K15: 4.5 | L15: =IF($A15="","",$G15*$J15) | M15: =IF($A15="","",$G15*$K15) | N15: =IF($A15="","",IFERROR(($K15-$J15)/$K15,0))
A16: KAW-102 | B16: Lapicero gel pastel x6 | C16: Kawaii/Escolar | D16: 25 | E16: =IF($A16="","",SUMIFS('1_Compras_e_Inventario_Inicial'!$G$11:$G$510,'1_Compras_e_Inventario_Inicial'!$D$11:$D$510,$A16)) | F16: =IF($A16="","",SUMIFS('3_Ventas_Diarias'!$E$11:$E$610,'3_Ventas_Diarias'!$C$11:$C$610,$A16)) | G16: =IF($A16="","",N($D16)+N($E16)-N($F16)) | H16: 30 | I16: =IF($A16="","",IF($G16<=0,"🔴 SIN STOCK",IF($G16<=$H16,"🟠 REPONER",IF($G16<=$H16*1.5,"🟡 VIGILAR","🟢 OK")))) | J16: =IF($A16="","",IFERROR(SUMIFS('1_Compras_e_Inventario_Inicial'!$I$11:$I$510,'1_Compras_e_Inventario_Inicial'!$D$11:$D$510,$A16)/SUMIFS('1_Compras_e_Inventario_Inicial'!$G$11:$G$510,'1_Compras_e_Inventario_Inicial'!$D$11:$D$510,$A16),0)) | K16: 9.9 | L16: =IF($A16="","",$G16*$J16) | M16: =IF($A16="","",$G16*$K16) | N16: =IF($A16="","",IFERROR(($K16-$J16)/$K16,0))
A17: KAW-103 | B17: Peluche llavero ajolote | C17: Kawaii/Escolar | D17: 10 | E17: =IF($A17="","",SUMIFS('1_Compras_e_Inventario_Inicial'!$G$11:$G$510,'1_Compras_e_Inventario_Inicial'!$D$11:$D$510,$A17)) | F17: =IF($A17="","",SUMIFS('3_Ventas_Diarias'!$E$11:$E$610,'3_Ventas_Diarias'!$C$11:$C$610,$A17)) | G17: =IF($A17="","",N($D17)+N($E17)-N($F17)) | H17: 20 | I17: =IF($A17="","",IF($G17<=0,"🔴 SIN STOCK",IF($G17<=$H17,"🟠 REPONER",IF($G17<=$H17*1.5,"🟡 VIGILAR","🟢 OK")))) | J17: =IF($A17="","",IFERROR(SUMIFS('1_Compras_e_Inventario_Inicial'!$I$11:$I$510,'1_Compras_e_Inventario_Inicial'!$D$11:$D$510,$A17)/SUMIFS('1_Compras_e_Inventario_Inicial'!$G$11:$G$510,'1_Compras_e_Inventario_Inicial'!$D$11:$D$510,$A17),0)) | K17: 16.9 | L17: =IF($A17="","",$G17*$J17) | M17: =IF($A17="","",$G17*$K17) | N17: =IF($A17="","",IFERROR(($K17-$J17)/$K17,0))
A18: LIB-201 | B18: Libro infantil ilustrado | C18: Libros | D18: 8 | E18: =IF($A18="","",SUMIFS('1_Compras_e_Inventario_Inicial'!$G$11:$G$510,'1_Compras_e_Inventario_Inicial'!$D$11:$D$510,$A18)) | F18: =IF($A18="","",SUMIFS('3_Ventas_Diarias'!$E$11:$E$610,'3_Ventas_Diarias'!$C$11:$C$610,$A18)) | G18: =IF($A18="","",N($D18)+N($E18)-N($F18)) | H18: 12 | I18: =IF($A18="","",IF($G18<=0,"🔴 SIN STOCK",IF($G18<=$H18,"🟠 REPONER",IF($G18<=$H18*1.5,"🟡 VIGILAR","🟢 OK")))) | J18: =IF($A18="","",IFERROR(SUMIFS('1_Compras_e_Inventario_Inicial'!$I$11:$I$510,'1_Compras_e_Inventario_Inicial'!$D$11:$D$510,$A18)/SUMIFS('1_Compras_e_Inventario_Inicial'!$G$11:$G$510,'1_Compras_e_Inventario_Inicial'!$D$11:$D$510,$A18),0)) | K18: 29.9 | L18: =IF($A18="","",$G18*$J18) | M18: =IF($A18="","",$G18*$K18) | N18: =IF($A18="","",IFERROR(($K18-$J18)/$K18,0))
A19: LIB-202 | B19: Diccionario escolar | C19: Libros | D19: 5 | E19: =IF($A19="","",SUMIFS('1_Compras_e_Inventario_Inicial'!$G$11:$G$510,'1_Compras_e_Inventario_Inicial'!$D$11:$D$510,$A19)) | F19: =IF($A19="","",SUMIFS('3_Ventas_Diarias'!$E$11:$E$610,'3_Ventas_Diarias'!$C$11:$C$610,$A19)) | G19: =IF($A19="","",N($D19)+N($E19)-N($F19)) | H19: 8 | I19: =IF($A19="","",IF($G19<=0,"🔴 SIN STOCK",IF($G19<=$H19,"🟠 REPONER",IF($G19<=$H19*1.5,"🟡 VIGILAR","🟢 OK")))) | J19: =IF($A19="","",IFERROR(SUMIFS('1_Compras_e_Inventario_Inicial'!$I$11:$I$510,'1_Compras_e_Inventario_Inicial'!$D$11:$D$510,$A19)/SUMIFS('1_Compras_e_Inventario_Inicial'!$G$11:$G$510,'1_Compras_e_Inventario_Inicial'!$D$11:$D$510,$A19),0)) | K19: 34.9 | L19: =IF($A19="","",$G19*$J19) | M19: =IF($A19="","",$G19*$K19) | N19: =IF($A19="","",IFERROR(($K19-$J19)/$K19,0))
A20: LIB-203 | B20: Plan lector secundaria | C20: Libros | D20: 6 | E20: =IF($A20="","",SUMIFS('1_Compras_e_Inventario_Inicial'!$G$11:$G$510,'1_Compras_e_Inventario_Inicial'!$D$11:$D$510,$A20)) | F20: =IF($A20="","",SUMIFS('3_Ventas_Diarias'!$E$11:$E$610,'3_Ventas_Diarias'!$C$11:$C$610,$A20)) | G20: =IF($A20="","",N($D20)+N($E20)-N($F20)) | H20: 10 | I20: =IF($A20="","",IF($G20<=0,"🔴 SIN STOCK",IF($G20<=$H20,"🟠 REPONER",IF($G20<=$H20*1.5,"🟡 VIGILAR","🟢 OK")))) | J20: =IF($A20="","",IFERROR(SUMIFS('1_Compras_e_Inventario_Inicial'!$I$11:$I$510,'1_Compras_e_Inventario_Inicial'!$D$11:$D$510,$A20)/SUMIFS('1_Compras_e_Inventario_Inicial'!$G$11:$G$510,'1_Compras_e_Inventario_Inicial'!$D$11:$D$510,$A20),0)) | K20: 26.9 | L20: =IF($A20="","",$G20*$J20) | M20: =IF($A20="","",$G20*$K20) | N20: =IF($A20="","",IFERROR(($K20-$J20)/$K20,0))
A21: ART-301 | B21: Témpera 12 colores | C21: Arte | D21: 12 | E21: =IF($A21="","",SUMIFS('1_Compras_e_Inventario_Inicial'!$G$11:$G$510,'1_Compras_e_Inventario_Inicial'!$D$11:$D$510,$A21)) | F21: =IF($A21="","",SUMIFS('3_Ventas_Diarias'!$E$11:$E$610,'3_Ventas_Diarias'!$C$11:$C$610,$A21)) | G21: =IF($A21="","",N($D21)+N($E21)-N($F21)) | H21: 20 | I21: =IF($A21="","",IF($G21<=0,"🔴 SIN STOCK",IF($G21<=$H21,"🟠 REPONER",IF($G21<=$H21*1.5,"🟡 VIGILAR","🟢 OK")))) | J21: =IF($A21="","",IFERROR(SUMIFS('1_Compras_e_Inventario_Inicial'!$I$11:$I$510,'1_Compras_e_Inventario_Inicial'!$D$11:$D$510,$A21)/SUMIFS('1_Compras_e_Inventario_Inicial'!$G$11:$G$510,'1_Compras_e_Inventario_Inicial'!$D$11:$D$510,$A21),0)) | K21: 13.9 | L21: =IF($A21="","",$G21*$J21) | M21: =IF($A21="","",$G21*$K21) | N21: =IF($A21="","",IFERROR(($K21-$J21)/$K21,0))
A22: ART-302 | B22: Block de dibujo A3 | C22: Arte | D22: 15 | E22: =IF($A22="","",SUMIFS('1_Compras_e_Inventario_Inicial'!$G$11:$G$510,'1_Compras_e_Inventario_Inicial'!$D$11:$D$510,$A22)) | F22: =IF($A22="","",SUMIFS('3_Ventas_Diarias'!$E$11:$E$610,'3_Ventas_Diarias'!$C$11:$C$610,$A22)) | G22: =IF($A22="","",N($D22)+N($E22)-N($F22)) | H22: 20 | I22: =IF($A22="","",IF($G22<=0,"🔴 SIN STOCK",IF($G22<=$H22,"🟠 REPONER",IF($G22<=$H22*1.5,"🟡 VIGILAR","🟢 OK")))) | J22: =IF($A22="","",IFERROR(SUMIFS('1_Compras_e_Inventario_Inicial'!$I$11:$I$510,'1_Compras_e_Inventario_Inicial'!$D$11:$D$510,$A22)/SUMIFS('1_Compras_e_Inventario_Inicial'!$G$11:$G$510,'1_Compras_e_Inventario_Inicial'!$D$11:$D$510,$A22),0)) | K22: 10.9 | L22: =IF($A22="","",$G22*$J22) | M22: =IF($A22="","",$G22*$K22) | N22: =IF($A22="","",IFERROR(($K22-$J22)/$K22,0))
... A31: KAW-104 | B31: Cuaderno ajolote tapa dura A5 | C31: Kawaii/Escolar | D31: 0 | E31: =IF($A31="","",SUMIFS('1_Compras_e_Inventario_Inicial'!$G$11:$G$510,'1_Compras_e_Inventario_Inicial'!$D$11:$D$510,$A31)) | F31: =IF($A31="","",SUMIFS('3_Ventas_Diarias'!$E$11:$E$610,'3_Ventas_Diarias'!$C$11:$C$610,$A31)) | G31: =IF($A31="","",N($D31)+N($E31)-N($F31)) | H31: 12 | I31: =IF($A31="","",IF($G31<=0,"🔴 SIN STOCK",IF($G31<=$H31,"🟠 REPONER",IF($G31<=$H31*1.5,"🟡 VIGILAR","🟢 OK")))) | J31: =IF($A31="","",IFERROR(SUMIFS('1_Compras_e_Inventario_Inicial'!$I$11:$I$510,'1_Compras_e_Inventario_Inicial'!$D$11:$D$510,$A31)/SUMIFS('1_Compras_e_Inventario_Inicial'!$G$11:$G$510,'1_Compras_e_Inventario_Inicial'!$D$11:$D$510,$A31),0)) | K31: 22.9 | L31: =IF($A31="","",$G31*$J31) | M31: =IF($A31="","",$G31*$K31) | N31: =IF($A31="","",IFERROR(($K31-$J31)/$K31,0))
E32: =IF($A32="","",SUMIFS('1_Compras_e_Inventario_Inicial'!$G$11:$G$510,'1_Compras_e_Inventario_Inicial'!$D$11:$D$510,$A32)) | F32: =IF($A32="","",SUMIFS('3_Ventas_Diarias'!$E$11:$E$610,'3_Ventas_Diarias'!$C$11:$C$610,$A32)) | G32: =IF($A32="","",N($D32)+N($E32)-N($F32)) | I32: =IF($A32="","",IF($G32<=0,"🔴 SIN STOCK",IF($G32<=$H32,"🟠 REPONER",IF($G32<=$H32*1.5,"🟡 VIGILAR","🟢 OK")))) | J32: =IF($A32="","",IFERROR(SUMIFS('1_Compras_e_Inventario_Inicial'!$I$11:$I$510,'1_Compras_e_Inventario_Inicial'!$D$11:$D$510,$A32)/SUMIFS('1_Compras_e_Inventario_Inicial'!$G$11:$G$510,'1_Compras_e_Inventario_Inicial'!$D$11:$D$510,$A32),0)) | L32: =IF($A32="","",$G32*$J32) | M32: =IF($A32="","",$G32*$K32) | N32: =IF($A32="","",IFERROR(($K32-$J32)/$K32,0))
E33: =IF($A33="","",SUMIFS('1_Compras_e_Inventario_Inicial'!$G$11:$G$510,'1_Compras_e_Inventario_Inicial'!$D$11:$D$510,$A33)) | F33: =IF($A33="","",SUMIFS('3_Ventas_Diarias'!$E$11:$E$610,'3_Ventas_Diarias'!$C$11:$C$610,$A33)) | G33: =IF($A33="","",N($D33)+N($E33)-N($F33)) | I33: =IF($A33="","",IF($G33<=0,"🔴 SIN STOCK",IF($G33<=$H33,"🟠 REPONER",IF($G33<=$H33*1.5,"🟡 VIGILAR","🟢 OK")))) | J33: =IF($A33="","",IFERROR(SUMIFS('1_Compras_e_Inventario_Inicial'!$I$11:$I$510,'1_Compras_e_Inventario_Inicial'!$D$11:$D$510,$A33)/SUMIFS('1_Compras_e_Inventario_Inicial'!$G$11:$G$510,'1_Compras_e_Inventario_Inicial'!$D$11:$D$510,$A33),0)) | L33: =IF($A33="","",$G33*$J33) | M33: =IF($A33="","",$G33*$K33) | N33: =IF($A33="","",IFERROR(($K33-$J33)/$K33,0))
E34: =IF($A34="","",SUMIFS('1_Compras_e_Inventario_Inicial'!$G$11:$G$510,'1_Compras_e_Inventario_Inicial'!$D$11:$D$510,$A34)) | F34: =IF($A34="","",SUMIFS('3_Ventas_Diarias'!$E$11:$E$610,'3_Ventas_Diarias'!$C$11:$C$610,$A34)) | G34: =IF($A34="","",N($D34)+N($E34)-N($F34)) | I34: =IF($A34="","",IF($G34<=0,"🔴 SIN STOCK",IF($G34<=$H34,"🟠 REPONER",IF($G34<=$H34*1.5,"🟡 VIGILAR","🟢 OK")))) | J34: =IF($A34="","",IFERROR(SUMIFS('1_Compras_e_Inventario_Inicial'!$I$11:$I$510,'1_Compras_e_Inventario_Inicial'!$D$11:$D$510,$A34)/SUMIFS('1_Compras_e_Inventario_Inicial'!$G$11:$G$510,'1_Compras_e_Inventario_Inicial'!$D$11:$D$510,$A34),0)) | L34: =IF($A34="","",$G34*$J34) | M34: =IF($A34="","",$G34*$K34) | N34: =IF($A34="","",IFERROR(($K34-$J34)/$K34,0))
E35: =IF($A35="","",SUMIFS('1_Compras_e_Inventario_Inicial'!$G$11:$G$510,'1_Compras_e_Inventario_Inicial'!$D$11:$D$510,$A35)) | F35: =IF($A35="","",SUMIFS('3_Ventas_Diarias'!$E$11:$E$610,'3_Ventas_Diarias'!$C$11:$C$610,$A35)) | G35: =IF($A35="","",N($D35)+N($E35)-N($F35)) | I35: =IF($A35="","",IF($G35<=0,"🔴 SIN STOCK",IF($G35<=$H35,"🟠 REPONER",IF($G35<=$H35*1.5,"🟡 VIGILAR","🟢 OK")))) | J35: =IF($A35="","",IFERROR(SUMIFS('1_Compras_e_Inventario_Inicial'!$I$11:$I$510,'1_Compras_e_Inventario_Inicial'!$D$11:$D$510,$A35)/SUMIFS('1_Compras_e_Inventario_Inicial'!$G$11:$G$510,'1_Compras_e_Inventario_Inicial'!$D$11:$D$510,$A35),0)) | L35: =IF($A35="","",$G35*$J35) | M35: =IF($A35="","",$G35*$K35) | N35: =IF($A35="","",IFERROR(($K35-$J35)/$K35,0))
E36: =IF($A36="","",SUMIFS('1_Compras_e_Inventario_Inicial'!$G$11:$G$510,'1_Compras_e_Inventario_Inicial'!$D$11:$D$510,$A36)) | F36: =IF($A36="","",SUMIFS('3_Ventas_Diarias'!$E$11:$E$610,'3_Ventas_Diarias'!$C$11:$C$610,$A36)) | G36: =IF($A36="","",N($D36)+N($E36)-N($F36)) | I36: =IF($A36="","",IF($G36<=0,"🔴 SIN STOCK",IF($G36<=$H36,"🟠 REPONER",IF($G36<=$H36*1.5,"🟡 VIGILAR","🟢 OK")))) | J36: =IF($A36="","",IFERROR(SUMIFS('1_Compras_e_Inventario_Inicial'!$I$11:$I$510,'1_Compras_e_Inventario_Inicial'!$D$11:$D$510,$A36)/SUMIFS('1_Compras_e_Inventario_Inicial'!$G$11:$G$510,'1_Compras_e_Inventario_Inicial'!$D$11:$D$510,$A36),0)) | L36: =IF($A36="","",$G36*$J36) | M36: =IF($A36="","",$G36*$K36) | N36: =IF($A36="","",IFERROR(($K36-$J36)/$K36,0))
E37: =IF($A37="","",SUMIFS('1_Compras_e_Inventario_Inicial'!$G$11:$G$510,'1_Compras_e_Inventario_Inicial'!$D$11:$D$510,$A37)) | F37: =IF($A37="","",SUMIFS('3_Ventas_Diarias'!$E$11:$E$610,'3_Ventas_Diarias'!$C$11:$C$610,$A37)) | G37: =IF($A37="","",N($D37)+N($E37)-N($F37)) | I37: =IF($A37="","",IF($G37<=0,"🔴 SIN STOCK",IF($G37<=$H37,"🟠 REPONER",IF($G37<=$H37*1.5,"🟡 VIGILAR","🟢 OK")))) | J37: =IF($A37="","",IFERROR(SUMIFS('1_Compras_e_Inventario_Inicial'!$I$11:$I$510,'1_Compras_e_Inventario_Inicial'!$D$11:$D$510,$A37)/SUMIFS('1_Compras_e_Inventario_Inicial'!$G$11:$G$510,'1_Compras_e_Inventario_Inicial'!$D$11:$D$510,$A37),0)) | L37: =IF($A37="","",$G37*$J37) | M37: =IF($A37="","",$G37*$K37) | N37: =IF($A37="","",IFERROR(($K37-$J37)/$K37,0))
E38: =IF($A38="","",SUMIFS('1_Compras_e_Inventario_Inicial'!$G$11:$G$510,'1_Compras_e_Inventario_Inicial'!$D$11:$D$510,$A38)) | F38: =IF($A38="","",SUMIFS('3_Ventas_Diarias'!$E$11:$E$610,'3_Ventas_Diarias'!$C$11:$C$610,$A38)) | G38: =IF($A38="","",N($D38)+N($E38)-N($F38)) | I38: =IF($A38="","",IF($G38<=0,"🔴 SIN STOCK",IF($G38<=$H38,"🟠 REPONER",IF($G38<=$H38*1.5,"🟡 VIGILAR","🟢 OK")))) | J38: =IF($A38="","",IFERROR(SUMIFS('1_Compras_e_Inventario_Inicial'!$I$11:$I$510,'1_Compras_e_Inventario_Inicial'!$D$11:$D$510,$A38)/SUMIFS('1_Compras_e_Inventario_Inicial'!$G$11:$G$510,'1_Compras_e_Inventario_Inicial'!$D$11:$D$510,$A38),0)) | L38: =IF($A38="","",$G38*$J38) | M38: =IF($A38="","",$G38*$K38) | N38: =IF($A38="","",IFERROR(($K38-$J38)/$K38,0))
E39: =IF($A39="","",SUMIFS('1_Compras_e_Inventario_Inicial'!$G$11:$G$510,'1_Compras_e_Inventario_Inicial'!$D$11:$D$510,$A39)) | F39: =IF($A39="","",SUMIFS('3_Ventas_Diarias'!$E$11:$E$610,'3_Ventas_Diarias'!$C$11:$C$610,$A39)) | G39: =IF($A39="","",N($D39)+N($E39)-N($F39)) | I39: =IF($A39="","",IF($G39<=0,"🔴 SIN STOCK",IF($G39<=$H39,"🟠 REPONER",IF($G39<=$H39*1.5,"🟡 VIGILAR","🟢 OK")))) | J39: =IF($A39="","",IFERROR(SUMIFS('1_Compras_e_Inventario_Inicial'!$I$11:$I$510,'1_Compras_e_Inventario_Inicial'!$D$11:$D$510,$A39)/SUMIFS('1_Compras_e_Inventario_Inicial'!$G$11:$G$510,'1_Compras_e_Inventario_Inicial'!$D$11:$D$510,$A39),0)) | L39: =IF($A39="","",$G39*$J39) | M39: =IF($A39="","",$G39*$K39) | N39: =IF($A39="","",IFERROR(($K39-$J39)/$K39,0))
E40: =IF($A40="","",SUMIFS('1_Compras_e_Inventario_Inicial'!$G$11:$G$510,'1_Compras_e_Inventario_Inicial'!$D$11:$D$510,$A40)) | F40: =IF($A40="","",SUMIFS('3_Ventas_Diarias'!$E$11:$E$610,'3_Ventas_Diarias'!$C$11:$C$610,$A40)) | G40: =IF($A40="","",N($D40)+N($E40)-N($F40)) | I40: =IF($A40="","",IF($G40<=0,"🔴 SIN STOCK",IF($G40<=$H40,"🟠 REPONER",IF($G40<=$H40*1.5,"🟡 VIGILAR","🟢 OK")))) | J40: =IF($A40="","",IFERROR(SUMIFS('1_Compras_e_Inventario_Inicial'!$I$11:$I$510,'1_Compras_e_Inventario_Inicial'!$D$11:$D$510,$A40)/SUMIFS('1_Compras_e_Inventario_Inicial'!$G$11:$G$510,'1_Compras_e_Inventario_Inicial'!$D$11:$D$510,$A40),0)) | L40: =IF($A40="","",$G40*$J40) | M40: =IF($A40="","",$G40*$K40) | N40: =IF($A40="","",IFERROR(($K40-$J40)/$K40,0))
E41: =IF($A41="","",SUMIFS('1_Compras_e_Inventario_Inicial'!$G$11:$G$510,'1_Compras_e_Inventario_Inicial'!$D$11:$D$510,$A41)) | F41: =IF($A41="","",SUMIFS('3_Ventas_Diarias'!$E$11:$E$610,'3_Ventas_Diarias'!$C$11:$C$610,$A41)) | G41: =IF($A41="","",N($D41)+N($E41)-N($F41)) | I41: =IF($A41="","",IF($G41<=0,"🔴 SIN STOCK",IF($G41<=$H41,"🟠 REPONER",IF($G41<=$H41*1.5,"🟡 VIGILAR","🟢 OK")))) | J41: =IF($A41="","",IFERROR(SUMIFS('1_Compras_e_Inventario_Inicial'!$I$11:$I$510,'1_Compras_e_Inventario_Inicial'!$D$11:$D$510,$A41)/SUMIFS('1_Compras_e_Inventario_Inicial'!$G$11:$G$510,'1_Compras_e_Inventario_Inicial'!$D$11:$D$510,$A41),0)) | L41: =IF($A41="","",$G41*$J41) | M41: =IF($A41="","",$G41*$K41) | N41: =IF($A41="","",IFERROR(($K41-$J41)/$K41,0))
E42: =IF($A42="","",SUMIFS('1_Compras_e_Inventario_Inicial'!$G$11:$G$510,'1_Compras_e_Inventario_Inicial'!$D$11:$D$510,$A42)) | F42: =IF($A42="","",SUMIFS('3_Ventas_Diarias'!$E$11:$E$610,'3_Ventas_Diarias'!$C$11:$C$610,$A42)) | G42: =IF($A42="","",N($D42)+N($E42)-N($F42)) | I42: =IF($A42="","",IF($G42<=0,"🔴 SIN STOCK",IF($G42<=$H42,"🟠 REPONER",IF($G42<=$H42*1.5,"🟡 VIGILAR","🟢 OK")))) | J42: =IF($A42="","",IFERROR(SUMIFS('1_Compras_e_Inventario_Inicial'!$I$11:$I$510,'1_Compras_e_Inventario_Inicial'!$D$11:$D$510,$A42)/SUMIFS('1_Compras_e_Inventario_Inicial'!$G$11:$G$510,'1_Compras_e_Inventario_Inicial'!$D$11:$D$510,$A42),0)) | L42: =IF($A42="","",$G42*$J42) | M42: =IF($A42="","",$G42*$K42) | N42: =IF($A42="","",IFERROR(($K42-$J42)/$K42,0))
E43: =IF($A43="","",SUMIFS('1_Compras_e_Inventario_Inicial'!$G$11:$G$510,'1_Compras_e_Inventario_Inicial'!$D$11:$D$510,$A43)) | F43: =IF($A43="","",SUMIFS('3_Ventas_Diarias'!$E$11:$E$610,'3_Ventas_Diarias'!$C$11:$C$610,$A43)) | G43: =IF($A43="","",N($D43)+N($E43)-N($F43)) | I43: =IF($A43="","",IF($G43<=0,"🔴 SIN STOCK",IF($G43<=$H43,"🟠 REPONER",IF($G43<=$H43*1.5,"🟡 VIGILAR","🟢 OK")))) | J43: =IF($A43="","",IFERROR(SUMIFS('1_Compras_e_Inventario_Inicial'!$I$11:$I$510,'1_Compras_e_Inventario_Inicial'!$D$11:$D$510,$A43)/SUMIFS('1_Compras_e_Inventario_Inicial'!$G$11:$G$510,'1_Compras_e_Inventario_Inicial'!$D$11:$D$510,$A43),0)) | L43: =IF($A43="","",$G43*$J43) | M43: =IF($A43="","",$G43*$K43) | N43: =IF($A43="","",IFERROR(($K43-$J43)/$K43,0))
... E210: =IF($A210="","",SUMIFS('1_Compras_e_Inventario_Inicial'!$G$11:$G$510,'1_Compras_e_Inventario_Inicial'!$D$11:$D$510,$A210)) | F210: =IF($A210="","",SUMIFS('3_Ventas_Diarias'!$E$11:$E$610,'3_Ventas_Diarias'!$C$11:$C$610,$A210)) | G210: =IF($A210="","",N($D210)+N($E210)-N($F210)) | I210: =IF($A210="","",IF($G210<=0,"🔴 SIN STOCK",IF($G210<=$H210,"🟠 REPONER",IF($G210<=$H210*1.5,"🟡 VIGILAR","🟢 OK")))) | J210: =IF($A210="","",IFERROR(SUMIFS('1_Compras_e_Inventario_Inicial'!$I$11:$I$510,'1_Compras_e_Inventario_Inicial'!$D$11:$D$510,$A210)/SUMIFS('1_Compras_e_Inventario_Inicial'!$G$11:$G$510,'1_Compras_e_Inventario_Inicial'!$D$11:$D$510,$A210),0)) | L210: =IF($A210="","",$G210*$J210) | M210: =IF($A210="","",$G210*$K210) | N210: =IF($A210="","",IFERROR(($K210-$J210)/$K210,0))

Sheet 3_Ventas_Diarias
A1: DAMABIS · Ventas Diarias Registro de ticket por ticket · Costo y ganancia automáticos
A6: 🛍️ VENTAS ACUMULADAS | C6: 💚 GANANCIA BRUTA | E6: 📦 UNIDADES VENDIDAS | G6: 🎟️ TICKET PROMEDIO | I6: 📊 MARGEN SOBRE VENTAS
A7: =SUM(G11:G610) | C7: =SUM(J11:J610) | E7: =SUM(E11:E610) | G7: =IFERROR(SUM(G11:G610)/SUMPRODUCT((B11:B610<>"")/COUNTIF(B11:B610,B11:B610&"")),0) | I7: =IFERROR(SUM(J11:J610)/SUM(G11:G610),0)
A9: ✏️ Captura manual (azul): Fecha · N° Ticket · SKU · Cantidad · Método de Pago. ⚙️ Descripción, Precio, Total, COGS, Ganancia y Categoría se llenan solos con BUSCARV.
A10: Fecha | B10: N° Ticket/Comprobante | C10: Código/SKU | D10: Descripción | E10: Cantidad Vendida | F10: Precio Venta Unitario | G10: Total Cobrado | H10: Método de Pago | I10: Costo de lo Vendido | J10: Ganancia Bruta | K10: Categoría (aux.)
A11: 46239 | B11: T-0001 | C11: CUA-010 | D11: =IF($C11="","",IFERROR(VLOOKUP($C11,'2_Control_de_Stock'!$A$11:$N$210,2,0),"⚠️ SKU no existe")) | E11: 12 | F11: =IF($C11="","",IFERROR(VLOOKUP($C11,'2_Control_de_Stock'!$A$11:$N$210,11,0),0)) | G11: =IF(OR($C11="",$E11=""),"",$E11*$F11) | H11: Efectivo | I11: =IF($C11="","",IFERROR($E11*VLOOKUP($C11,'2_Control_de_Stock'!$A$11:$N$210,10,0),0)) | J11: =IF($G11="","",$G11-$I11) | K11: =IF($C11="","",IFERROR(VLOOKUP($C11,'2_Control_de_Stock'!$A$11:$N$210,3,0),""))
A12: 46239 | B12: T-0002 | C12: KAW-101 | D12: =IF($C12="","",IFERROR(VLOOKUP($C12,'2_Control_de_Stock'!$A$11:$N$210,2,0),"⚠️ SKU no existe")) | E12: 8 | F12: =IF($C12="","",IFERROR(VLOOKUP($C12,'2_Control_de_Stock'!$A$11:$N$210,11,0),0)) | G12: =IF(OR($C12="",$E12=""),"",$E12*$F12) | H12: Yape/Plin | I12: =IF($C12="","",IFERROR($E12*VLOOKUP($C12,'2_Control_de_Stock'!$A$11:$N$210,10,0),0)) | J12: =IF($G12="","",$G12-$I12) | K12: =IF($C12="","",IFERROR(VLOOKUP($C12,'2_Control_de_Stock'!$A$11:$N$210,3,0),""))
A13: 46240 | B13: T-0003 | C13: ESC-401 | D13: =IF($C13="","",IFERROR(VLOOKUP($C13,'2_Control_de_Stock'!$A$11:$N$210,2,0),"⚠️ SKU no existe")) | E13: 5 | F13: =IF($C13="","",IFERROR(VLOOKUP($C13,'2_Control_de_Stock'!$A$11:$N$210,11,0),0)) | G13: =IF(OR($C13="",$E13=""),"",$E13*$F13) | H13: Tarjeta | I13: =IF($C13="","",IFERROR($E13*VLOOKUP($C13,'2_Control_de_Stock'!$A$11:$N$210,10,0),0)) | J13: =IF($G13="","",$G13-$I13) | K13: =IF($C13="","",IFERROR(VLOOKUP($C13,'2_Control_de_Stock'!$A$11:$N$210,3,0),""))
A14: 46240 | B14: T-0004 | C14: PAP-001 | D14: =IF($C14="","",IFERROR(VLOOKUP($C14,'2_Control_de_Stock'!$A$11:$N$210,2,0),"⚠️ SKU no existe")) | E14: 3 | F14: =IF($C14="","",IFERROR(VLOOKUP($C14,'2_Control_de_Stock'!$A$11:$N$210,11,0),0)) | G14: =IF(OR($C14="",$E14=""),"",$E14*$F14) | H14: Efectivo | I14: =IF($C14="","",IFERROR($E14*VLOOKUP($C14,'2_Control_de_Stock'!$A$11:$N$210,10,0),0)) | J14: =IF($G14="","",$G14-$I14) | K14: =IF($C14="","",IFERROR(VLOOKUP($C14,'2_Control_de_Stock'!$A$11:$N$210,3,0),""))
A15: 46241 | B15: T-0005 | C15: LIB-201 | D15: =IF($C15="","",IFERROR(VLOOKUP($C15,'2_Control_de_Stock'!$A$11:$N$210,2,0),"⚠️ SKU no existe")) | E15: 4 | F15: =IF($C15="","",IFERROR(VLOOKUP($C15,'2_Control_de_Stock'!$A$11:$N$210,11,0),0)) | G15: =IF(OR($C15="",$E15=""),"",$E15*$F15) | H15: Transferencia | I15: =IF($C15="","",IFERROR($E15*VLOOKUP($C15,'2_Control_de_Stock'!$A$11:$N$210,10,0),0)) | J15: =IF($G15="","",$G15-$I15) | K15: =IF($C15="","",IFERROR(VLOOKUP($C15,'2_Control_de_Stock'!$A$11:$N$210,3,0),""))
A16: 46242 | B16: T-0006 | C16: KAW-102 | D16: =IF($C16="","",IFERROR(VLOOKUP($C16,'2_Control_de_Stock'!$A$11:$N$210,2,0),"⚠️ SKU no existe")) | E16: 10 | F16: =IF($C16="","",IFERROR(VLOOKUP($C16,'2_Control_de_Stock'!$A$11:$N$210,11,0),0)) | G16: =IF(OR($C16="",$E16=""),"",$E16*$F16) | H16: Efectivo | I16: =IF($C16="","",IFERROR($E16*VLOOKUP($C16,'2_Control_de_Stock'!$A$11:$N$210,10,0),0)) | J16: =IF($G16="","",$G16-$I16) | K16: =IF($C16="","",IFERROR(VLOOKUP($C16,'2_Control_de_Stock'!$A$11:$N$210,3,0),""))
A17: 46243 | B17: T-0007 | C17: ART-301 | D17: =IF($C17="","",IFERROR(VLOOKUP($C17,'2_Control_de_Stock'!$A$11:$N$210,2,0),"⚠️ SKU no existe")) | E17: 6 | F17: =IF($C17="","",IFERROR(VLOOKUP($C17,'2_Control_de_Stock'!$A$11:$N$210,11,0),0)) | G17: =IF(OR($C17="",$E17=""),"",$E17*$F17) | H17: Yape/Plin | I17: =IF($C17="","",IFERROR($E17*VLOOKUP($C17,'2_Control_de_Stock'!$A$11:$N$210,10,0),0)) | J17: =IF($G17="","",$G17-$I17) | K17: =IF($C17="","",IFERROR(VLOOKUP($C17,'2_Control_de_Stock'!$A$11:$N$210,3,0),""))
A18: 46244 | B18: T-0008 | C18: MOC-501 | D18: =IF($C18="","",IFERROR(VLOOKUP($C18,'2_Control_de_Stock'!$A$11:$N$210,2,0),"⚠️ SKU no existe")) | E18: 2 | F18: =IF($C18="","",IFERROR(VLOOKUP($C18,'2_Control_de_Stock'!$A$11:$N$210,11,0),0)) | G18: =IF(OR($C18="",$E18=""),"",$E18*$F18) | H18: Tarjeta | I18: =IF($C18="","",IFERROR($E18*VLOOKUP($C18,'2_Control_de_Stock'!$A$11:$N$210,10,0),0)) | J18: =IF($G18="","",$G18-$I18) | K18: =IF($C18="","",IFERROR(VLOOKUP($C18,'2_Control_de_Stock'!$A$11:$N$210,3,0),""))
A19: 46245 | B19: T-0009 | C19: CUA-011 | D19: =IF($C19="","",IFERROR(VLOOKUP($C19,'2_Control_de_Stock'!$A$11:$N$210,2,0),"⚠️ SKU no existe")) | E19: 14 | F19: =IF($C19="","",IFERROR(VLOOKUP($C19,'2_Control_de_Stock'!$A$11:$N$210,11,0),0)) | G19: =IF(OR($C19="",$E19=""),"",$E19*$F19) | H19: Efectivo | I19: =IF($C19="","",IFERROR($E19*VLOOKUP($C19,'2_Control_de_Stock'!$A$11:$N$210,10,0),0)) | J19: =IF($G19="","",$G19-$I19) | K19: =IF($C19="","",IFERROR(VLOOKUP($C19,'2_Control_de_Stock'!$A$11:$N$210,3,0),""))
A20: 46246 | B20: T-0010 | C20: ESC-402 | D20: =IF($C20="","",IFERROR(VLOOKUP($C20,'2_Control_de_Stock'!$A$11:$N$210,2,0),"⚠️ SKU no existe")) | E20: 18 | F20: =IF($C20="","",IFERROR(VLOOKUP($C20,'2_Control_de_Stock'!$A$11:$N$210,11,0),0)) | G20: =IF(OR($C20="",$E20=""),"",$E20*$F20) | H20: Efectivo | I20: =IF($C20="","",IFERROR($E20*VLOOKUP($C20,'2_Control_de_Stock'!$A$11:$N$210,10,0),0)) | J20: =IF($G20="","",$G20-$I20) | K20: =IF($C20="","",IFERROR(VLOOKUP($C20,'2_Control_de_Stock'!$A$11:$N$210,3,0),""))
A21: 46247 | B21: T-0011 | C21: KAW-103 | D21: =IF($C21="","",IFERROR(VLOOKUP($C21,'2_Control_de_Stock'!$A$11:$N$210,2,0),"⚠️ SKU no existe")) | E21: 7 | F21: =IF($C21="","",IFERROR(VLOOKUP($C21,'2_Control_de_Stock'!$A$11:$N$210,11,0),0)) | G21: =IF(OR($C21="",$E21=""),"",$E21*$F21) | H21: Yape/Plin | I21: =IF($C21="","",IFERROR($E21*VLOOKUP($C21,'2_Control_de_Stock'!$A$11:$N$210,10,0),0)) | J21: =IF($G21="","",$G21-$I21) | K21: =IF($C21="","",IFERROR(VLOOKUP($C21,'2_Control_de_Stock'!$A$11:$N$210,3,0),""))
A22: 46248 | B22: T-0012 | C22: LIB-202 | D22: =IF($C22="","",IFERROR(VLOOKUP($C22,'2_Control_de_Stock'!$A$11:$N$210,2,0),"⚠️ SKU no existe")) | E22: 3 | F22: =IF($C22="","",IFERROR(VLOOKUP($C22,'2_Control_de_Stock'!$A$11:$N$210,11,0),0)) | G22: =IF(OR($C22="",$E22=""),"",$E22*$F22) | H22: Tarjeta | I22: =IF($C22="","",IFERROR($E22*VLOOKUP($C22,'2_Control_de_Stock'!$A$11:$N$210,10,0),0)) | J22: =IF($G22="","",$G22-$I22) | K22: =IF($C22="","",IFERROR(VLOOKUP($C22,'2_Control_de_Stock'!$A$11:$N$210,3,0),""))
... A40: 46265 | B40: T-0030 | C40: LIB-201 | D40: =IF($C40="","",IFERROR(VLOOKUP($C40,'2_Control_de_Stock'!$A$11:$N$210,2,0),"⚠️ SKU no existe")) | E40: 5 | F40: =IF($C40="","",IFERROR(VLOOKUP($C40,'2_Control_de_Stock'!$A$11:$N$210,11,0),0)) | G40: =IF(OR($C40="",$E40=""),"",$E40*$F40) | H40: Efectivo | I40: =IF($C40="","",IFERROR($E40*VLOOKUP($C40,'2_Control_de_Stock'!$A$11:$N$210,10,0),0)) | J40: =IF($G40="","",$G40-$I40) | K40: =IF($C40="","",IFERROR(VLOOKUP($C40,'2_Control_de_Stock'!$A$11:$N$210,3,0),""))
D41: =IF($C41="","",IFERROR(VLOOKUP($C41,'2_Control_de_Stock'!$A$11:$N$210,2,0),"⚠️ SKU no existe")) | F41: =IF($C41="","",IFERROR(VLOOKUP($C41,'2_Control_de_Stock'!$A$11:$N$210,11,0),0)) | G41: =IF(OR($C41="",$E41=""),"",$E41*$F41) | I41: =IF($C41="","",IFERROR($E41*VLOOKUP($C41,'2_Control_de_Stock'!$A$11:$N$210,10,0),0)) | J41: =IF($G41="","",$G41-$I41) | K41: =IF($C41="","",IFERROR(VLOOKUP($C41,'2_Control_de_Stock'!$A$11:$N$210,3,0),""))
D42: =IF($C42="","",IFERROR(VLOOKUP($C42,'2_Control_de_Stock'!$A$11:$N$210,2,0),"⚠️ SKU no existe")) | F42: =IF($C42="","",IFERROR(VLOOKUP($C42,'2_Control_de_Stock'!$A$11:$N$210,11,0),0)) | G42: =IF(OR($C42="",$E42=""),"",$E42*$F42) | I42: =IF($C42="","",IFERROR($E42*VLOOKUP($C42,'2_Control_de_Stock'!$A$11:$N$210,10,0),0)) | J42: =IF($G42="","",$G42-$I42) | K42: =IF($C42="","",IFERROR(VLOOKUP($C42,'2_Control_de_Stock'!$A$11:$N$210,3,0),""))
D43: =IF($C43="","",IFERROR(VLOOKUP($C43,'2_Control_de_Stock'!$A$11:$N$210,2,0),"⚠️ SKU no existe")) | F43: =IF($C43="","",IFERROR(VLOOKUP($C43,'2_Control_de_Stock'!$A$11:$N$210,11,0),0)) | G43: =IF(OR($C43="",$E43=""),"",$E43*$F43) | I43: =IF($C43="","",IFERROR($E43*VLOOKUP($C43,'2_Control_de_Stock'!$A$11:$N$210,10,0),0)) | J43: =IF($G43="","",$G43-$I43) | K43: =IF($C43="","",IFERROR(VLOOKUP($C43,'2_Control_de_Stock'!$A$11:$N$210,3,0),""))
D44: =IF($C44="","",IFERROR(VLOOKUP($C44,'2_Control_de_Stock'!$A$11:$N$210,2,0),"⚠️ SKU no existe")) | F44: =IF($C44="","",IFERROR(VLOOKUP($C44,'2_Control_de_Stock'!$A$11:$N$210,11,0),0)) | G44: =IF(OR($C44="",$E44=""),"",$E44*$F44) | I44: =IF($C44="","",IFERROR($E44*VLOOKUP($C44,'2_Control_de_Stock'!$A$11:$N$210,10,0),0)) | J44: =IF($G44="","",$G44-$I44) | K44: =IF($C44="","",IFERROR(VLOOKUP($C44,'2_Control_de_Stock'!$A$11:$N$210,3,0),""))
D45: =IF($C45="","",IFERROR(VLOOKUP($C45,'2_Control_de_Stock'!$A$11:$N$210,2,0),"⚠️ SKU no existe")) | F45: =IF($C45="","",IFERROR(VLOOKUP($C45,'2_Control_de_Stock'!$A$11:$N$210,11,0),0)) | G45: =IF(OR($C45="",$E45=""),"",$E45*$F45) | I45: =IF($C45="","",IFERROR($E45*VLOOKUP($C45,'2_Control_de_Stock'!$A$11:$N$210,10,0),0)) | J45: =IF($G45="","",$G45-$I45) | K45: =IF($C45="","",IFERROR(VLOOKUP($C45,'2_Control_de_Stock'!$A$11:$N$210,3,0),""))
D46: =IF($C46="","",IFERROR(VLOOKUP($C46,'2_Control_de_Stock'!$A$11:$N$210,2,0),"⚠️ SKU no existe")) | F46: =IF($C46="","",IFERROR(VLOOKUP($C46,'2_Control_de_Stock'!$A$11:$N$210,11,0),0)) | G46: =IF(OR($C46="",$E46=""),"",$E46*$F46) | I46: =IF($C46="","",IFERROR($E46*VLOOKUP($C46,'2_Control_de_Stock'!$A$11:$N$210,10,0),0)) | J46: =IF($G46="","",$G46-$I46) | K46: =IF($C46="","",IFERROR(VLOOKUP($C46,'2_Control_de_Stock'!$A$11:$N$210,3,0),""))
D47: =IF($C47="","",IFERROR(VLOOKUP($C47,'2_Control_de_Stock'!$A$11:$N$210,2,0),"⚠️ SKU no existe")) | F47: =IF($C47="","",IFERROR(VLOOKUP($C47,'2_Control_de_Stock'!$A$11:$N$210,11,0),0)) | G47: =IF(OR($C47="",$E47=""),"",$E47*$F47) | I47: =IF($C47="","",IFERROR($E47*VLOOKUP($C47,'2_Control_de_Stock'!$A$11:$N$210,10,0),0)) | J47: =IF($G47="","",$G47-$I47) | K47: =IF($C47="","",IFERROR(VLOOKUP($C47,'2_Control_de_Stock'!$A$11:$N$210,3,0),""))
D48: =IF($C48="","",IFERROR(VLOOKUP($C48,'2_Control_de_Stock'!$A$11:$N$210,2,0),"⚠️ SKU no existe")) | F48: =IF($C48="","",IFERROR(VLOOKUP($C48,'2_Control_de_Stock'!$A$11:$N$210,11,0),0)) | G48: =IF(OR($C48="",$E48=""),"",$E48*$F48) | I48: =IF($C48="","",IFERROR($E48*VLOOKUP($C48,'2_Control_de_Stock'!$A$11:$N$210,10,0),0)) | J48: =IF($G48="","",$G48-$I48) | K48: =IF($C48="","",IFERROR(VLOOKUP($C48,'2_Control_de_Stock'!$A$11:$N$210,3,0),""))
D49: =IF($C49="","",IFERROR(VLOOKUP($C49,'2_Control_de_Stock'!$A$11:$N$210,2,0),"⚠️ SKU no existe")) | F49: =IF($C49="","",IFERROR(VLOOKUP($C49,'2_Control_de_Stock'!$A$11:$N$210,11,0),0)) | G49: =IF(OR($C49="",$E49=""),"",$E49*$F49) | I49: =IF($C49="","",IFERROR($E49*VLOOKUP($C49,'2_Control_de_Stock'!$A$11:$N$210,10,0),0)) | J49: =IF($G49="","",$G49-$I49) | K49: =IF($C49="","",IFERROR(VLOOKUP($C49,'2_Control_de_Stock'!$A$11:$N$210,3,0),""))
D50: =IF($C50="","",IFERROR(VLOOKUP($C50,'2_Control_de_Stock'!$A$11:$N$210,2,0),"⚠️ SKU no existe")) | F50: =IF($C50="","",IFERROR(VLOOKUP($C50,'2_Control_de_Stock'!$A$11:$N$210,11,0),0)) | G50: =IF(OR($C50="",$E50=""),"",$E50*$F50) | I50: =IF($C50="","",IFERROR($E50*VLOOKUP($C50,'2_Control_de_Stock'!$A$11:$N$210,10,0),0)) | J50: =IF($G50="","",$G50-$I50) | K50: =IF($C50="","",IFERROR(VLOOKUP($C50,'2_Control_de_Stock'!$A$11:$N$210,3,0),""))
D51: =IF($C51="","",IFERROR(VLOOKUP($C51,'2_Control_de_Stock'!$A$11:$N$210,2,0),"⚠️ SKU no existe")) | F51: =IF($C51="","",IFERROR(VLOOKUP($C51,'2_Control_de_Stock'!$A$11:$N$210,11,0),0)) | G51: =IF(OR($C51="",$E51=""),"",$E51*$F51) | I51: =IF($C51="","",IFERROR($E51*VLOOKUP($C51,'2_Control_de_Stock'!$A$11:$N$210,10,0),0)) | J51: =IF($G51="","",$G51-$I51) | K51: =IF($C51="","",IFERROR(VLOOKUP($C51,'2_Control_de_Stock'!$A$11:$N$210,3,0),""))
D52: =IF($C52="","",IFERROR(VLOOKUP($C52,'2_Control_de_Stock'!$A$11:$N$210,2,0),"⚠️ SKU no existe")) | F52: =IF($C52="","",IFERROR(VLOOKUP($C52,'2_Control_de_Stock'!$A$11:$N$210,11,0),0)) | G52: =IF(OR($C52="",$E52=""),"",$E52*$F52) | I52: =IF($C52="","",IFERROR($E52*VLOOKUP($C52,'2_Control_de_Stock'!$A$11:$N$210,10,0),0)) | J52: =IF($G52="","",$G52-$I52) | K52: =IF($C52="","",IFERROR(VLOOKUP($C52,'2_Control_de_Stock'!$A$11:$N$210,3,0),""))
... D610: =IF($C610="","",IFERROR(VLOOKUP($C610,'2_Control_de_Stock'!$A$11:$N$210,2,0),"⚠️ SKU no existe")) | F610: =IF($C610="","",IFERROR(VLOOKUP($C610,'2_Control_de_Stock'!$A$11:$N$210,11,0),0)) | G610: =IF(OR($C610="",$E610=""),"",$E610*$F610) | I610: =IF($C610="","",IFERROR($E610*VLOOKUP($C610,'2_Control_de_Stock'!$A$11:$N$210,10,0),0)) | J610: =IF($G610="","",$G610-$I610) | K610: =IF($C610="","",IFERROR(VLOOKUP($C610,'2_Control_de_Stock'!$A$11:$N$210,3,0),""))

Sheet 4_Dashboard_DAMABIS
A1: DAMABIS ✨ Panel de Control Gerencial Librería y Útiles Escolares · Indicadores del mes seleccionado
P4: Rango calculado (auxiliar)
P5: =DATE($D$7,$D$6,1)
A6: 📅 PERIODO | C6: Mes | D6: 8 | E6: =CHOOSE($D$6,"ENERO","FEBRERO","MARZO","ABRIL","MAYO","JUNIO","JULIO","AGOSTO","SEPTIEMBRE","OCTUBRE","NOVIEMBRE","DICIEMBRE")&" "&$D$7 | P6: =EOMONTH($P$5,0)
C7: Año | D7: 2026
A9: 🛍️ VENTAS TOTALES DEL MES | D9: 💚 GANANCIA BRUTA DEL MES | G9: 💰 INVERSIÓN EN COMPRAS DEL MES | J9: 🏦 VALOR TOTAL DEL INVENTARIO | M9: 📈 MARGEN DEL MES
A10: =SUMIFS('3_Ventas_Diarias'!$G$11:$G$610,'3_Ventas_Diarias'!$A$11:$A$610,">="&$P$5,'3_Ventas_Diarias'!$A$11:$A$610,"<="&$P$6) | D10: =SUMIFS('3_Ventas_Diarias'!$J$11:$J$610,'3_Ventas_Diarias'!$A$11:$A$610,">="&$P$5,'3_Ventas_Diarias'!$A$11:$A$610,"<="&$P$6) | G10: =SUMIFS('1_Compras_e_Inventario_Inicial'!$I$11:$I$510,'1_Compras_e_Inventario_Inicial'!$A$11:$A$510,">="&$P$5,'1_Compras_e_Inventario_Inicial'!$A$11:$A$510,"<="&$P$6) | J10: =SUM('2_Control_de_Stock'!$L$11:$L$210) | M10: =IFERROR(SUMIFS('3_Ventas_Diarias'!$J$11:$J$610,'3_Ventas_Diarias'!$A$11:$A$610,">="&$P$5,'3_Ventas_Diarias'!$A$11:$A$610,"<="&$P$6)/SUMIFS('3_Ventas_Diarias'!$G$11:$G$610,'3_Ventas_Diarias'!$A$11:$A$610,">="&$P$5,'3_Ventas_Diarias'!$A$11:$A$610,"<="&$P$6),0)
A13: ⭐ PRODUCTO ESTRELLA DEL MES | D13: 🎟️ TICKETS DEL MES | G13: 📦 UNIDADES VENDIDAS EN EL MES | J13: 🚨 SKUs EN ALERTA | M13: 💳 % VENTAS EN EFECTIVO
A14: =IFERROR(INDEX('0_Listas_y_Apoyo'!$I$4:$I$203,MATCH(MAX('0_Listas_y_Apoyo'!$M$4:$M$203),'0_Listas_y_Apoyo'!$M$4:$M$203,0)),"Sin ventas") | D14: =SUMPRODUCT(('3_Ventas_Diarias'!$B$11:$B$610<>"")*('3_Ventas_Diarias'!$A$11:$A$610>=$P$5)*('3_Ventas_Diarias'!$A$11:$A$610<=$P$6)/COUNTIF('3_Ventas_Diarias'!$B$11:$B$610,'3_Ventas_Diarias'!$B$11:$B$610&"")) | G14: =SUMIFS('3_Ventas_Diarias'!$E$11:$E$610,'3_Ventas_Diarias'!$A$11:$A$610,">="&$P$5,'3_Ventas_Diarias'!$A$11:$A$610,"<="&$P$6) | J14: =COUNTIF('2_Control_de_Stock'!$I$11:$I$210,"*REPONER*")+COUNTIF('2_Control_de_Stock'!$I$11:$I$210,"*SIN STOCK*") | M14: =IFERROR(SUMIFS('3_Ventas_Diarias'!$G$11:$G$610,'3_Ventas_Diarias'!$H$11:$H$610,"Efectivo",'3_Ventas_Diarias'!$A$11:$A$610,">="&$P$5,'3_Ventas_Diarias'!$A$11:$A$610,"<="&$P$6)/SUMIFS('3_Ventas_Diarias'!$G$11:$G$610,'3_Ventas_Diarias'!$A$11:$A$610,">="&$P$5,'3_Ventas_Diarias'!$A$11:$A$610,"<="&$P$6),0)
A18: 📚 VENTAS POR CATEGORÍA | F18: 🏆 TOP 5 PRODUCTOS MÁS VENDIDOS DEL MES (por ingresos S/)
A19: Categoría | B19: Unidades | C19: Ingresos | D19: % Part. | F19: # | G19: Descripción | H19: SKU | I19: Unidades | J19: Ingresos
A20: ='0_Listas_y_Apoyo'!$A$4 | B20: =SUMIFS('3_Ventas_Diarias'!$E$11:$E$610,'3_Ventas_Diarias'!$K$11:$K$610,$A20,'3_Ventas_Diarias'!$A$11:$A$610,">="&$P$5,'3_Ventas_Diarias'!$A$11:$A$610,"<="&$P$6) | C20: =SUMIFS('3_Ventas_Diarias'!$G$11:$G$610,'3_Ventas_Diarias'!$K$11:$K$610,$A20,'3_Ventas_Diarias'!$A$11:$A$610,">="&$P$5,'3_Ventas_Diarias'!$A$11:$A$610,"<="&$P$6) | D20: =IFERROR($C20/SUM($C$20:$C$29),0) | F20: 1 | G20: =IFERROR(IF(LARGE('0_Listas_y_Apoyo'!$M$4:$M$203,1)<=0,"—",INDEX('0_Listas_y_Apoyo'!$I$4:$I$203,MATCH(LARGE('0_Listas_y_Apoyo'!$M$4:$M$203,1),'0_Listas_y_Apoyo'!$M$4:$M$203,0))),"—") | H20: =IFERROR(IF(LARGE('0_Listas_y_Apoyo'!$M$4:$M$203,1)<=0,"—",INDEX('0_Listas_y_Apoyo'!$H$4:$H$203,MATCH(LARGE('0_Listas_y_Apoyo'!$M$4:$M$203,1),'0_Listas_y_Apoyo'!$M$4:$M$203,0))),"—") | I20: =IFERROR(IF(LARGE('0_Listas_y_Apoyo'!$M$4:$M$203,1)<=0,0,INDEX('0_Listas_y_Apoyo'!$J$4:$J$203,MATCH(LARGE('0_Listas_y_Apoyo'!$M$4:$M$203,1),'0_Listas_y_Apoyo'!$M$4:$M$203,0))),0) | J20: =IFERROR(IF(LARGE('0_Listas_y_Apoyo'!$M$4:$M$203,1)<=0,0,INDEX('0_Listas_y_Apoyo'!$K$4:$K$203,MATCH(LARGE('0_Listas_y_Apoyo'!$M$4:$M$203,1),'0_Listas_y_Apoyo'!$M$4:$M$203,0))),0)
A21: ='0_Listas_y_Apoyo'!$A$5 | B21: =SUMIFS('3_Ventas_Diarias'!$E$11:$E$610,'3_Ventas_Diarias'!$K$11:$K$610,$A21,'3_Ventas_Diarias'!$A$11:$A$610,">="&$P$5,'3_Ventas_Diarias'!$A$11:$A$610,"<="&$P$6) | C21: =SUMIFS('3_Ventas_Diarias'!$G$11:$G$610,'3_Ventas_Diarias'!$K$11:$K$610,$A21,'3_Ventas_Diarias'!$A$11:$A$610,">="&$P$5,'3_Ventas_Diarias'!$A$11:$A$610,"<="&$P$6) | D21: =IFERROR($C21/SUM($C$20:$C$29),0) | F21: 2 | G21: =IFERROR(IF(LARGE('0_Listas_y_Apoyo'!$M$4:$M$203,2)<=0,"—",INDEX('0_Listas_y_Apoyo'!$I$4:$I$203,MATCH(LARGE('0_Listas_y_Apoyo'!$M$4:$M$203,2),'0_Listas_y_Apoyo'!$M$4:$M$203,0))),"—") | H21: =IFERROR(IF(LARGE('0_Listas_y_Apoyo'!$M$4:$M$203,2)<=0,"—",INDEX('0_Listas_y_Apoyo'!$H$4:$H$203,MATCH(LARGE('0_Listas_y_Apoyo'!$M$4:$M$203,2),'0_Listas_y_Apoyo'!$M$4:$M$203,0))),"—") | I21: =IFERROR(IF(LARGE('0_Listas_y_Apoyo'!$M$4:$M$203,2)<=0,0,INDEX('0_Listas_y_Apoyo'!$J$4:$J$203,MATCH(LARGE('0_Listas_y_Apoyo'!$M$4:$M$203,2),'0_Listas_y_Apoyo'!$M$4:$M$203,0))),0) | J21: =IFERROR(IF(LARGE('0_Listas_y_Apoyo'!$M$4:$M$203,2)<=0,0,INDEX('0_Listas_y_Apoyo'!$K$4:$K$203,MATCH(LARGE('0_Listas_y_Apoyo'!$M$4:$M$203,2),'0_Listas_y_Apoyo'!$M$4:$M$203,0))),0)
A22: ='0_Listas_y_Apoyo'!$A$6 | B22: =SUMIFS('3_Ventas_Diarias'!$E$11:$E$610,'3_Ventas_Diarias'!$K$11:$K$610,$A22,'3_Ventas_Diarias'!$A$11:$A$610,">="&$P$5,'3_Ventas_Diarias'!$A$11:$A$610,"<="&$P$6) | C22: =SUMIFS('3_Ventas_Diarias'!$G$11:$G$610,'3_Ventas_Diarias'!$K$11:$K$610,$A22,'3_Ventas_Diarias'!$A$11:$A$610,">="&$P$5,'3_Ventas_Diarias'!$A$11:$A$610,"<="&$P$6) | D22: =IFERROR($C22/SUM($C$20:$C$29),0) | F22: 3 | G22: =IFERROR(IF(LARGE('0_Listas_y_Apoyo'!$M$4:$M$203,3)<=0,"—",INDEX('0_Listas_y_Apoyo'!$I$4:$I$203,MATCH(LARGE('0_Listas_y_Apoyo'!$M$4:$M$203,3),'0_Listas_y_Apoyo'!$M$4:$M$203,0))),"—") | H22: =IFERROR(IF(LARGE('0_Listas_y_Apoyo'!$M$4:$M$203,3)<=0,"—",INDEX('0_Listas_y_Apoyo'!$H$4:$H$203,MATCH(LARGE('0_Listas_y_Apoyo'!$M$4:$M$203,3),'0_Listas_y_Apoyo'!$M$4:$M$203,0))),"—") | I22: =IFERROR(IF(LARGE('0_Listas_y_Apoyo'!$M$4:$M$203,3)<=0,0,INDEX('0_Listas_y_Apoyo'!$J$4:$J$203,MATCH(LARGE('0_Listas_y_Apoyo'!$M$4:$M$203,3),'0_Listas_y_Apoyo'!$M$4:$M$203,0))),0) | J22: =IFERROR(IF(LARGE('0_Listas_y_Apoyo'!$M$4:$M$203,3)<=0,0,INDEX('0_Listas_y_Apoyo'!$K$4:$K$203,MATCH(LARGE('0_Listas_y_Apoyo'!$M$4:$M$203,3),'0_Listas_y_Apoyo'!$M$4:$M$203,0))),0)
A23: ='0_Listas_y_Apoyo'!$A$7 | B23: =SUMIFS('3_Ventas_Diarias'!$E$11:$E$610,'3_Ventas_Diarias'!$K$11:$K$610,$A23,'3_Ventas_Diarias'!$A$11:$A$610,">="&$P$5,'3_Ventas_Diarias'!$A$11:$A$610,"<="&$P$6) | C23: =SUMIFS('3_Ventas_Diarias'!$G$11:$G$610,'3_Ventas_Diarias'!$K$11:$K$610,$A23,'3_Ventas_Diarias'!$A$11:$A$610,">="&$P$5,'3_Ventas_Diarias'!$A$11:$A$610,"<="&$P$6) | D23: =IFERROR($C23/SUM($C$20:$C$29),0) | F23: 4 | G23: =IFERROR(IF(LARGE('0_Listas_y_Apoyo'!$M$4:$M$203,4)<=0,"—",INDEX('0_Listas_y_Apoyo'!$I$4:$I$203,MATCH(LARGE('0_Listas_y_Apoyo'!$M$4:$M$203,4),'0_Listas_y_Apoyo'!$M$4:$M$203,0))),"—") | H23: =IFERROR(IF(LARGE('0_Listas_y_Apoyo'!$M$4:$M$203,4)<=0,"—",INDEX('0_Listas_y_Apoyo'!$H$4:$H$203,MATCH(LARGE('0_Listas_y_Apoyo'!$M$4:$M$203,4),'0_Listas_y_Apoyo'!$M$4:$M$203,0))),"—") | I23: =IFERROR(IF(LARGE('0_Listas_y_Apoyo'!$M$4:$M$203,4)<=0,0,INDEX('0_Listas_y_Apoyo'!$J$4:$J$203,MATCH(LARGE('0_Listas_y_Apoyo'!$M$4:$M$203,4),'0_Listas_y_Apoyo'!$M$4:$M$203,0))),0) | J23: =IFERROR(IF(LARGE('0_Listas_y_Apoyo'!$M$4:$M$203,4)<=0,0,INDEX('0_Listas_y_Apoyo'!$K$4:$K$203,MATCH(LARGE('0_Listas_y_Apoyo'!$M$4:$M$203,4),'0_Listas_y_Apoyo'!$M$4:$M$203,0))),0)
A24: ='0_Listas_y_Apoyo'!$A$8 | B24: =SUMIFS('3_Ventas_Diarias'!$E$11:$E$610,'3_Ventas_Diarias'!$K$11:$K$610,$A24,'3_Ventas_Diarias'!$A$11:$A$610,">="&$P$5,'3_Ventas_Diarias'!$A$11:$A$610,"<="&$P$6) | C24: =SUMIFS('3_Ventas_Diarias'!$G$11:$G$610,'3_Ventas_Diarias'!$K$11:$K$610,$A24,'3_Ventas_Diarias'!$A$11:$A$610,">="&$P$5,'3_Ventas_Diarias'!$A$11:$A$610,"<="&$P$6) | D24: =IFERROR($C24/SUM($C$20:$C$29),0) | F24: 5 | G24: =IFERROR(IF(LARGE('0_Listas_y_Apoyo'!$M$4:$M$203,5)<=0,"—",INDEX('0_Listas_y_Apoyo'!$I$4:$I$203,MATCH(LARGE('0_Listas_y_Apoyo'!$M$4:$M$203,5),'0_Listas_y_Apoyo'!$M$4:$M$203,0))),"—") | H24: =IFERROR(IF(LARGE('0_Listas_y_Apoyo'!$M$4:$M$203,5)<=0,"—",INDEX('0_Listas_y_Apoyo'!$H$4:$H$203,MATCH(LARGE('0_Listas_y_Apoyo'!$M$4:$M$203,5),'0_Listas_y_Apoyo'!$M$4:$M$203,0))),"—") | I24: =IFERROR(IF(LARGE('0_Listas_y_Apoyo'!$M$4:$M$203,5)<=0,0,INDEX('0_Listas_y_Apoyo'!$J$4:$J$203,MATCH(LARGE('0_Listas_y_Apoyo'!$M$4:$M$203,5),'0_Listas_y_Apoyo'!$M$4:$M$203,0))),0) | J24: =IFERROR(IF(LARGE('0_Listas_y_Apoyo'!$M$4:$M$203,5)<=0,0,INDEX('0_Listas_y_Apoyo'!$K$4:$K$203,MATCH(LARGE('0_Listas_y_Apoyo'!$M$4:$M$203,5),'0_Listas_y_Apoyo'!$M$4:$M$203,0))),0)
A25: ='0_Listas_y_Apoyo'!$A$9 | B25: =SUMIFS('3_Ventas_Diarias'!$E$11:$E$610,'3_Ventas_Diarias'!$K$11:$K$610,$A25,'3_Ventas_Diarias'!$A$11:$A$610,">="&$P$5,'3_Ventas_Diarias'!$A$11:$A$610,"<="&$P$6) | C25: =SUMIFS('3_Ventas_Diarias'!$G$11:$G$610,'3_Ventas_Diarias'!$K$11:$K$610,$A25,'3_Ventas_Diarias'!$A$11:$A$610,">="&$P$5,'3_Ventas_Diarias'!$A$11:$A$610,"<="&$P$6) | D25: =IFERROR($C25/SUM($C$20:$C$29),0)
A26: ='0_Listas_y_Apoyo'!$A$10 | B26: =SUMIFS('3_Ventas_Diarias'!$E$11:$E$610,'3_Ventas_Diarias'!$K$11:$K$610,$A26,'3_Ventas_Diarias'!$A$11:$A$610,">="&$P$5,'3_Ventas_Diarias'!$A$11:$A$610,"<="&$P$6) | C26: =SUMIFS('3_Ventas_Diarias'!$G$11:$G$610,'3_Ventas_Diarias'!$K$11:$K$610,$A26,'3_Ventas_Diarias'!$A$11:$A$610,">="&$P$5,'3_Ventas_Diarias'!$A$11:$A$610,"<="&$P$6) | D26: =IFERROR($C26/SUM($C$20:$C$29),0) | F26: 💳 VENTAS POR MÉTODO DE PAGO
A27: ='0_Listas_y_Apoyo'!$A$11 | B27: =SUMIFS('3_Ventas_Diarias'!$E$11:$E$610,'3_Ventas_Diarias'!$K$11:$K$610,$A27,'3_Ventas_Diarias'!$A$11:$A$610,">="&$P$5,'3_Ventas_Diarias'!$A$11:$A$610,"<="&$P$6) | C27: =SUMIFS('3_Ventas_Diarias'!$G$11:$G$610,'3_Ventas_Diarias'!$K$11:$K$610,$A27,'3_Ventas_Diarias'!$A$11:$A$610,">="&$P$5,'3_Ventas_Diarias'!$A$11:$A$610,"<="&$P$6) | D27: =IFERROR($C27/SUM($C$20:$C$29),0) | F27: Método | G27: Importe | H27: % Part.
A28: ='0_Listas_y_Apoyo'!$A$12 | B28: =SUMIFS('3_Ventas_Diarias'!$E$11:$E$610,'3_Ventas_Diarias'!$K$11:$K$610,$A28,'3_Ventas_Diarias'!$A$11:$A$610,">="&$P$5,'3_Ventas_Diarias'!$A$11:$A$610,"<="&$P$6) | C28: =SUMIFS('3_Ventas_Diarias'!$G$11:$G$610,'3_Ventas_Diarias'!$K$11:$K$610,$A28,'3_Ventas_Diarias'!$A$11:$A$610,">="&$P$5,'3_Ventas_Diarias'!$A$11:$A$610,"<="&$P$6) | D28: =IFERROR($C28/SUM($C$20:$C$29),0) | F28: ='0_Listas_y_Apoyo'!$B$4 | G28: =SUMIFS('3_Ventas_Diarias'!$G$11:$G$610,'3_Ventas_Diarias'!$H$11:$H$610,$F28,'3_Ventas_Diarias'!$A$11:$A$610,">="&$P$5,'3_Ventas_Diarias'!$A$11:$A$610,"<="&$P$6) | H28: =IFERROR($G28/SUM($G$28:$G$32),0)
A29: ='0_Listas_y_Apoyo'!$A$13 | B29: =SUMIFS('3_Ventas_Diarias'!$E$11:$E$610,'3_Ventas_Diarias'!$K$11:$K$610,$A29,'3_Ventas_Diarias'!$A$11:$A$610,">="&$P$5,'3_Ventas_Diarias'!$A$11:$A$610,"<="&$P$6) | C29: =SUMIFS('3_Ventas_Diarias'!$G$11:$G$610,'3_Ventas_Diarias'!$K$11:$K$610,$A29,'3_Ventas_Diarias'!$A$11:$A$610,">="&$P$5,'3_Ventas_Diarias'!$A$11:$A$610,"<="&$P$6) | D29: =IFERROR($C29/SUM($C$20:$C$29),0) | F29: ='0_Listas_y_Apoyo'!$B$5 | G29: =SUMIFS('3_Ventas_Diarias'!$G$11:$G$610,'3_Ventas_Diarias'!$H$11:$H$610,$F29,'3_Ventas_Diarias'!$A$11:$A$610,">="&$P$5,'3_Ventas_Diarias'!$A$11:$A$610,"<="&$P$6) | H29: =IFERROR($G29/SUM($G$28:$G$32),0)
A30: TOTAL | B30: =SUM($B$20:$B$29) | C30: =SUM($C$20:$C$29) | D30: =IFERROR($C30/$C30,0) | F30: ='0_Listas_y_Apoyo'!$B$6 | G30: =SUMIFS('3_Ventas_Diarias'!$G$11:$G$610,'3_Ventas_Diarias'!$H$11:$H$610,$F30,'3_Ventas_Diarias'!$A$11:$A$610,">="&$P$5,'3_Ventas_Diarias'!$A$11:$A$610,"<="&$P$6) | H30: =IFERROR($G30/SUM($G$28:$G$32),0)
F31: ='0_Listas_y_Apoyo'!$B$7 | G31: =SUMIFS('3_Ventas_Diarias'!$G$11:$G$610,'3_Ventas_Diarias'!$H$11:$H$610,$F31,'3_Ventas_Diarias'!$A$11:$A$610,">="&$P$5,'3_Ventas_Diarias'!$A$11:$A$610,"<="&$P$6) | H31: =IFERROR($G31/SUM($G$28:$G$32),0)
F32: ='0_Listas_y_Apoyo'!$B$8 | G32: =SUMIFS('3_Ventas_Diarias'!$G$11:$G$610,'3_Ventas_Diarias'!$H$11:$H$610,$F32,'3_Ventas_Diarias'!$A$11:$A$610,">="&$P$5,'3_Ventas_Diarias'!$A$11:$A$610,"<="&$P$6) | H32: =IFERROR($G32/SUM($G$28:$G$32),0)
A51: ℹ️ Cambia el Mes (D6) y el Año (D7) — celdas amarillas — y todo el panel se recalcula. Fuente de datos: hojas 1, 2 y 3. Moneda: Soles (S/).
